Workbook

Sheet Dashboard
B2: Financial Dashboard
B4: Year | C4: =Principal!C3 -> 2003 | D4: =Principal!D3 -> 2004 | E4: =Principal!E3 -> 2005 | F4: =Principal!F3 -> 2006 | G4: =Principal!G3 -> 2007 | H4: =Principal!H3 -> 2008 | I4: =Principal!I3 -> 2009 | J4: =Principal!J3 -> 2010 | ... AA4: =Principal!AA3 -> 2027
B5: Total Income | C5: =Principal!C13 -> 25595 | D5: =Principal!D13 -> 29655 | E5: =Principal!E13 -> 38875 | F5: =Principal!F13 -> 34850 | G5: =Principal!G13 -> 26575 | H5: =Principal!H13 -> 26700 | I5: =Principal!I13 -> 56950 | J5: =Principal!J13 -> 41080 | ... AA5: =Principal!AA13 -> 0
B6: Total Expenses | C6: =Principal!C51 -> 21996 | D6: =Principal!D51 -> 19294 | E6: =Principal!E51 -> 27015 | F6: =Principal!F51 -> 23585 | G6: =Principal!G51 -> 23200 | H6: =Principal!H51 -> 29780 | I6: =Principal!I51 -> 44265 | J6: =Principal!J51 -> 39830 | ... AA6: =Principal!AA51 -> 0
B7: Net Savings | C7: =Principal!C58 -> 716 | D7: =Principal!D58 -> 6158 | E7: =Principal!E58 -> 11033 | F7: =Principal!F58 -> 10435 | G7: =Principal!G58 -> 2825 | H7: =Principal!H58 -> -5940 | I7: =Principal!I58 -> 10935 | J7: =Principal!J58 -> 1250 | ... AA7: =Principal!AA58 -> 0
B9: Savings Margin (%) | C9: =IF(C5=0, 0, C7/C5) -> 0.027974214 | D9: =IF(D5=0, 0, D7/D5) -> 0.2076547 | E9: =IF(E5=0, 0, E7/E5) -> 0.28380707 | F9: =IF(F5=0, 0, F7/F5) -> 0.29942611 | G9: =IF(G5=0, 0, G7/G5) -> 0.10630292 | H9: =IF(H5=0, 0, H7/H5) -> -0.22247191 | I9: =IF(I5=0, 0, I7/I5) -> 0.19201054 | J9: =IF(J5=0, 0, J7/J5) -> 0.030428432 | ... AA9: =IF(AA5=0, 0, AA7/AA5) -> 0

Sheet Info
B2: FINANZAS DOMÉSTICAS 2002 - 2026
AD8: =COUNTA(D9:AC9) -> 25 | AE8: Años
D9: 2002 | E9: 2003 | F9: 2004 | G9: 2005 | H9: 2006 | I9: 2007 | J9: 2008 | K9: 2009 | L9: 2010 | M9: 2011 | N9: 2012 | O9: 2013 | P9: 2014 | Q9: 2015 | R9: 2016 | S9: 2017 | T9: 2018 | U9: 2019 | V9: 2020 | W9: 2021 | X9: 2022 | Y9: 2023 | Z9: 2024 | AA9: 2025 | AB9: 2026 | AD9: TOTALES
D10: 14990 | E10: 25595 | F10: 29655 | G10: 38875 | H10: 34850 | I10: 26500 | J10: 26700 | K10: 56550 | L10: 41080 | M10: 19720 | N10: 24700 | O10: 25875 | P10: 27865 | Q10: 29035 | R10: 31595 | S10: 31265 | T10: 31760 | U10: 31575 | V10: 32245 | W10: 35815 | X10: 37330 | Y10: 37980 | Z10: 44150 | AA10: 46200 | AC10: Ingresos | AD10: =SUM(D10:AA10) -> 781905 | AE10: (netos)
D11: 11525 | E11: 24880 | F11: 23500 | G11: 27850 | H11: 23800 | I11: 23500 | J11: 32650 | K11: 46550 | L11: 39850 | M11: 26570 | N11: 29500 | O11: 30150 | P11: 33090 | Q11: 24190 | R11: 36075 | S11: 27750 | T11: 34135 | U11: 29070 | V11: 27695 | W11: 31025 | X11: 38670 | Y11: 46435 | Z11: 48705 | AA11: 48600 | AC11: Gastos | AD11: =SUM(D11:AA11) -> 765765
D13: =D10-D11 -> 3465 | E13: =E10-E11 -> 715 | F13: =F10-F11 -> 6155 | G13: =G10-G11 -> 11025 | H13: =H10-H11 -> 11050 | I13: =I10-I11 -> 3000 | J13: =J10-J11 -> -5950 | K13: =K10-K11 -> 10000 | ... AA13: =AA10-AA11 -> -2400 | AC13: Resto | AD13: =SUM(D13:AA13) -> 16140
D15: SVS | E15: SVS | F15: SVS | G15: Trak | H15: Olivia | I15: MIPS | J15: MIPS | K15: MIPS | L15: Novartis
F16: Trak | G16: Olivia | H16: MIPS | K16: Novartis | L16: Nexus
D37: 2022 | E37: 2023 | G37: 2023 | H37: 2024 | J37: 2024 | K37: 2025 | M37: 2025 | N37: 2026 | P37: 2026 | Q37: 2027
D38: Sept | E38: Ene | G38: Sept | H38: Ene | J38: Sept | K38: Ene | M38: Sept | N38: Ene | P38: Sept | Q38: Ene
C39: Cuenta Corriente | D39: 46000 | E39: 47000 | F39: =E39/$E$46 -> 0.68814056 | G39: 40000 | H39: 39450 | I39: =H39/$H$46 -> 0.5571247 | J39: 36700 | K39: 35575 | L39: =K39/$K$46 -> 0.45530172 | M39: 35710 | N39: 31200 | O39: =N39/$N$46 -> 0.3604228
C40: Cuenta BBVA | D40: 1600 | E40: 650 | F40: =E40/$E$46 -> 0.0095168375 | G40: 405 | H40: 395 | I40: =H40/$H$46 -> 0.0055783081 | J40: 540 | K40: 750 | L40: =K40/$K$46 -> 0.0095987714 | M40: 445 | N40: 500 | O40: =N40/$N$46 -> 0.0057760065
C41: ETFs y acciones(*) | D41: 1000 | E41: 2000 | F41: =E41/$E$46 -> 0.029282577 | G41: 6150 | H41: 8130 | I41: =H41/$H$46 -> 0.11481429 | J41: 11385 | K41: 12575 | L41: =K41/$K$46 -> 0.1609394 | M41: =M48+M49 -> 17915 | N41: 20430 | O41: =N41/$N$46 -> 0.23600762 | R41: (DeGiro + BrokerNow)
C42: Fondo BBVA | D42: 1500 | E42: 2700 | F42: =E42/$E$46 -> 0.039531479 | G42: 3585 | H42: 4195 | I42: =H42/$H$46 -> 0.059243045 | J42: 5315 | K42: 5500 | L42: =K42/$K$46 -> 0.07039099 | M42: 6400 | N42: 6900 | O42: =N42/$N$46 -> 0.079708889 | R42: (BBVA Futuro Sostenible ISR FI)
C43: PP La Caixa | D43: 15650 | E43: 14500 | F43: =E43/$E$46 -> 0.21229868 | G43: 15950 | H43: 16000 | I43: =H43/$H$46 -> 0.22595679 | J43: 18150 | K43: 19125 | L43: =K43/$K$46 -> 0.24476867 | M43: 19050 | N43: 20150 | O43: =N43/$N$46 -> 0.23277306 | R43: (CABK Tendencias Renta Variable)
C44: PPE Santander | D44: 925 | E44: 1450 | F44: =E44/$E$46 -> 0.021229868 | G44: 2140 | H44: 2640 | I44: =H44/$H$46 -> 0.03728287 | J44: 3985 | K44: 4610 | L44: =K44/$K$46 -> 0.059000448 | M44: 5900 | N44: 7385 | O44: =N44/$N$46 -> 0.085311616
C46: TOTAL | D46: =SUM(D39:D45) -> 66675 | E46: =SUM(E39:E45) -> 68300 | G46: =SUM(G39:G45) -> 68230 | H46: =SUM(H39:H45) -> 70810 | J46: =SUM(J39:J45) -> 76075 | K46: =SUM(K39:K45) -> 78135 | M46: =SUM(M39:M45) -> 85420 | N46: =SUM(N39:N45) -> 86565
D48: (*) | E48: DeGiro, BrokerNow | L48: BrokerNow | M48: 5810 | N48: 7215
L49: DeGiro | M49: 12105 | N49: 13215

Sheet Historico
C4: Ahorro | D4: CC | E4: Total
B5: 39873 | C5: 21350 | D5: 17700 | E5: =C5+D5 -> 39050
B6: 39965 | C6: 21450 | D6: 9700 | E6: =C6+D6 -> 31150 | F6: minimo
B7: 40026 | C7: 21450 | D7: 22200 | E7: =C7+D7 -> 43650
B8: 40118 | C8: 21450 | D8: 22500 | E8: =C8+D8 -> 43950
B9: 40210 | C9: 21450 | D9: 27800 | E9: =C9+D9 -> 49250
B10: 40269 | C10: 21450 | D10: 29700 | E10: =C10+D10 -> 51150
B11: 40330 | C11: 21450 | D11: 30700 | E11: =C11+D11 -> 52150
B12: 40422 | C12: 21450 | D12: 30600 | E12: =C12+D12 -> 52050
B13: 40513 | C13: 21460 | D13: 30600 | E13: =C13+D13 -> 52060
B14: 40603 | C14: 21470 | D14: 27600 | E14: =C14+D14 -> 49070
B15: 40695 | C15: 21470 | D15: 25000 | E15: =C15+D15 -> 46470
B16: 40787 | C16: 21475 | D16: 24000 | E16: =C16+D16 -> 45475
B17: 40878 | C17: 21475 | D17: 23000 | E17: =C17+D17 -> 44475
B18: 40969 | C18: 21480 | D18: 18000 | E18: =C18+D18 -> 39480
... B36: 42614 | C36: 14500 | D36: 17500 | E36: =C36+D36 -> 32000
B37: 42705 | C37: 12225 | D37: 25000 | E37: =C37+D37 -> 37225 | G37: A partir de 2016 Ahorro = SIAL + Plazo Fijo + Plan Pensiones
B38: 42795 | C38: 12350 | D38: 25000 | E38: =C38+D38 -> 37350 | N38: A partir del 2016 Ahorro = SIAL + Deposito + PlanJubilacion
B39: 42887 | C39: 13225 | D39: 27000 | E39: =C39+D39 -> 40225
B40: 42979 | C40: 13750 | D40: 27500 | E40: =C40+D40 -> 41250 | Y40: Años
B41: 43070 | C41: 14000 | D41: 29000 | E41: =C41+D41 -> 43000 | I41: 2025 | J41: 2024 | K41: 2023 | L41: 2022 | M41: 2021 | N41: 2020 | O41: 2019 | P41: 2018 | Q41: 2017 | R41: 2016 | S41: 2015 | T41: 2014 | U41: 2013 | V41: 2012 | W41: 2011 | Y41: =COUNTA(I41:X41) -> 15
B42: 43160 | C42: 16250 | D42: 26000 | E42: =C42+D42 -> 42250
B43: 43252 | C43: 16750 | D43: 28000 | E43: =C43+D43 -> 44750 | X43: TOTALES
B44: 43344 | C44: 17000 | D44: 28000 | E44: =C44+D44 -> 45000 | G44: Total Ingresos | J44: 44150 | K44: 37980 | L44: 37330 | M44: 35815 | N44: 32245 | O44: 31575 | P44: 31760 | Q44: 31130 | R44: 31625 | S44: 29035 | T44: 26300 | U44: 25875 | V44: 25750 | W44: 19720 | X44: =SUM(I44:W44) -> 440290 | Y44: TOTAL
B45: 43435 | C45: 19250 | D45: 25000 | E45: =C45+D45 -> 44250 | H45: Hacienda | L45: 575
B46: 43466 | C46: 19600 | D46: 24100 | E46: =C46+D46 -> 43700 | G46: Ahorro e Inversion | J46: 3048 | K46: 4345 | X46: =SUM(I46:W46) -> 7393
B47: 43525 | C47: 20200 | D47: 22500 | E47: =C47+D47 -> 42700 | G47: Automovil
B48: 43586 | C48: 21000 | D48: 23000 | E48: =C48+D48 -> 44000 | H48: Compra/Renting | J48: 2650 | K48: 11360 | L48: 400 | M48: 2350 | N48: 2175 | O48: 3450 | P48: 0 | Q48: 0 | R48: 10600 | S48: 0 | T48: 0 | U48: 9300 | V48: 0 | W48: 0 | X48: =SUM(I48:W48) -> 42285 | Y48: COCHE
B49: 43647 | C49: 21100 | D49: 25500 | E49: =C49+D49 -> 46600 | H49: Combustible | J49: 370 | K49: 220 | L49: 175 | M49: 60 | N49: 245 | O49: 950 | P49: 900 | Q49: 1075 | R49: 950 | S49: 1000 | T49: 950 | U49: 1450 | V49: 1430 | W49: 650 | X49: =SUM(I49:W49) -> 10425
B50: 43709 | C50: 21500 | D50: 24500 | E50: =C50+D50 -> 46000 | H50: Impuestos | J50: 70 | K50: 290 | L50: 70 | M50: 150 | N50: 70 | O50: 70 | P50: 70 | Q50: 70 | R50: 125 | S50: 70 | T50: 70 | U50: 70 | V50: 90 | W50: 70 | X50: =SUM(I50:W50) -> 1355
B51: 43770 | C51: 22100 | D51: 25500 | E51: =C51+D51 -> 47600 | H51: Mantenimiento | J51: 15 | K51: 20 | L51: 30 | M51: 165 | N51: 0 | O51: 155 | P51: 525 | Q51: 165 | R51: 0 | S51: 255 | T51: 270 | U51: 85 | V51: 360 | W51: 100 | X51: =SUM(I51:W51) -> 2145
B52: 43800 | C52: 22200 | D52: 28000 | E52: =C52+D52 -> 50200 | H52: Parking,Peajes | J52: 0 | K52: 35 | L52: 45 | M52: 0 | N52: 75 | O52: 100 | P52: 300 | Q52: 160 | R52: 150 | S52: 50 | T52: 220 | U52: 70 | V52: 50 | W52: 25 | X52: =SUM(I52:W52) -> 1280
B53: 43831 | C53: 22650 | D53: 27000 | E53: =C53+D53 -> 49650 | G53: Dietas | J53: 5475 | K53: 4550 | L53: 3840 | M53: 3655 | N53: 2925 | O53: 2150 | P53: 1770 | Q53: 2475 | R53: 1815 | S53: 1425 | T53: 1275 | U53: 1100 | V53: 1665 | W53: 2700 | X53: =SUM(I53:W53) -> 36820 | Y53: SUPER
B54: 43891 | C54: 22650 | D54: 26500 | E54: =C54+D54 -> 49150 | G54: Gimnasios y ropa dep | J54: 685 | K54: 450 | L54: 285 | M54: 205 | N54: 335 | O54: 375 | P54: 300 | Q54: 325 | R54: 375 | S54: 350 | T54: 875 | U54: 605 | V54: 775 | W54: 625 | X54: =SUM(I54:W54) -> 6565 | Y54: DEPORTE
B55: 43952 | C55: 22500 | D55: 28500 | E55: =C55+D55 -> 51000 | H55: Libros, colecciones, papeleria | K55: 5 | L55: 5 | M55: 280 | N55: 280 | O55: 615 | P55: 600 | Q55: 725 | R55: 675 | S55: 325 | T55: 555 | U55: 110 | V55: 210 | W55: 1000 | X55: =SUM(I55:W55) -> 5385
B56: 44013 | C56: 23000 | D56: 28500 | E56: =C56+D56 -> 51500 | G56: Agua, Luz, Gas | J56: 1245 | K56: 1095 | L56: 1195 | M56: 1345 | N56: 1360 | O56: 1350 | P56: 1200 | Q56: 1150 | R56: 1475 | S56: 250 | T56: 1125 | U56: 900 | V56: 900 | W56: 860 | X56: =SUM(I56:W56) -> 15450 | Y56: AGUA LUZ GAS
B57: 44075 | C57: 24000 | D57: 29000 | E57: =C57+D57 -> 53000 | G57: Telefonía | J57: 470 | K57: 465 | L57: 420 | M57: 420 | N57: 410 | O57: 370 | P57: 575 | Q57: 525 | R57: 300 | S57: 775 | T57: 575 | U57: 610 | V57: 855 | W57: 1270 | X57: =SUM(I57:W57) -> 8040 | Y57: TELECO
B58: 44105 | C58: 23850 | D58: 31500 | E58: =C58+D58 -> 55350 | G58: Alquiler | J58: 10740 | K58: 10440 | L58: 9940 | M58: 9840 | N58: 9675 | O58: 9840 | P58: 9550 | Q58: 9125 | R58: 8900 | S58: 8900 | T58: 11225 | U58: 8650 | V58: 12000 | W58: 8570 | X58: =SUM(I58:W58) -> 137395 | Y58: ALQUILER
B59: 44166 | C59: 24750 | D59: 32500 | E59: =C59+D59 -> 57250 | G59: Hogar y vestuario | J59: 2280 | K59: 5 | L59: 385 | M59: 1970 | N59: 320 | O59: 475 | P59: 450 | Q59: 275 | R59: 1550 | S59: 575 | T59: 4000 | U59: 600 | V59: 4800 | W59: 700 | X59: =SUM(I59:W59) -> 18385 | Y59: HOGAR
B60: 44197 | C60: 26000 | D60: 36000 | E60: =C60+D60 -> 62000 | G60: Niños | J60: 875 | K60: 2445 | L60: 2845 | M60: 2780 | N60: 800 | O60: 1425 | P60: 1650 | Q60: 975 | R60: 1015 | S60: 500 | T60: 400 | U60: 250 | X60: =SUM(I60:W60) -> 15960 | Y60: NIÑOS
B61: 44256 | C61: 26025 | D61: 37000 | E61: =C61+D61 -> 63025 | G61: Impuestos | J61: -70 | K61: 35 | L61: -575 | M61: 210 | N61: 105 | O61: 0 | P61: 0 | Q61: 0 | R61: 0 | S61: 100 | T61: 4500 | U61: 260 | V61: 750 | W61: 1900 | X61: =SUM(I61:W61) -> 7215 | Y61: IMPUESTOS
B62: 44317 | C62: 16400 | D62: 49000 | E62: =C62+D62 -> 65400 | G62: Loteria | J62: 730 | K62: 670 | L62: 800 | M62: 600 | N62: 580 | O62: 725 | P62: 1025 | Q62: 825 | R62: 575 | S62: 415 | T62: 725 | U62: 475 | V62: 560 | W62: 425 | X62: =SUM(I62:W62) -> 9130 | Y62: LOTERIA
B63: 44378 | C63: 16375 | D63: 50000 | E63: =C63+D63 -> 66375 | G63: Ocio
B64: 44440 | C64: 17150 | D64: 48000 | E64: =C64+D64 -> 65150 | H64: General | J64: 1420 | K64: 1685 | L64: 1950 | M64: 910 | N64: 720 | O64: 1700 | P64: 1175 | Q64: 1455 | R64: 1150 | S64: 1000 | T64: 1400 | U64: 1800 | V64: 2115 | W64: 1850 | X64: =SUM(I64:W64) -> 20330 | Y64: OCIO
B65: 44470 | C65: 17000 | D65: 49000 | E65: =C65+D65 -> 66000 | H65: Otros | J65: 890 | K65: 255 | L65: 625 | M65: 430 | N65: 180 | O65: 900 | P65: 1125 | Q65: 1000 | R65: 700 | S65: 250 | T65: 300 | U65: 200 | V65: 180 | W65: 1410 | X65: =SUM(I65:W65) -> 8445 | Y65: OCIO2
B66: 44531 | C66: 17250 | D66: 47350 | E66: =C66+D66 -> 64600 | G66: Regalos | J66: 315 | K66: 1220 | L66: 695 | M66: 445 | N66: 1280 | O66: 1000 | P66: 550 | Q66: 1075 | R66: 1025 | S66: 1175 | T66: 300 | U66: 850 | V66: 950 | W66: 1450 | X66: =SUM(I66:W66) -> 12330 | Y66: REGALOS
B67: 44562 | C67: 18115 | D67: 48000 | E67: =C67+D67 -> 66115 | G67: Salud y cosmetica | J67: 5785 | K67: 215 | L67: 150 | M67: 170 | N67: 750 | O67: 125 | P67: 175 | Q67: 135 | R67: 75 | S67: 500 | T67: 115 | U67: 625 | V67: 215 | W67: 100 | X67: =SUM(I67:W67) -> 9135 | Y67: SALUD
B68: 44621 | C68: 16450 | D68: 41750 | E68: =C68+D68 -> 58200 | G68: Seguros | J68: 880 | K68: 430 | L68: 385 | M68: 355 | N68: 385 | O68: 395 | P68: 900 | Q68: 875 | R68: 850 | S68: 775 | T68: 745 | U68: 805 | V68: 755 | W68: 725 | X68: =SUM(I68:W68) -> 9260 | Y68: SEGUROS
B69: 44682 | C69: 15000 | D69: 50000 | E69: =C69+D69 -> 65000 | G69: Gastos trabajo | J69: 0 | K69: 0 | L69: 0 | M69: 10 | N69: 0 | O69: 70 | P69: 0 | Q69: 65 | R69: 325 | S69: 300 | T69: 350 | U69: 0 | V69: 0 | W69: 0 | X69: =SUM(I69:W69) -> 1120
B70: 44743 | C70: 15000 | D70: 50700 | E70: =C70+D70 -> 65700 | G70: Tecnología | J70: 2865 | K70: 10 | L70: 3855 | M70: 1770 | N70: 1660 | O70: 750 | P70: 3850 | Q70: 1800 | R70: 300 | S70: 2300 | T70: 0 | U70: 300 | V70: 475 | W70: 150 | X70: =SUM(I70:W70) -> 20085 | Y70: TECNOLOGIA
B71: 44805 | C71: 18200 | D71: 46000 | E71: =C71+D71 -> 64200 | H71: Planes de ahorro y transferencias | J71: 2950 | K71: 2600 | L71: 7300 | M71: 120 | N71: 1110 | O71: 320 | P71: 2350 | Q71: 1115 | R71: 350 | S71: 160 | T71: 160 | U71: 180 | V71: 170 | W71: 475 | X71: =SUM(I71:W71) -> 19360 | Y71: TRANSFERENCIA
B72: 44835 | C72: 18050 | D72: 47000 | E72: =C72+D72 -> 65050 | G72: Transporte | J72: 270 | K72: 25 | L72: 65 | M72: 0 | N72: 40 | O72: 20 | P72: 15 | Q72: 50 | R72: 50 | S72: 50 | T72: 150 | U72: 55 | V72: 180 | W72: 600 | X72: =SUM(I72:W72) -> 1570 | Y72: TRANSPORTE
B73: 44896 | C73: 20325 | D73: 46000 | E73: =C73+D73 -> 66325 | G73: Viajes y vacaciones | J73: 4610 | K73: 3565 | L73: 3215 | M73: 2785 | N73: 2175 | O73: 1800 | P73: 4425 | Q73: 2100 | R73: 2475 | S73: 1150 | T73: 0 | U73: 780 | V73: 1600 | W73: 1100 | X73: =SUM(I73:W73) -> 31780 | Y73: VACACIONES
B74: 44927 | C74: 20875 | D74: 47000 | E74: =C74+D74 -> 67875
B75: 44986 | C75: 22300 | D75: 37700 | E75: =C75+D75 -> 60000 | G75: TOTAL Gastos | J75: =SUM(J46:J73) -> 48568 | K75: =SUM(K46:K73) -> 46435 | L75: =SUM(L47:L73) -> 38100 | M75: =SUM(M47:M73) -> 31025 | N75: =SUM(N47:N73) -> 27655 | O75: =SUM(O47:O73) -> 29130 | P75: =SUM(P47:P73) -> 33480 | Q75: =SUM(Q47:Q73) -> 27540 | R75: =SUM(R47:R73) -> 35805 | S75: =SUM(S47:S73) -> 22650 | ... W75: =SUM(W47:W73) -> 26755 | X75: =SUM(I75:W75) -> 458643 | Y75: TOTAL
B76: 45047 | C76: 24175 | D76: 42000 | E76: =C76+D76 -> 66175
B77: 45108 | C77: 25710 | D77: 41750 | E77: =C77+D77 -> 67460
B78: 45170 | C78: 27815 | D78: 40405 | E78: =C78+D78 -> 68220
B79: 45261 | C79: 29600 | D79: 39500 | E79: =C79+D79 -> 69100
B80: 45292 | C80: 30960 | D80: 39850 | E80: =C80+D80 -> 70810 | G80: Promedios mensuales | J80: 2024 | K80: 2023 | L80: 2017 | M80: 2016 | N80: 2015 | O80: 2014 | P80: 2013 | Q80: 2012 | R80: 2011 | S80: 2010 | T80: 2009 | U80: 2008 | V80: 2007 | W80: 2006
B81: 45352 | C81: 32700 | D81: 37425 | E81: =C81+D81 -> 70125
B82: 45413 | C82: 34615 | D82: 40500 | E82: =C82+D82 -> 75115 | I82: Salario | K82: 3165 | L82: 2594.1667 | M82: 1914.1667 | N82: 2419.5833 | O82: 2202.0833 | P82: 1996.6667 | Q82: 1717.9167 | R82: 1414.1667 | S82: 3360.8333 | T82: 3010.4167 | U82: 2050 | V82: 2000 | W82: 1670.8333
B83: 45566 | C83: 38835 | D83: 37240 | E83: =C83+D83 -> 76075 | I83: Salario (Pagas extraordinarias) | J83: 0 | K83: 0 | L83: 0 | M83: 667.08333 | N83: 0 | O83: 0 | P83: 152.08333 | Q83: 292.5 | R83: 229.16667 | S83: 0 | T83: 1735.4167 | U83: 175 | V83: 214.58333 | W83: 150
B84: 45658 | C84: 41810 | D84: 36325 | E84: =C84+D84 -> 78135 | I84: Otros ingresos | J84: 0 | K84: 0 | L84: 11.25 | M84: 51.666667 | N84: 0 | O84: 120 | P84: 7.5 | Q84: 60 | R84: 0 | S84: 62.5 | T84: 0 | U84: 0 | V84: 0 | W84: 1083.3333
B85: 45717 | C85: 42810 | D85: 34295 | E85: =C85+D85 -> 77105 | I85: Reajuste del saldo | J85: 0 | K85: 0 | L85: 0 | M85: 0 | N85: 0 | O85: 0 | P85: 0 | Q85: 0 | R85: 0 | S85: 0 | T85: 0 | U85: 0 | V85: 0 | W85: 0
B86: 45778 | C86: 43250 | D86: 40425 | E86: =C86+D86 -> 83675 | I86: Ingresos de origen familiar | J86: 0 | K86: 0 | L86: 0 | M86: 0 | N86: 0 | O86: 0 | P86: 0 | Q86: 0 | R86: 0 | S86: 0 | T86: 0 | U86: 0 | V86: 0 | W86: 0
B87: 45931 | C87: 51330 | D87: 34625 | E87: =C87+D87 -> 85955 | I87: Varios | J87: 0 | K87: 0 | L87: 0 | M87: 0 | N87: 0 | O87: 0 | P87: 0 | Q87: 0 | R87: 0 | S87: 0 | T87: 0 | U87: 0 | V87: 0 | W87: 0
B88: 46023 | C88: 54865 | D88: 31700 | E88: =C88+D88 -> 86565
B89: 46082 | C89: 58000 | D89: 30275 | E89: =C89+D89 -> 88275 | I89: Coche | K89: 950 | L89: 0 | M89: 883.33333 | N89: 0 | O89: 0 | P89: 775 | Q89: 0 | R89: 0 | S89: 0 | T89: 1603.33 | U89: 615 | V89: 455 | W89: 455
B90: 46143 | C90: 63280 | D90: 33750 | E90: =C90+D90 -> 97030 | F90: maximo | I90: Alquiler | K90: 870 | L90: 760 | M90: 740 | N90: 740 | O90: 798.75 | P90: 720 | Q90: 909.16667 | R90: 714.16667 | S90: 705.83333 | T90: 609.58333 | U90: 684.16667 | V90: 0 | W90: 0
B91: 46296 | I91: Gimnasios | K91: 27 | L91: 26.666667 | M91: 30.833333 | N91: 27.5 | O91: 72.083333 | P91: 49.583333 | Q91: 54.583333 | R91: 51.666667 | S91: 45.416667 | T91: 50.833333 | U91: 51.25 | V91: 33.333333 | W91: 32.916667
I92: Ahorro e Inversion | K92: 365 | L92: 33.333333 | M92: 30 | N92: 50 | O92: 0 | P92: 0 | Q92: 0 | R92: 0 | S92: 0 | T92: 0 | U92: 0 | V92: 29.166667 | W92: 70.833333
I93: Traspasos y planes de ahorro | K93: 215 | L93: 59.166667 | M93: 29.166667 | N93: 13.333333 | O93: 13.333333 | P93: 15 | Q93: 14.166667 | R93: 39.166667 | S93: 38.333333 | T93: 0 | U93: 0 | V93: 5 | W93: 0
I94: Comida y bebida | K94: 380 | L94: 205.83333 | M94: 151.25 | N94: 118.75 | O94: 108.75 | P94: 90 | Q94: 138.75 | R94: 225 | S94: 280 | T94: 199.16667 | U94: 187.91667 | V94: 179.58333 | W94: 197.5
I95: Primitiva y otras loterias | K95: 56 | L95: 68.75 | M95: 46.666667 | N95: 34.583333 | O95: 64.166667 | P95: 39.166667 | Q95: 46.666667 | R95: 35.416667 | S95: 35.416667 | T95: 33.333333 | U95: 34.583333 | V95: 28.75 | W95: 34.583333
I96: Teléfono y otros gastos domésticos | K96: 135 | L96: 138.75 | M96: 147.91667 | N96: 162.91667 | O96: 176.25 | P96: 125.83333 | Q96: 145 | R96: 177.5 | S96: 179.16667 | T96: 113.33333 | U96: 77.916667 | V96: 101.25 | W96: 72.5
I97: Seguros (coche, decesos,hogar) | K97: 60 | L97: 72.5 | M97: 71.25 | N97: 64.583333 | O97: 66.666667 | P97: 67.083333 | Q97: 62.916667 | R97: 62.916667 | S97: 57.5 | T97: 30.416667 | U97: 0 | V97: 0 | W97: 60.416667
I99: Salud y cuidado personal | K99: 20 | L99: 11.25 | M99: 6.6666667 | N99: 40 | O99: 11.25 | P99: 52.083333 | Q99: 18.75 | R99: 11.666667 | S99: 3.75 | T99: 31.666667 | U99: 30 | V99: 5 | W99: 4.1666667
C100: Ahorro | D100: CC | E100: Total | I100: Averías (fontanería, etc.) | K100: 0 | L100: 0 | M100: 0 | N100: 0 | O100: 0 | P100: 13.333333 | Q100: 0 | R100: 0 | S100: 0 | T100: 0 | U100: 0 | V100: 0 | W100: 0
C101: (e inversion) | I101: Material oficina (cuadernos, salidas, etc.) | K101: 0.5 | L101: 1.25 | M101: 3.3333333 | N101: 2.9166667 | O101: 0.83333333 | P101: 3.75 | Q101: 0 | R101: 0.41666667 | S101: 0.83333333 | T101: 3.75 | U101: 0 | V101: 3.75 | W101: 5.8333333
B102: =YEARFRAC(B5,B88) -> 16.833333 | C102: años | I102: Gastos trabajo | K102: 0 | L102: 5.4166667 | M102: 26.666667 | N102: 24.166667 | O102: 29.166667 | P102: 8.3333333 | Q102: 0 | R102: 0 | S102: 93.75 | T102: 180.83333 | U102: 238.33333 | V102: 45.833333 | W102: 69.166667
I103: Regalos (cumpleaños, reyes, sobrinos,...) | K103: 102 | L103: 90 | M103: 85.416667 | N103: 97.5 | O103: 62.083333 | P103: 70.416667 | Q103: 78.333333 | R103: 120.83333 | S103: 208.75 | T103: 62.5 | U103: 95.416667 | V103: 108.75 | W103: 60
I104: Ocio (salidas, cenas, cine,...) | K104: 130 | L104: 121.25 | M104: 95.833333 | N104: 82.5 | O104: 77.5 | P104: 95.833333 | Q104: 137.91667 | R104: 109.58333 | S104: 90.833333 | T104: 145.41667 | U104: 145.41667 | V104: 141.25 | W104: 126.66667
I105: Encuadernaciones apuntes | K105: 0 | L105: 2.0833333 | M105: 2.5 | N105: 0 | O105: 0.41666667 | P105: 3.75 | Q105: 0 | R105: 0 | S105: 0 | T105: 0.83333333 | U105: 0 | V105: 0 | W105: 1.6666667
I106: Ropa y calzado | K106: 1 | L106: 14.166667 | M106: 82.083333 | N106: 10.416667 | O106: 0.83333333 | P106: 17.916667 | Q106: 19.583333 | R106: 48.333333 | S106: 0 | T106: 16.666667 | U106: 7.5 | V106: 25.416667 | W106: 10.416667
I107: Vacaciones | K107: 300 | L107: 168.75 | M107: 206.66667 | N107: 94.166667 | O107: 5.4166667 | P107: 60.833333 | Q107: 105.41667 | R107: 92.083333 | S107: 0 | T107: 85.833333 | U107: 12.5 | V107: 135.41667 | W107: 66.666667
I108: Reparaciones del automóvil | K108: 0 | L108: 13.75 | M108: 1.25 | N108: 21.25 | O108: 36.666667 | P108: 7.0833333 | Q108: 28.333333 | R108: 0 | S108: 0 | T108: 0 | U108: 0 | V108: 0.83333333 | W108: 28.333333
I109: Libros | K109: 0 | L109: 22.083333 | M109: 7.9166667 | N109: 2.9166667 | O109: 30.416667 | P109: 2.0833333 | Q109: 5 | R109: 9.5833333 | S109: 15.833333 | T109: 22.5 | U109: 4.5833333 | V109: 15.833333 | W109: 5
I110: Automóvil (combustible + párking) | K110: 20 | L110: 89.166667 | M110: 95.416667 | N110: 87.083333 | O110: 110.41667 | P110: 147.08333 | Q110: 130.41667 | R110: 52.5 | S110: 42.916667 | T110: 21.67 | U110: 2.5 | V110: 26.666667 | W110: 35.416667
I111: Otros medios de transporte (tren, metro,...) | K111: 2 | L111: 3.75 | M111: 2.5 | N111: 2.5 | O111: 12.083333 | P111: 4.5833333 | Q111: 15 | R111: 49.166667 | S111: 28.333333 | T111: 61.666667 | U111: 37.5 | V111: 29.166667 | W111: 36.25
I112: Material Deportivo | K112: 10 | L112: 2.5 | M112: 4.1666667 | N112: 0 | O112: 0 | P112: 0.83333333 | Q112: 9.1666667 | R112: 5 | S112: 34.166667 | T112: 12.5 | U112: 4.1666667 | V112: 23.333333 | W112: 0
I113: Viajes Personales, Excursiones | K113: 0 | L113: 6.6666667 | M113: 0 | N113: 1.6666667 | O113: 0 | P113: 33.75 | Q113: 45 | R113: 18.75 | S113: 52.5 | T113: 128.75 | U113: 54.583333 | V113: 177.5 | W113: 125.83333
I114: Videos, revistas, periodicos y colecciones | K114: 8 | L114: 30 | M114: 42.5 | N114: 22.916667 | O114: 43.333333 | P114: 18.75 | Q114: 17.916667 | R114: 14.166667 | S114: 25.416667 | T114: 18.75 | U114: 8.75 | V114: 24.583333 | W114: 35.833333
... I116: Tecnologia, Electronica, Informatica | K116: 1 | L116: 149.58333 | M116: 25 | N116: 190.41667 | O116: 0.41666667 | P116: 25 | Q116: 39.583333 | R116: 11.25 | S116: 218.75 | T116: 84.583333 | U116: 175.41667 | V116: 147.5 | W116: 163.33333
I117: Utensilios de viaje | L117: 0 | M117: 0 | N117: 0 | O117: 8.3333333 | P117: 0 | Q117: 0 | R117: 0 | S117: 4.1666667 | T117: 0 | U117: 0 | V117: 5 | W117: 0
I118: Hacienda | K118: 3 | L118: 0 | M118: 0 | N118: 5.8333333 | O118: 374.58333 | P118: 5.8333333 | Q118: 2.0833333 | R118: 134.16667 | S118: 732.91667 | T118: 0 | U118: 0 | V118: 0 | W118: 41.666667
I119: Hogar, Mudanzas | K119: 0 | L119: 6.25 | M119: 41.666667 | N119: 36.666667 | O119: 555.83333 | P119: 15.416667 | Q119: 335 | R119: 5 | S119: 349.58333 | T119: 9.5833333 | U119: 124.16667 | V119: 0 | W119: 0
I120: Otros | K120: 21.25 | L120: 84.583333 | M120: 59.166667 | N120: 19.583333 | O120: 40 | P120: 15 | Q120: 15 | R120: 117.5 | S120: 157.5 | T120: 134.16667 | U120: 115.83333 | V120: 212.5 | W120: 223.75
I121: Niños | K121: 170 | L121: 81.666667 | M121: 84.583333 | N121: 40.833333 | O121: 35 | P121: 23.75 | Q121: 0 | R121: 0 | S121: 0 | T121: 0 | U121: 0 | V121: 0 | W121: 0
I122: Asociaciones | K122: 38 | L122: 10 | M122: 2.5 | N122: 0 | O122: 0 | P122: 4.1666667 | Q122: 12.5 | R122: 25.416667 | S122: 11.25 | T122: 8.75 | U122: 12.5 | V122: 18.5 | W122: 20
...

Sheet WIP
B5: Año ▾ | C5: Mes | D5: Ingresos | E5: Gastos | F5: Diferencia | H5: Año | I5: Mes | J5: Ingresos | K5: Gastos | L5: Diferencia
B6: 2022 | C6: Enero | D6: 4085 | E6: 4045 | F6: 40 | H6: 2023 | I6: Enero | J6: 3900 | K6: 3495 | L6: 405
B7: 2022 | C7: Febrero | D7: 1885 | E7: 6470 | F7: -4585 | H7: 2023 | I7: Febrero | J7: 1790 | K7: 10430 | L7: -8640
B8: 2022 | C8: Marzo | D8: 1890 | E8: 1880 | F8: 10 | H8: 2023 | I8: Marzo | J8: 1770 | K8: 1825 | L8: -55
B9: 2022 | C9: Abril | D9: 9225 | E9: 2155 | F9: 7070 | H9: 2023 | I9: Abril | J9: 9700 | K9: 6045 | L9: 3655
B10: 2022 | C10: Mayo | D10: 2400 | E10: 2451 | F10: -51 | H10: 2023 | I10: Mayo | J10: 1830 | K10: 2730 | L10: -900
B11: 2022 | C11: Junio | D11: 1845 | E11: 2065 | F11: -220 | H11: 2023 | I11: Junio | J11: 1840 | K11: 2770 | L11: -930
B12: 2022 | C12: Julio | D12: 4025 | E12: 3040 | F12: 985 | H12: 2023 | I12: Julio | J12: 4095 | K12: 3575 | L12: 520
B13: 2022 | C13: Agosto | D13: 2525 | E13: 4016 | F13: -1491 | H13: 2023 | I13: Agosto | J13: 2915 | K13: 3120 | L13: -205
B14: 2022 | C14: Septiembre | D14: 1880 | E14: 4700 | F14: -2820 | H14: 2023 | I14: Septiembre | J14: 1955 | K14: 2060 | L14: -105
B15: 2022 | C15: Octubre | D15: 3980 | E15: 3545 | F15: 435 | H15: 2023 | I15: Octubre | J15: 4235 | K15: 4420 | L15: -185
B16: 2022 | C16: Noviembre | D16: 1800 | E16: 2165 | F16: -365 | H16: 2023 | I16: Noviembre | J16: 1975 | K16: 2690 | L16: -715
B17: 2022 | C17: Diciembre | D17: 1790 | E17: 2140 | F17: -350 | H17: 2023 | I17: Diciembre | J17: 1975 | K17: 3275 | L17: -1300
B18: Total: | D18: 37330 | E18: 38672 | F18: -1342 | H18: Total: | J18: 37980 | K18: 46435 | L18: -8455
B22: Categoría | C22: Importe | D22: Total | F22: 2023
B23: Automovil:Combustible | C23: -175 | H23: Enero | I23: Febrero | J23: Marzo | K23: Abril | L23: Mayo | M23: Junio | N23: Julio | O23: Agosto | P23: Septiembre | Q23: Octubre | R23: Noviembre | S23: Diciembre
B24: Automovil:Compra/Renting | C24: -400 | F24: Ahorro-Inversion | H24: 0 | I24: 0 | J24: 0 | K24: -2300 | L24: -240 | M24: -225 | N24: -250 | O24: -150 | P24: -160 | Q24: -795 | R24: -95 | S24: -130 | T24: -4345 | U24: =AVERAGE(H24:S24) -> -362.08333
B25: Automovil:Impuestos | C25: -70 | F25: Automovil:Mantenimiento | H25: -10 | I25: 0 | J25: 0 | K25: 0 | L25: 0 | M25: 0 | N25: 0 | O25: 0 | P25: 0 | Q25: 0 | R25: -10 | S25: 0 | T25: -20 | U25: =AVERAGE(H25:S25) -> -1.6666667
B26: Automovil:Mantenimiento | C26: -30 | F26: Automovil:Combustible | H26: 0 | I26: -20 | J26: -20 | K26: 0 | L26: -20 | M26: -20 | N26: -30 | O26: -20 | P26: -20 | Q26: -40 | R26: 0 | S26: -30 | T26: -220 | U26: =AVERAGE(H26:S26) -> -18.333333
B27: Automovil:Parking-Peajes | C27: -45 | F27: Automovil:Parking-Peajes | H27: 0 | I27: -5 | J27: 0 | K27: 0 | L27: -5 | M27: 0 | N27: 0 | O27: 0 | P27: 0 | Q27: 0 | R27: 0 | S27: -25 | T27: -35 | U27: =AVERAGE(H27:S27) -> -2.9166667
B28: Total categoría: | D28: -720 | F28: Automovil:Impuestos | H28: -100 | I28: 0 | J28: 0 | K28: 0 | L28: -70 | M28: 0 | N28: -120 | O28: 0 | P28: 0 | Q28: 0 | R28: 0 | S28: 0 | T28: -290 | U28: =AVERAGE(H28:S28) -> -24.166667
B29: Comida:Dietas | C29: -3840 | D29: -3840 | F29: Automovil:Compra/Renting | H29: 0 | I29: -8500 | J29: -280 | K29: -1300 | L29: -280 | M29: 0 | N29: 0 | O29: 0 | P29: 0 | Q29: -1000 | R29: 0 | S29: 0 | T29: -11360 | U29: =AVERAGE(H29:S29) -> -946.66667
B30: Deporte:Gimnasio | C30: -260 | F30: Comida:Dietas | H30: -285 | I30: -275 | J30: -300 | K30: -405 | L30: -370 | M30: -480 | N30: -375 | O30: -275 | P30: -445 | Q30: -415 | R30: -475 | S30: -450 | T30: -4550 | U30: =AVERAGE(H30:S30) -> -379.16667
B31: Deporte:Ropa | C31: -25 | F31: Deporte:Ropa | H31: 0 | I31: 0 | J31: 0 | K31: 0 | L31: -25 | M31: 0 | N31: 0 | O31: 0 | P31: -45 | Q31: -50 | R31: 0 | S31: 0 | T31: -120 | U31: =AVERAGE(H31:S31) -> -10
B32: Total categoría: | D32: -285 | F32: Deporte:Gimnasio | H32: -65 | I32: 0 | J32: 0 | K32: -65 | L32: 0 | M32: 0 | N32: -65 | O32: 0 | P32: 0 | Q32: -105 | R32: -15 | S32: -15 | T32: -330 | U32: =AVERAGE(H32:S32) -> -27.5
B33: Formacion-Cultura:Papeleria | C33: -5 | D33: -5 | F33: Formacion-Cultura:Papeleria | H33: 0 | I33: 0 | J33: 0 | K33: 0 | L33: 0 | M33: 0 | N33: 0 | O33: 0 | P33: 0 | Q33: 0 | R33: -5 | S33: 0 | T33: -5 | U33: =AVERAGE(H33:S33) -> -0.41666667
B34: GastoFijoMensual:Agua | C34: -340 | F34: GastoFijoMensual:Telefono | H34: -35 | I34: -35 | J34: -35 | K34: -40 | L34: -40 | M34: -40 | N34: -40 | O34: -40 | P34: -40 | Q34: -40 | R34: -40 | S34: -40 | T34: -465 | U34: =AVERAGE(H34:S34) -> -38.75
B35: GastoFijoMensual:Alquiler | C35: -9940 | F35: GastoFijoMensual:Electricidad | H35: 0 | I35: -125 | J35: 0 | K35: -110 | L35: 0 | M35: -100 | N35: 0 | O35: -100 | P35: 0 | Q35: -85 | R35: 0 | S35: -50 | T35: -570 | U35: =AVERAGE(H35:S35) -> -47.5
B36: GastoFijoMensual:Electricidad | C36: -665 | F36: GastoFijoMensual:Gas | H36: 0 | I36: -45 | J36: 0 | K36: -60 | L36: 0 | M36: -25 | N36: 0 | O36: -20 | P36: 0 | Q36: -25 | R36: 0 | S36: -20 | T36: -195 | U36: =AVERAGE(H36:S36) -> -16.25
B37: GastoFijoMensual:Gas | C37: -190 | F37: GastoFijoMensual:Alquiler | H37: -870 | I37: -870 | J37: -870 | K37: -870 | L37: -870 | M37: -870 | N37: -870 | O37: -870 | P37: -870 | Q37: -870 | R37: -870 | S37: -870 | T37: -10440 | U37: =AVERAGE(H37:S37) -> -870
B38: GastoFijoMensual:Telefono | C38: -420 | F38: GastoFijoMensual:Agua | H38: 0 | I38: -55 | J38: 0 | K38: -55 | L38: 0 | M38: -55 | N38: 0 | O38: -55 | P38: 0 | Q38: -55 | R38: 0 | S38: -55 | T38: -330 | U38: =AVERAGE(H38:S38) -> -27.5
B39: Total categoría: | D39: -11555 | F39: Hogar y Vestuario:Ropa | H39: 0 | I39: 0 | J39: 0 | K39: 0 | L39: 0 | M39: 0 | N39: 0 | O39: 0 | P39: -5 | Q39: 0 | R39: 0 | S39: 0 | T39: -5 | U39: =AVERAGE(H39:S39) -> -0.41666667
B40: Hogar y Vestuario:Mobiliario | C40: -185 | F40: Hogar y Vestuario:Niños | H40: -50 | I40: -45 | J40: -110 | K40: -275 | L40: -535 | M40: -600 | N40: -115 | O40: -30 | P40: -40 | Q40: -90 | R40: -50 | S40: -50 | T40: -1990 | U40: =AVERAGE(H40:S40) -> -165.83333
B41: Hogar y Vestuario:Niños | C41: -2845 | F41: Impuestos:Hacienda | H41: 0 | I41: 0 | J41: 0 | K41: -35 | L41: 0 | M41: 0 | N41: 0 | O41: 0 | P41: 0 | Q41: 0 | R41: 0 | S41: 0 | T41: -35 | U41: =AVERAGE(H41:S41) -> -2.9166667
B42: Hogar y Vestuario:Ropa | C42: -160 | F42: Ingresos:Salario | H42: 3900 | I42: 1790 | J42: 1770 | K42: 9700 | L42: 1830 | M42: 1840 | N42: 4095 | O42: 2915 | P42: 1955 | Q42: 4235 | R42: 1975 | S42: 1975 | T42: 37980 | U42: =AVERAGE(H42:S42) -> 3165
B43: Hogar y Vestuario:Varios | C43: -40 | F43: Loteria | H43: -25 | I43: -55 | J43: -35 | K43: -95 | L43: -75 | M43: -60 | N43: -30 | O43: -50 | P43: -30 | Q43: -45 | R43: -85 | S43: -85 | T43: -670 | U43: =AVERAGE(H43:S43) -> -55.833333
B44: Total categoría: | D44: -3230 | F44: Ocio | H44: -35 | I44: 0 | J44: 0 | K44: 0 | L44: 0 | M44: 0 | N44: 0 | O44: -75 | P44: 0 | Q44: 0 | R44: 0 | S44: 0 | T44: -110 | U44: =AVERAGE(H44:S44) -> -9.1666667
B45: Impuestos:Hacienda | C45: 575 | D45: 575 | F45: Ocio:Revistas-Colecciones | H45: -50 | I45: 0 | J45: 0 | K45: -50 | L45: 0 | M45: 0 | N45: 0 | O45: 0 | P45: 0 | Q45: 0 | R45: 0 | S45: 0 | T45: -100 | U45: =AVERAGE(H45:S45) -> -8.3333333
B46: Ingresos:Salario | C46: 36755 | D46: 36755 | F46: Ocio:FinSemana y Festivos | H46: -180 | I46: -55 | J46: -75 | K46: -135 | L46: -80 | M46: -115 | N46: -75 | O46: -125 | P46: -180 | Q46: -190 | R46: -65 | S46: -200 | T46: -1475 | U46: =AVERAGE(H46:S46) -> -122.91667
B47: Loteria | C47: -800 | D47: -800 | F47: Ocio:Otros | H47: 0 | I47: 0 | J47: -10 | K47: 0 | L47: 0 | M47: 0 | N47: -10 | O47: 0 | P47: -160 | Q47: -75 | R47: 0 | S47: 0 | T47: -255 | U47: =AVERAGE(H47:S47) -> -21.25
B48: Ocio | C48: -185 | F48: Regalos | H48: -745 | I48: 0 | J48: -40 | K48: -115 | L48: -60 | M48: -50 | N48: 0 | O48: 0 | P48: 0 | Q48: 0 | R48: 0 | S48: -210 | T48: -1220 | U48: =AVERAGE(H48:S48) -> -101.66667
B49: Ocio:FinSemana y Festivos | C49: -1365 | F49: Salud:Farmacos | H49: -10 | I49: 0 | J49: -5 | K49: 0 | L49: 0 | M49: -60 | N49: 0 | O49: 0 | P49: 0 | Q49: 0 | R49: 0 | S49: -65 | T49: -140 | U49: =AVERAGE(H49:S49) -> -11.666667
B50: Ocio:Otros | C50: -625 | F50: Salud:Cosmetica | H50: 0 | I50: 0 | J50: 0 | K50: -75 | L50: 0 | M50: 0 | N50: 0 | O50: 0 | P50: 0 | Q50: 0 | R50: 0 | S50: 0 | T50: -75 | U50: =AVERAGE(H50:S50) -> -6.25
B51: Ocio:Revistas-Colecciones | C51: -100 | F51: Seguros:Hogar | H51: -190 | I51: 0 | J51: 0 | K51: 0 | L51: 0 | M51: 0 | N51: 0 | O51: 0 | P51: 0 | Q51: 0 | R51: 0 | S51: 0 | T51: -190 | U51: =AVERAGE(H51:S51) -> -15.833333
B52: Total categoría: | D52: -2275 | F52: Seguros:Decesos | H52: -20 | I52: -20 | J52: -20 | K52: -20 | L52: -20 | M52: -20 | N52: -20 | O52: -20 | P52: -20 | Q52: -20 | R52: -20 | S52: -20 | T52: -240 | U52: =AVERAGE(H52:S52) -> -20
B53: Regalos | C53: -695 | D53: -695 | F53: Tecnologia | H53: 0 | I53: 0 | J53: 0 | K53: 0 | L53: 0 | M53: -10 | N53: 0 | O53: 0 | P53: 0 | Q53: 0 | R53: 0 | S53: 0 | T53: -10 | U53: =AVERAGE(H53:S53) -> -0.83333333
B54: Salud:Farmacos | C54: -150 | D54: -150 | F54: Transferencia | H54: -800 | I54: -300 | J54: 0 | K54: 0 | L54: 0 | M54: 0 | N54: -1000 | O54: -500 | P54: 0 | Q54: 0 | R54: 0 | S54: 0 | T54: -2600 | U54: =AVERAGE(H54:S54) -> -216.66667
B55: Seguros:Decesos | C55: -205 | F55: Tren-metro-bus | H55: 0 | I55: 0 | J55: 0 | K55: 0 | L55: 0 | M55: 0 | N55: -25 | O55: 0 | P55: 0 | Q55: 0 | R55: 0 | S55: 0 | T55: -25 | U55: =AVERAGE(H55:S55) -> -2.0833333
B56: Seguros:Hogar | C56: -180 | F56: Vacaciones | H56: 0 | I56: 0 | J56: 0 | K56: 0 | L56: 0 | M56: 0 | N56: -510 | O56: -750 | P56: 0 | Q56: -475 | R56: -915 | S56: -915 | T56: -3565 | U56: =AVERAGE(H56:S56) -> -297.08333
B57: Total categoría: | D57: -385 | F57: Varios | H57: -25 | I57: -25 | J57: -25 | K57: -40 | L57: -40 | M57: -40 | N57: -40 | O57: -40 | P57: -45 | Q57: -45 | R57: -45 | S57: -45 | T57: -455 | U57: =AVERAGE(H57:S57) -> -37.916667
B58: Tecnologia | C58: -3855 | D58: -3855 | F58: Ingresos | H58: 3900 | I58: 1790 | J58: 1770 | K58: 9700 | L58: 1830 | M58: 1840 | N58: 4095 | O58: 2915 | P58: 1955 | Q58: 4235 | R58: 1975 | S58: 1975 | T58: 37980 | U58: =AVERAGE(H58:S58) -> 3165
B59: Transferencia | C59: -7300 | D59: -7300 | F59: Gastos | H59: -3495 | I59: -10430 | J59: -1825 | K59: -6045 | L59: -2730 | M59: -2770 | N59: -3575 | O59: -3120 | P59: -2060 | Q59: -4420 | R59: -2690 | S59: -3275 | T59: -46435 | U59: =AVERAGE(H59:S59) -> -3869.5833
B60: Tren-metro-bus | C60: -62 | D60: -62 | F60: Total | H60: 405 | I60: -8640 | J60: -55 | K60: 3655 | L60: -900 | M60: -930 | N60: 520 | O60: -205 | P60: -105 | Q60: -185 | R60: -715 | S60: -1300 | T60: -8455 | U60: =AVERAGE(H60:S60) -> -704.58333
B61: Vacaciones | C61: -3215 | D61: -3215
B62: Varios | C62: -300 | D62: -300
B63: Total Expenses: | D63: -38672
B64: Total Income: | D64: 37330
B65: Suma total: | D65: -1342

Sheet Principal
C3: 2003 | D3: 2004 | E3: 2005 | F3: 2006 | G3: 2007 | H3: 2008 | I3: 2009 | J3: 2010 | K3: 2011 | L3: 2012 | M3: 2013 | N3: 2014 | O3: 2015 | P3: 2016 | Q3: 2017 | R3: 2018 | S3: 2019 | T3: 2020 | U3: 2021 | V3: 2022 | W3: 2023 | X3: 2024 | Y3: 2025 | Z3: 2026 | AA3: 2027 | AB3: TOTALES | AC3: Promedios
B5: Salario | C5: 17490 | D5: 22055 | E5: 15700 | F5: 20050 | G5: 24000 | H5: 24600 | I5: 36125 | J5: 40330 | K5: 16970 | L5: 20615 | M5: 23960 | N5: 26425 | O5: 29035 | P5: 23000 | Q5: 31130 | R5: 31500 | S5: 31575 | T5: 32245 | U5: 35815 | V5: 36755 | W5: 37980 | X5: 44150 | Y5: 46200 | AB5: =SUM(C5:Y5) -> 667705 | AC5: =AVERAGE(C5:X5) -> 28250.227 | AD5: Salario
B6: Salario (Pagas extraordinarias) | C6: 4750 | D6: 7600 | E6: 11175 | F6: 1800 | G6: 2575 | H6: 2100 | I6: 20825 | J6: 0 | K6: 2750 | L6: 3510 | M6: 1825 | N6: 0 | O6: 0 | P6: 8000 | Q6: 0 | R6: 250 | S6: 0 | T6: 0 | U6: 0 | V6: 0 | W6: 0 | X6: 0 | Y6: 0 | AB6: =SUM(C6:Y6) -> 67160 | AC6: =AVERAGE(C6:X6) -> 3052.7273 | AD6: Salario (Pagas extraordinarias)
B7: Otros ingresos | C7: 2500 | D7: 0 | E7: 0 | F7: 13000 | G7: 0 | H7: 0 | I7: 0 | J7: 750 | K7: 0 | L7: 720 | M7: 90 | N7: 1440 | O7: 0 | P7: 625 | Q7: 135 | R7: 0 | S7: 0 | T7: 0 | U7: 0 | V7: 575 | W7: 0 | X7: 0 | Y7: 0 | AB7: =SUM(C7:Y7) -> 19835 | AC7: =AVERAGE(C7:X7) -> 901.59091 | AD7: Otros ingresos
B8: Reajuste del saldo | C8: 0 | D8: 0 | E8: 0 | F8: 0 | G8: 0 | H8: 0 | I8: 0 | J8: 0 | K8: 0 | L8: 0 | M8: 0 | N8: 0 | O8: 0 | P8: 0 | Q8: 0 | R8: 0 | S8: 0 | T8: 0 | U8: 0 | V8: 0 | W8: 0 | X8: 0 | Y8: 0 | AB8: =SUM(C8:Y8) -> 0 | AC8: =AVERAGE(C8:X8) -> 0 | AD8: Reajuste del saldo
B9: Inversión | C9: 0 | D9: 0 | E9: 12000 | F9: 0 | G9: 0 | H9: 0 | I9: 0 | J9: 0 | K9: 0 | L9: 0 | M9: 0 | N9: 0 | O9: 0 | P9: 0 | Q9: 0 | R9: 0 | S9: 0 | T9: 0 | U9: 0 | V9: 0 | W9: 0 | X9: 0 | Y9: 0 | AB9: =SUM(C9:Y9) -> 12000 | AC9: =AVERAGE(C9:X9) -> 545.45455 | AD9: Inversión
B10: Ayudas familiares | C10: 0 | D10: 0 | E10: 0 | F10: 0 | G10: 0 | H10: 0 | I10: 0 | J10: 0 | K10: 0 | L10: 0 | M10: 0 | N10: 0 | O10: 0 | P10: 0 | Q10: 0 | R10: 0 | S10: 0 | T10: 0 | U10: 0 | V10: 0 | W10: 0 | X10: 0 | Y10: 0 | AB10: =SUM(C10:Y10) -> 0 | AC10: =AVERAGE(C10:X10) -> 0 | AD10: Ayudas familiares
B11: Bolsa de Ahorro | C11: 355 | D11: 0 | E11: 0 | F11: 0 | G11: 0 | H11: 0 | I11: 0 | J11: 0 | K11: 0 | L11: 0 | M11: 0 | N11: 0 | O11: 0 | P11: 0 | Q11: 0 | R11: 0 | S11: 0 | T11: 0 | U11: 0 | V11: 0 | W11: 0 | X11: 0 | Y11: 0 | AB11: =SUM(C11:Y11) -> 355 | AC11: =AVERAGE(C11:X11) -> 16.136364 | AD11: Bolsa de Ahorro
B12: Varios | C12: 500 | D12: 0 | E12: 0 | F12: 0 | G12: 0 | H12: 0 | I12: 0 | J12: 0 | K12: 0 | L12: 0 | M12: 0 | N12: 0 | O12: 0 | P12: 0 | Q12: 0 | R12: 0 | S12: 0 | T12: 0 | U12: 0 | V12: 0 | W12: 0 | X12: 0 | Y12: 0 | AB12: =SUM(C12:Y12) -> 500 | AC12: =AVERAGE(C12:X12) -> 22.727273 | AD12: Varios
B13: TOTAL INGRESOS | C13: =SUM(C5:C12) -> 25595 | D13: =SUM(D5:D12) -> 29655 | E13: =SUM(E5:E12) -> 38875 | F13: =SUM(F5:F12) -> 34850 | G13: =SUM(G5:G12) -> 26575 | H13: =SUM(H5:H12) -> 26700 | I13: =SUM(I5:I12) -> 56950 | J13: =SUM(J5:J12) -> 41080 | ... Y13: =SUM(Y5:Y12) -> 46200 | AB13: =SUM(C13:Y13) -> 767555 | AC13: =AVERAGE(C13:X13) -> 32788.864 | AD13: Ingresos 2003-2025
B15: Coche | C15: 5605 | D15: 5460 | E15: 5460 | F15: 5460 | G15: 5460 | H15: 7380 | I15: 18650 | J15: 0 | K15: 0 | L15: 0 | M15: 9300 | N15: 0 | O15: 0 | P15: 10600 | Q15: 0 | R15: 0 | S15: 3450 | T15: 2175 | U15: 2500 | V15: 400 | W15: 11650 | X15: 2735 | Y15: 4160 | AB15: =SUM(C15:Y15) -> 100445 | AC15: =AVERAGE(C15:Y15) -> 4367.1739
B16: Gimnasios | C16: 325 | D16: 445 | E16: 320 | F16: 395 | G16: 400 | H16: 615 | I16: 610 | J16: 545 | K16: 620 | L16: 655 | M16: 595 | N16: 865 | O16: 330 | P16: 375 | Q16: 320 | R16: 295 | S16: 320 | T16: 300 | U16: 115 | V16: 260 | W16: 330 | X16: 610 | Y16: 580 | AB16: =SUM(C16:Y16) -> 10225 | AC16: =AVERAGE(C16:Y16) -> 444.56522
B17: Plan de Ahorro / Inversion | C17: 720 | D17: 760 | E17: 1200 | F17: 850 | G17: 350 | H17: 0 | I17: 0 | J17: 0 | K17: 0 | L17: 0 | M17: 0 | N17: 0 | O17: 600 | P17: 650 | Q17: 400 | R17: 335 | S17: 320 | T17: 1110 | U17: 120 | V17: 0 | W17: 0 | X17: 3048 | Y17: 7290 | AB17: =SUM(C17:Y17) -> 17753 | AC17: =AVERAGE(C17:Y17) -> 771.86957
B18: Traspaso Caixa Catalunya / BBVA | C18: 1500 | D18: 100 | E18: 1200 | F18: 0 | G18: 60 | H18: 0 | I18: 0 | J18: 460 | K18: 470 | L18: 170 | M18: 180 | N18: 160 | O18: 160 | P18: 50 | Q18: 710 | R18: 2000 | S18: 0 | T18: 0 | U18: 0 | V18: 7300 | W18: 6945 | X18: 2950 | Y18: 1300 | AB18: =SUM(C18:Y18) -> 25715 | AC18: =AVERAGE(C18:Y18) -> 1118.0435
B19: Comida y bebida | C19: 605 | D19: 615 | E19: 1810 | F19: 2370 | G19: 2155 | H19: 2255 | I19: 2390 | J19: 3360 | K19: 2700 | L19: 1665 | M19: 1080 | N19: 1305 | O19: 1425 | P19: 1815 | Q19: 2470 | R19: 1770 | S19: 2150 | T19: 2925 | U19: 3655 | V19: 3840 | W19: 4550 | X19: 5475 | Y19: 6395 | AB19: =SUM(C19:Y19) -> 58780 | AC19: =AVERAGE(C19:Y19) -> 2555.6522
B20: Primitiva y otras loterias | C20: 149 | D20: 264 | E20: 335 | F20: 415 | G20: 345 | H20: 415 | I20: 400 | J20: 425 | K20: 425 | L20: 560 | M20: 470 | N20: 770 | O20: 415 | P20: 550 | Q20: 825 | R20: 1025 | S20: 725 | T20: 580 | U20: 600 | V20: 800 | W20: 670 | X20: 730 | Y20: 805 | AB20: =SUM(C20:Y20) -> 12698 | AC20: =AVERAGE(C20:Y20) -> 552.08696
B21: Tfno, Agua, Gas, Luz, etc | C21: 160 | D21: 705 | E21: 835 | F21: 870 | G21: 1215 | H21: 935 | I21: 1360 | J21: 2150 | K21: 2130 | L21: 1740 | M21: 1510 | N21: 2115 | O21: 1955 | P21: 1775 | Q21: 1665 | R21: 1755 | S21: 1725 | T21: 1770 | U21: 1765 | V21: 1615 | W21: 1560 | X21: 1715 | Y21: 2885 | AB21: =SUM(C21:Y21) -> 35910 | AC21: =AVERAGE(C21:Y21) -> 1561.3043
B22: Otros | C22: 780 | D22: 1725 | E22: 2110 | F22: 2685 | G22: 2550 | H22: 1390 | I22: 1625 | J22: 1890 | K22: 1410 | L22: 180 | M22: 180 | N22: 480 | O22: 235 | P22: 700 | Q22: 1015 | R22: 1135 | S22: 900 | T22: 180 | U22: 210 | V22: 625 | W22: 255 | X22: 350 | Y22: 120 | AB22: =SUM(C22:Y22) -> 22730 | AC22: =AVERAGE(C22:Y22) -> 988.26087
B23: Seguros (coche, vida, tarjetas) | C23: 900 | D23: 900 | E23: 850 | F23: 725 | G23: 0 | H23: 0 | I23: 365 | J23: 690 | K23: 755 | L23: 755 | M23: 805 | N23: 800 | O23: 775 | P23: 850 | Q23: 870 | R23: 890 | S23: 395 | T23: 385 | U23: 355 | V23: 385 | W23: 430 | X23: 880 | Y23: 930 | AB23: =SUM(C23:Y23) -> 14690 | AC23: =AVERAGE(C23:Y23) -> 638.69565
B24: Asociaciones, subscripciones,… | C24: 270 | D24: 0 | E24: 0 | F24: 0 | G24: 30 | H24: 30 | I24: 30 | J24: 100 | K24: 305 | L24: 140 | M24: 50 | N24: 50 | O24: 50 | P24: 50 | Q24: 120 | R24: 150 | S24: 215 | T24: 180 | U24: 220 | V24: 100 | W24: 100 | X24: 100 | Y24: 620 | AB24: =SUM(C24:Y24) -> 2910 | AC24: =AVERAGE(C24:Y24) -> 126.52174 | AD24: Netflix, Google, MS
B26: Alquiler | C26: 0 | D26: 0 | E26: 0 | F26: 0 | G26: 0 | H26: 8210 | I26: 7315 | J26: 8470 | K26: 8570 | L26: 10910 | M26: 8640 | N26: 9585 | O26: 8880 | P26: 8880 | Q26: 9120 | R26: 9550 | S26: 9840 | T26: 9675 | U26: 9840 | V26: 9940 | W26: 10440 | X26: 10740 | Y26: 11035 | AB26: =SUM(C26:Y26) -> 169640 | AC26: =AVERAGE(C26:Y26) -> 7375.6522
B27: Salud y cuidado personal | C27: 30 | D27: 40 | E27: 120 | F27: 50 | G27: 60 | H27: 360 | I27: 380 | J27: 45 | K27: 140 | L27: 225 | M27: 625 | N27: 135 | O27: 480 | P27: 100 | Q27: 135 | R27: 165 | S27: 125 | T27: 750 | U27: 170 | V27: 150 | W27: 215 | X27: 5785 | Y27: 1155 | AB27: =SUM(C27:Y27) -> 11440 | AC27: =AVERAGE(C27:Y27) -> 497.3913
B28: Averías (fontanería, etc.) | C28: 0 | D28: 0 | E28: 0 | F28: 0 | G28: 0 | H28: 0 | I28: 0 | J28: 0 | K28: 0 | L28: 0 | M28: 160 | N28: 0 | O28: 0 | P28: 0 | Q28: 0 | R28: 0 | S28: 0 | T28: 0 | U28: 0 | V28: 0 | W28: 0 | X28: 15 | Y28: 0 | AB28: =SUM(C28:Y28) -> 175 | AC28: =AVERAGE(C28:Y28) -> 7.6086957
B29: Material oficina (cuadernos, salidas, etc.) | C29: 65 | D29: 40 | E29: 25 | F29: 90 | G29: 45 | H29: 0 | I29: 55 | J29: 10 | K29: 5 | L29: 0 | M29: 90 | N29: 15 | O29: 35 | P29: 75 | Q29: 15 | R29: 15 | S29: 105 | T29: 60 | U29: 20 | V29: 5 | W29: 5 | X29: 10 | Y29: 5 | AB29: =SUM(C29:Y29) -> 790 | AC29: =AVERAGE(C29:Y29) -> 34.347826
B30: Gastos trabajo | C30: 2885 | D30: 4205 | E30: 830 | F30: 830 | G30: 550 | H30: 2860 | I30: 2170 | J30: 1125 | K30: 0 | L30: 0 | M30: 100 | N30: 350 | O30: 290 | P30: 325 | Q30: 65 | R30: 0 | S30: 70 | T30: 0 | U30: 10 | V30: 0 | W30: 0 | X30: 0 | Y30: 0 | AB30: =SUM(C30:Y30) -> 16665 | AC30: =AVERAGE(C30:Y30) -> 724.56522 | AD30: (no contabilizables)
B31: Regalos (cumpleaños, reyes, …) | C31: 550 | D31: 1365 | E31: 1730 | F31: 720 | G31: 1305 | H31: 1145 | I31: 1000 | J31: 2505 | K31: 1450 | L31: 940 | M31: 845 | N31: 745 | O31: 1170 | P31: 1025 | Q31: 1080 | R31: 550 | S31: 1000 | T31: 1280 | U31: 445 | V31: 695 | W31: 1220 | X31: 315 | Y31: 1800 | AB31: =SUM(C31:Y31) -> 24880 | AC31: =AVERAGE(C31:Y31) -> 1081.7391
B32: Ocio (salidas, cenas, revistas,...) | C32: 795 | D32: 1665 | E32: 1650 | F32: 1520 | G32: 1695 | H32: 1745 | I32: 1745 | J32: 1090 | K32: 1315 | L32: 1655 | M32: 1150 | N32: 930 | O32: 990 | P32: 1150 | Q32: 1455 | R32: 1355 | S32: 1700 | T32: 580 | U32: 910 | V32: 1545 | W32: 1730 | X32: 1770 | Y32: 1880 | AB32: =SUM(C32:Y32) -> 32020 | AC32: =AVERAGE(C32:Y32) -> 1392.1739
B33: Ropa y calzado | C33: 220 | D33: 470 | E33: 185 | F33: 125 | G33: 305 | H33: 90 | I33: 200 | J33: 0 | K33: 580 | L33: 235 | M33: 215 | N33: 10 | O33: 125 | P33: 1000 | Q33: 170 | R33: 230 | S33: 75 | T33: 65 | U33: 65 | V33: 160 | W33: 5 | X33: 305 | Y33: 45 | AB33: =SUM(C33:Y33) -> 4880 | AC33: =AVERAGE(C33:Y33) -> 212.17391
B34: Vacaciones | C34: 950 | D34: 475 | E34: 1200 | F34: 800 | G34: 1625 | H34: 150 | I34: 1030 | J34: 0 | K34: 1105 | L34: 1265 | M34: 730 | N34: 65 | O34: 1130 | P34: 2475 | Q34: 2025 | R34: 4425 | S34: 1800 | T34: 2175 | U34: 2785 | V34: 3215 | W34: 3565 | X34: 4610 | Y34: 2300 | AB34: =SUM(C34:Y34) -> 39900 | AC34: =AVERAGE(C34:Y34) -> 1734.7826
B35: Reparaciones del automóvil | C35: 300 | D35: 630 | E35: 0 | F35: 340 | G35: 10 | H35: 0 | I35: 0 | J35: 0 | K35: 0 | L35: 340 | M35: 85 | N35: 440 | O35: 255 | P35: 15 | Q35: 165 | R35: 520 | S35: 155 | T35: 0 | U35: 165 | V35: 100 | W35: 20 | X35: 15 | Y35: 0 | AB35: =SUM(C35:Y35) -> 3555 | AC35: =AVERAGE(C35:Y35) -> 154.56522
B36: Libros | C36: 205 | D36: 175 | E36: 310 | F36: 60 | G36: 190 | H36: 55 | I36: 270 | J36: 190 | K36: 115 | L36: 60 | M36: 25 | N36: 365 | O36: 35 | P36: 100 | Q36: 265 | R36: 120 | S36: 60 | T36: 40 | U36: 0 | V36: 0 | W36: 5 | X36: 0 | Y36: 0 | AB36: =SUM(C36:Y36) -> 2645 | AC36: =AVERAGE(C36:Y36) -> 115
B37: Automóvil (combustible + párking) | C37: 505 | D37: 430 | E37: 570 | F37: 425 | G37: 320 | H37: 30 | I37: 850 | J37: 515 | K37: 630 | L37: 1565 | M37: 1765 | N37: 1325 | O37: 1110 | P37: 1150 | Q37: 1070 | R37: 1200 | S37: 1050 | T37: 390 | U37: 60 | V37: 220 | W37: 35 | X37: 370 | Y37: 200 | AB37: =SUM(C37:Y37) -> 15785 | AC37: =AVERAGE(C37:Y37) -> 686.30435
B38: Otros medios de transporte (tren, metro,...) | C38: 46 | D38: 90 | E38: 300 | F38: 435 | G38: 350 | H38: 450 | I38: 750 | J38: 340 | K38: 590 | L38: 180 | M38: 55 | N38: 145 | O38: 30 | P38: 30 | Q38: 45 | R38: 15 | S38: 20 | T38: 40 | U38: 0 | V38: 65 | W38: 25 | X38: 270 | Y38: 30 | AB38: =SUM(C38:Y38) -> 4301 | AC38: =AVERAGE(C38:Y38) -> 187
B39: Material Deportivo | C39: 115 | D39: 50 | E39: 30 | F39: 0 | G39: 280 | H39: 50 | I39: 150 | J39: 410 | K39: 60 | L39: 110 | M39: 10 | N39: 0 | O39: 0 | P39: 50 | Q39: 30 | R39: 10 | S39: 50 | T39: 35 | U39: 90 | V39: 25 | W39: 120 | X39: 75 | Y39: 100 | AB39: =SUM(C39:Y39) -> 1850 | AC39: =AVERAGE(C39:Y39) -> 80.434783
B40: Viajes Personales, Excursiones | C40: 375 | D40: 805 | E40: 1710 | F40: 1510 | G40: 2130 | H40: 655 | I40: 1550 | J40: 630 | K40: 225 | L40: 400 | M40: 405 | N40: 0 | O40: 20 | P40: 0 | Q40: 80 | R40: 0 | S40: 0 | T40: 0 | U40: 0 | V40: 0 | W40: 0 | X40: 0 | Y40: 1550 | AB40: =SUM(C40:AA40) -> 12045 | AC40: =AVERAGE(C40:Y40) -> 523.69565
B41: Videos, revistas, periodicos y colecciones | C41: 176 | D41: 395 | E41: 360 | F41: 430 | G41: 295 | H41: 105 | I41: 225 | J41: 305 | K41: 170 | L41: 215 | M41: 225 | N41: 520 | O41: 275 | P41: 510 | Q41: 360 | R41: 315 | S41: 235 | T41: 180 | U41: 150 | V41: 300 | W41: 100 | X41: 0 | Y41: 25 | AB41: =SUM(C41:Y41) -> 5871 | AC41: =AVERAGE(C41:Y41) -> 255.26087
B42: Formación | C42: 2150 | D42: 780 | E42: 800 | F42: 610 | G42: 0 | H42: 0 | I42: 2100 | J42: 0 | K42: 995 | L42: 0 | M42: 0 | N42: 275 | O42: 250 | P42: 0 | Q42: 390 | R42: 140 | S42: 50 | T42: 0 | U42: 110 | V42: 0 | W42: 5 | X42: 0 | Y42: 0 | AB42: =SUM(C42:AA42) -> 8655 | AC42: =AVERAGE(C42:Y42) -> 376.30435
B43: Tecnologia, Electronica, Informatica | C43: 275 | D43: 275 | E43: 1785 | F43: 1960 | G43: 1770 | H43: 2105 | I43: 1000 | J43: 2625 | K43: 135 | L43: 475 | M43: 300 | N43: 5 | O43: 2285 | P43: 300 | Q43: 1795 | R43: 3840 | S43: 750 | T43: 1660 | U43: 1770 | V43: 3855 | W43: 10 | X43: 2865 | Y43: 205 | AB43: =SUM(C43:AA43) -> 32045 | AC43: =AVERAGE(C43:Y43) -> 1393.2609
B44: Utensilios | C44: 700 | D44: 275 | E44: 0 | F44: 0 | G44: 60 | H44: 0 | I44: 0 | J44: 50 | K44: 0 | L44: 0 | M44: 0 | N44: 100 | O44: 0 | P44: 0 | Q44: 0 | R44: 50 | S44: 0 | T44: 0 | U44: 0 | V44: 40 | W44: 5 | X44: 10 | Y44: 50 | AB44: =SUM(C44:AA44) -> 1340 | AC44: =AVERAGE(C44:Y44) -> 58.26087
B45: Hacienda y otros impuestos | C45: 575 | D45: 300 | E45: 1900 | F45: 500 | G45: 0 | H45: 0 | I45: 0 | J45: 8795 | K45: 1610 | L45: 25 | M45: 70 | N45: 4495 | O45: 70 | P45: 0 | Q45: 0 | R45: 70 | S45: 70 | T45: 105 | U45: 210 | V45: 0 | W45: 0 | X45: 70 | Y45: 155 | AB45: =SUM(C45:AA45) -> 19020 | AC45: =AVERAGE(C45:Y45) -> 826.95652
B46: Hogar, Mudanzas, Muebles | C46: 1800 | D46: 0 | E46: 0 | F46: 0 | G46: 0 | H46: 1490 | I46: 115 | J46: 4195 | K46: 60 | L46: 4020 | M46: 185 | N46: 6670 | O46: 440 | P46: 500 | Q46: 75 | R46: 350 | S46: 190 | T46: 145 | U46: 1770 | V46: 185 | W46: 0 | X46: 750 | Y46: 100 | AB46: =SUM(C46:AA46) -> 23040 | AC46: =AVERAGE(C46:Y46) -> 1001.7391
B47: Niños | C47: 0 | D47: 0 | E47: 0 | F47: 0 | G47: 0 | H47: 0 | I47: 0 | J47: 0 | K47: 0 | L47: 0 | M47: 285 | N47: 420 | O47: 490 | P47: 1000 | Q47: 980 | R47: 1630 | S47: 1425 | T47: 800 | U47: 2780 | V47: 2845 | W47: 1990 | X47: 875 | Y47: 2655 | AB47: =SUM(C47:AA47) -> 18175 | AC47: =AVERAGE(C47:Y47) -> 790.21739
B48: Varios | C48: 750 | D48: 60 | E48: 220 | F48: 240 | G48: 195 | H48: 120 | I48: 100 | J48: 35 | K48: 0 | L48: 150 | M48: 0 | N48: 0 | O48: 0 | P48: 0 | Q48: 0 | R48: 25 | S48: 100 | T48: 110 | U48: 135 | V48: 0 | W48: 455 | X48: 1225 | Y48: 285 | AB48: =SUM(C48:AA48) -> 4205 | AC48: =AVERAGE(C48:Y48) -> 182.82609
B49: Comisión Préstamo | C49: 400 | D49: 0 | E49: 0 | F49: 0 | G49: 0 | H49: 0 | I49: 0 | J49: 0 | K49: 0 | L49: 0 | M49: 0 | N49: 0 | O49: 0 | P49: 0 | Q49: 0 | R49: 0 | S49: 0 | T49: 0 | U49: 0 | V49: 0 | W49: 0 | X49: 0 | Y49: 0 | AB49: =SUM(C49:AA49) -> 400 | AC49: =AVERAGE(C49:Y49) -> 17.391304
B51: TOTAL GASTOS | C51: =SUM(C15:C50) - C30 -> 21996 | D51: =SUM(D15:D50) - D30 -> 19294 | E51: =SUM(E15:E50) - E30 -> 27015 | F51: =SUM(F15:F50) - F30 -> 23585 | G51: =SUM(G15:G50) - G30 -> 23200 | H51: =SUM(H15:H50) - H30 -> 29780 | I51: =SUM(I15:I50) - I30 -> 44265 | J51: =SUM(J15:J50) - J30 -> 39830 | ... M51: =SUM(M15:M50) - M30 -> 30035 | N51: =SUM(N15:N50) -> 33140 | O51: =SUM(O15:O50) -> 24305 | P51: =SUM(P15:P50) -> 36100 | Q51: =SUM(Q15:Q50) -> 27715 | R51: =SUM(R15:R50) -> 33930 | S51: =SUM(S15:S50) -> 29070 | T51: =SUM(T15:T50) -> 27695 | U51: =SUM(U15:U50) -> 31025 | ... Y51: =SUM(Y15:Y50) -> 48660 | AB51: =SUM(AB15:AB50) - AB30 -> 738513 | AC51: =AVERAGE(C51:Y51) -> 32157.522 | AD51: Gastos 2003-2024
B52: Promedio Caixa Catalunya | C52: 1241.6667 | D52: 825 | E52: 100 | F52: 116.66667 | G52: 116.66667 | H52: 300 | I52: 520 | J52: 180 | K52: 180 | L52: 110 | M52: 105 | N52: 104 | O52: 105 | P52: 105 | Q52: 100 | R52: 100 | S52: 250 | T52: 300 | U52: 350 | AC52: =AVERAGE(C52:Y52) -> 274.15789
B53: Promedio Cuenta Corriente | C53: 2947 | D53: 6460.75 | E53: 13954.667 | F53: 22538.75 | G53: 21226.25 | H53: 16817.083 | I53: 21825 | J53: 28665 | K53: 28665 | L53: 20575 | M53: 16000 | N53: 18390 | O53: 16145 | P53: 22500 | AC53: =AVERAGE(C53:Y53) -> 18336.393
B55: Promedio Gastos mensuales | C55: 1948.25 | D55: 1949.75 | E55: 2220.1667 | F55: 2034.5833 | G55: 1979.1667 | H55: 2625.8333 | I55: 3835 | J55: 3410 | K55: 3410 | L55: 2385 | M55: 2510 | N55: 2760 | O55: 2015 | P55: 3000 | R55: 2645 | U55: 2585 | AC55: =AVERAGE(C55:Y55) -> 2582.0469
B56: Promedio Ahorros totales | C56: 5633.3333 | D56: 9957.25 | E56: 18149.083 | F56: 27758.333 | G56: 34090.833 | H56: 38000.417 | I56: 43815 | J56: 50380 | K56: 50380 | L56: 42170 | M56: 37665 | N56: 40020 | O56: 38000 | P56: 37250 | AC56: =AVERAGE(C56:Y56) -> 33804.946
B57: Promedio Resto | C57: 3006.6667 | D57: 6973.9167 | E57: 14974.083 | F57: 23408.333 | G57: 21461.667 | H57: 14191.25 | I57: 18000 | J57: 25250 | K57: 25250 | L57: 18190 | M57: 13535 | N57: 15635 | O57: 14125 | P57: 19600 | AC57: =AVERAGE(C57:Y57) -> 16685.78
B58: RESTO Ingresos - Gastos | C58: 716 | D58: 6158 | E58: 11033 | F58: 10435 | G58: 2825 | H58: -5940 | I58: 10935 | J58: =J13-J51 -> 1250 | K58: =K13-K51 -> -6850 | L58: =L13-L51 -> -3790 | M58: =M13-M51 -> -4160 | N58: =N13-N51 -> -5275 | O58: =O13-O51 -> 4730 | P58: =P13-P51 -> -4475 | Q58: =Q13-Q51 -> 3550 | ... Y58: =Y13-Y51 -> -2460 | AB58: =SUM(C58:X58) -> 16489 | AC58: =AVERAGE(C58:Y58) -> 609.95652 | AD58: Ahorro 2003-2024
C59: 2003 | D59: 2004 | E59: 2005 | F59: 2006 | G59: 2007 | H59: 2008 | I59: 2009 | J59: 2010 | K59: 2011 | L59: 2012 | M59: 2013 | N59: 2014 | O59: 2015 | P59: 2016 | Q59: 2017 | R59: 2018 | S59: 2019 | T59: 2020 | U59: 2021 | V59: 2022 | W59: 2023 | X59: 2024 | Y59: 2025 | Z59: 2026 | AA59: 2027 | AB59: =COUNTA(C59:AA59) -> 25 | AC59: años
H64: =370+645+390 -> 1405
H65: =180+165+50 -> 395

Sheet Graficos
C5: 1991 | D5: 1992 | E5: 1993 | F5: 1994 | G5: 1995 | H5: 1996 | I5: 1997 | J5: 1998 | K5: 1999 | L5: 2000 | M5: 2001 | N5: 2002 | O5: 2003 | P5: 2004 | Q5: 2005 | R5: 2006 | S5: 2007 | T5: 2008 | U5: 2009 | V5: 2010 | W5: 2011 | X5: 2012 | Y5: 2013 | Z5: 2014 | AA5: 2015
B6: Ingresos | C6: 5190.94 | D6: 4297.24 | E6: 5736.06 | F6: 9315.69 | G6: 9934.73 | H6: 12278.68 | I6: 12278.68 | J6: 11629.58 | K6: 14123.78 | L6: 13522.77 | M6: 16236 | N6: 20900 | O6: 25595 | P6: 29655 | Q6: 38875 | R6: 34850 | S6: 26575 | T6: 26700 | U6: 56950 | V6: 41080 | W6: 19720 | X6: 24845 | Y6: 25875 | Z6: 27865 | AA6: 29035 | AB6: Ingresos
B7: Gastos | C7: 5339.99 | D7: 4318.27 | E7: 4946.33 | F7: 9177.45 | G7: 10920.39 | H7: 11467.31 | I7: 12218.58 | J7: 11719.74 | K7: 14328.13 | L7: 14003.58 | M7: 14997 | N7: 19500 | O7: 21996 | P7: 19294 | Q7: 27015 | R7: 23585 | S7: 23200 | T7: 29780 | U7: 44265 | V7: 39830 | W7: 26570 | X7: 28635 | Y7: 30135 | Z7: 33140 | AA7: 24200 | AB7: Gastos
C8: =C6-C7 -> -149.05 | D8: =D6-D7 -> -21.03 | E8: =E6-E7 -> 789.73 | F8: =F6-F7 -> 138.24 | G8: =G6-G7 -> -985.66 | H8: =H6-H7 -> 811.37 | I8: =I6-I7 -> 60.1 | J8: =J6-J7 -> -90.16 | ... AA8: =AA6-AA7 -> 4835
M10: 2016 | N10: 2017 | O10: 2018 | P10: 2019 | Q10: 2020 | R10: 2021 | S10: 2022 | T10: 2023 | U10: 2024 | V10: 2025 | W10: 2026 | X10: 2027 | Y10: 2028 | Z10: 2029 | AA10: 2030
D11: Total INGRESOS | E11: =SUM(C6:AA6)+SUM(M11:AA11) -> 902969.15 | G11: Saldo TOTAL | H11: =E11-E12 -> 30207.38 | M11: 31595 | N11: 31265 | O11: 31750 | P11: 31575 | Q11: 32245 | R11: 35815 | S11: 37330 | T11: 37980 | U11: 44150 | V11: 46200 | AB11: Ingresos
D12: Total GASTOS | E12: =SUM(C7:AA7)+SUM(M12:AA12) -> 872761.77 | M12: 36075 | N12: 27740 | O12: 34135 | P12: 29100 | Q12: 27695 | R12: 31025 | S12: 38670 | T12: 46435 | U12: 48705 | V12: 48600 | AB12: Gastos
M13: =M11-M12 -> -4480 | N13: =N11-N12 -> 3525 | O13: =O11-O12 -> -2385 | P13: =P11-P12 -> 2475 | Q13: =Q11-Q12 -> 4550 | R13: =R11-R12 -> 4790 | S13: =S11-S12 -> -1340 | T13: =T11-T12 -> -8455 | ... V13: =V11-V12 -> -2400
C43: Ingresos | D43: Gastos
A44: 1991 | B44: Ene 91 | C44: 325 | D44: 335 | E44: =C44-D44 -> -10
B45: Febrero | C45: 0 | D45: 405 | E45: =C45-D45 -> -405 | H45: 2020
B46: Marzo | C46: 1085 | D46: 450 | E46: =C46-D46 -> 635 | H46: Concepto | I46: Ene | J46: Mar | K46: May | L46: Jul | M46: Oct | N46: Dic
B47: Abril | C47: 545 | D47: 220 | E47: =C47-D47 -> 325 | H47: CC | I47: 27000 | J47: 26500 | K47: 28500 | L47: 28500 | M47: 31500 | N47: 32500 | O47: =N47/$N$51 -> 0.56788398
B48: Mayo | C48: 545 | D48: 430 | E48: =C48-D48 -> 115 | H48: SIAL | I48: 8900 | J48: 8950 | K48: 9000 | L48: 9050 | M48: 9150 | N48: 9230 | O48: =N48/$N$51 -> 0.16127905
B49: Junio | C49: 545 | D49: 425 | E49: =C49-D49 -> 120 | H49: PP | I49: 13750 | J49: 13700 | K49: 13500 | L49: 13950 | M49: 14675 | N49: 15500 | O49: =N49/$N$51 -> 0.27083697
B50: Julio | C50: 545 | D50: 360 | E50: =C50-D50 -> 185
B51: Agosto | C51: 545 | D51: 735 | E51: =C51-D51 -> -190 | H51: TOTAL | I51: 49650 | J51: 49150 | K51: 51000 | L51: 51500 | M51: 55325 | N51: 57230
B52: Septiembre | C52: 545 | D52: 665 | E52: =C52-D52 -> -120 | H52: 2021
B53: Octubre | C53: 545 | D53: 1355 | E53: =C53-D53 -> -810 | H53: Concepto | I53: Ene | J53: Mar | K53: May | L53: Jul | M53: Oct | N53: Dic
B54: Noviembre | C54: 0 | D54: 175 | E54: =C54-D54 -> -175 | H54: CC | I54: 36000 | J54: 37000 | K54: 49000 | L54: 50000 | M54: 49000 | N54: 47350 | O54: =N54/$N$58 -> 0.73410853
B55: Diciembre | C55: 0 | D55: 25 | E55: =C55-D55 -> -25 | H55: SIAL | I55: 10000 | J55: 10075 | K55: --- | L55: --- | M55: --- | N55: --- | O55: ---
A56: 1992 | B56: Ene 92 | C56: 305 | D56: 125 | E56: =C56-D56 -> 180 | H56: PP | I56: 16000 | J56: 15750 | K56: 16400 | L56: 16375 | M56: 17000 | N56: 17250 | O56: =N56/$N$58 -> 0.26744186
B57: Febrero | C57: 0 | D57: 50 | E57: =C57-D57 -> -50
B58: Marzo | C58: 170 | D58: 245 | E58: =C58-D58 -> -75 | H58: TOTAL | I58: 62000 | J58: 62825 | K58: 65400 | L58: 66375 | M58: 66000 | N58: 64500
B59: Abril | C59: 270 | D59: 315 | E59: =C59-D59 -> -45 | H59: 2022
B60: Mayo | C60: 270 | D60: 150 | E60: =C60-D60 -> 120 | H60: Concepto | I60: Ene | J60: Mar | K60: May | L60: Jul | M60: Oct | N60: Dic
B61: Junio | C61: 270 | D61: 240 | E61: =C61-D61 -> 30 | H61: CC | I61: 48000 | J61: 41750 | K61: 50000 | L61: 50700 | M61: 47000 | N61: 46000 | O61: =N61/$N$65 -> 0.69355447
B62: Julio | C62: 450 | D62: 275 | E62: =C62-D62 -> 175 | H62: PP (1) | I62: 18115 | J62: 16450 | K62: 15000 | L62: 15000 | M62: 14750 | N62: 16550 | O62: =N62/$N$65 -> 0.24952884
B63: Agosto | C63: 1490 | D63: 695 | E63: =C63-D63 -> 795 | H63: INV (2) | I63: --- | J63: --- | K63: --- | L63: --- | M63: 3300 | N63: 3775 | O63: =N63/$N$65 -> 0.056916698
B64: Septiembre | C64: 0 | D64: 600 | E64: =C64-D64 -> -600
B65: Octubre | C65: 365 | D65: 775 | E65: =C65-D65 -> -410 | H65: TOTAL | I65: =SUM(I61:I63) -> 66115 | J65: =SUM(J61:J63) -> 58200 | K65: =SUM(K61:K63) -> 65000 | L65: =SUM(L61:L63) -> 65700 | M65: =SUM(M61:M63) -> 65050 | N65: =SUM(N61:N63) -> 66325
B66: Noviembre | C66: 365 | D66: 535 | E66: =C66-D66 -> -170 | H66: 2023
B67: Diciembre | C67: 365 | D67: 330 | E67: =C67-D67 -> 35 | H67: Concepto | I67: Ene | J67: Mar | K67: May | L67: Jul | M67: Oct | N67: Dic
A68: 1993 | B68: Ene 93 | C68: 365 | D68: 320 | E68: =C68-D68 -> 45 | H68: CC | I68: 47000 | J68: 37695 | K68: 42000 | L68: 41750 | M68: 41870 | N68: 39500 | O68: =N68/$N$72 -> 0.57163531
B69: Febrero | C69: 365 | D69: 300 | E69: =C69-D69 -> 65 | H69: PP (1) | I69: 16125 | J69: 16750 | K69: 16325 | L69: 17540 | M69: 17300 | N69: 18175 | O69: =N69/$N$72 -> 0.2630246
B70: Marzo | C70: 365 | D70: 365 | E70: =C70-D70 -> 0 | H70: INV (2) | I70: 4750 | J70: 5595 | K70: 7925 | L70: 8170 | M70: 10250 | N70: 11425 | O70: =N70/$N$72 -> 0.16534009
B71: Abril | C71: 365 | D71: 365 | E71: =C71-D71 -> 0
B72: Mayo | C72: 365 | D72: 345 | E72: =C72-D72 -> 20 | H72: TOTAL | I72: =SUM(I68:I70) -> 67875 | J72: =SUM(J68:J70) -> 60040 | K72: =SUM(K68:K70) -> 66250 | L72: =SUM(L68:L70) -> 67460 | M72: =SUM(M68:M70) -> 69420 | N72: =SUM(N68:N70) -> 69100
B73: Junio | C73: 1870 | D73: 195 | E73: =C73-D73 -> 1675
B74: Julio | C74: 365 | D74: 515 | E74: =C74-D74 -> -150 | H74: 2024
B75: Agosto | C75: 365 | D75: 225 | E75: =C75-D75 -> 140 | H75: Concepto | I75: Ene | J75: Mar | K75: May | L75: Jul | M75: Oct | N75: Dic
B76: Septiembre | C76: 0 | D76: 625 | E76: =C76-D76 -> -625 | H76: CC | I76: 39850 | J76: 37425 | K76: 41200 | L76: 41205 | M76: 37240 | N76: 36600 | O76: =N76/$N$80 -> 0.46713465
B77: Octubre | C77: 365 | D77: 745 | E77: =C77-D77 -> -380 | H77: PP (1) | I77: 18650 | J77: 20085 | K77: 20375 | L77: 21465 | M77: 22135 | N77: 24020 | O77: =N77/$N$80 -> 0.30657307
B78: Noviembre | C78: 385 | D78: 275 | E78: =C78-D78 -> 110 | H78: INV (2) | I78: 12325 | J78: 12625 | K78: 14250 | L78: 15250 | M78: 16700 | N78: 17730 | O78: =N78/$N$80 -> 0.22629228
B79: Diciembre | C79: 610 | D79: 665 | E79: =C79-D79 -> -55
A80: 1994 | B80: Ene 94 | C80: 1355 | D80: 2325 | E80: =C80-D80 -> -970 | H80: TOTAL | I80: =SUM(I76:I78) -> 70825 | J80: =SUM(J76:J78) -> 70135 | K80: =SUM(K76:K78) -> 75825 | L80: =SUM(L76:L78) -> 77920 | M80: =SUM(M76:M78) -> 76075 | N80: =SUM(N76:N78) -> 78350
B81: Febrero | C81: 670 | D81: 535 | E81: =C81-D81 -> 135
B82: Marzo | C82: 670 | D82: 665 | E82: =C82-D82 -> 5 | H82: 2025
B83: Abril | C83: 670 | D83: 495 | E83: =C83-D83 -> 175 | H83: Concepto | I83: Ene | J83: Mar | K83: May | L83: Jul | M83: Oct | N83: Dic
B84: Mayo | C84: 670 | D84: 305 | E84: =C84-D84 -> 365 | H84: CC | I84: 36325 | J84: 34295 | K84: 40425 | L84: 37490 | M84: 34625 | N84: 33600 | O84: =N84/$N$88 -> 0.38327725
B85: Junio | C85: 670 | D85: 305 | E85: =C85-D85 -> 365 | H85: PP (1) | I85: 23735 | J85: 23335 | K85: 21665 | L85: 24260 | M85: 25875 | N85: 27000 | O85: =N85/$N$88 -> 0.30799065
B86: Julio | C86: 665 | D86: 520 | E86: =C86-D86 -> 145 | H86: INV (2) | I86: 18075 | J86: 19475 | K86: 21585 | L86: 23000 | M86: 25455 | N86: 27065 | O86: =N86/$N$88 -> 0.30873211
B87: Agosto | C87: 665 | D87: 485 | E87: =C87-D87 -> 180
B88: Septiembre | C88: 665 | D88: 510 | E88: =C88-D88 -> 155 | H88: TOTAL | I88: =SUM(I84:I86) -> 78135 | J88: =SUM(J84:J86) -> 77105 | K88: =SUM(K84:K86) -> 83675 | L88: =SUM(L84:L86) -> 84750 | M88: =SUM(M84:M86) -> 85955 | N88: =SUM(N84:N86) -> 87665
B89: Octubre | C89: 665 | D89: 1325 | E89: =C89-D89 -> -660
B90: Noviembre | C90: 665 | D90: 630 | E90: =C90-D90 -> 35 | H90: 2026
B91: Diciembre | C91: 1325 | D91: 1095 | E91: =C91-D91 -> 230 | H91: Concepto | I91: Ene | J91: Mar | K91: May | L91: Jul | M91: Oct | N91: Dic
A92: 1995 | B92: Ene 95 | C92: 665 | D92: 965 | E92: =C92-D92 -> -300 | H92: CC | I92: 31700 | J92: 30275 | K92: 33750 | O92: =K92/$K$96 -> 0.34783057
B93: Febrero | C93: 665 | D93: 510 | E93: =C93-D93 -> 155 | H93: PP (1) | I93: 27535 | J93: 28100 | K93: 29300 | O93: =K93/$K$96 -> 0.30196846
B94: Marzo | C94: 1325 | D94: 1255 | E94: =C94-D94 -> 70 | H94: INV (2) | I94: 27330 | J94: 29900 | K94: 33980 | O94: =K94/$K$96 -> 0.35020097
B95: Abril | C95: 665 | D95: 1265 | E95: =C95-D95 -> -600
B96: Mayo | C96: 855 | D96: 915 | E96: =C96-D96 -> -60 | H96: TOTAL | I96: =SUM(I92:I94) -> 86565 | J96: =SUM(J92:J94) -> 88275 | K96: =SUM(K92:K94) -> 97030 | L96: =SUM(L92:L94) -> 0 | M96: =SUM(M92:M94) -> 0 | N96: =SUM(N92:N94) -> 0
B97: Junio | C97: 1795 | D97: 1095 | E97: =C97-D97 -> 700 | K97: (maximo)
B98: Julio | C98: 820 | D98: 745 | E98: =C98-D98 -> 75 | H98: (1) PP Caixabank + Santander
B99: Agosto | C99: 2690 | D99: 1000 | E99: =C99-D99 -> 1690 | H99: (2) Inversion Degiro + BBVA (FTEs + Fondo) + Ocean Broker
B100: Septiembre | C100: 0 | D100: 500 | E100: =C100-D100 -> -500
B101: Octubre | C101: 0 | D101: 825 | E101: =C101-D101 -> -825
B102: Noviembre | C102: 0 | D102: 695 | E102: =C102-D102 -> -695
B103: Diciembre | C103: 485 | D103: 810 | E103: =C103-D103 -> -325
A104: 1996 | B104: Ene 96 | C104: 605 | D104: 656 | E104: =C104-D104 -> -51
B105: Febrero | C105: 900 | D105: 775 | E105: =C105-D105 -> 125
B106: Marzo | C106: 815 | D106: 905 | E106: =C106-D106 -> -90
B107: Abril | C107: 675 | D107: 685 | E107: =C107-D107 -> -10
B108: Mayo | C108: 1435 | D108: 1330 | E108: =C108-D108 -> 105
B109: Junio | C109: 810 | D109: 975 | E109: =C109-D109 -> -165
B110: Julio | C110: 1625 | D110: 1255 | E110: =C110-D110 -> 370
B111: Agosto | C111: 875 | D111: 785 | E111: =C111-D111 -> 90
B112: Septiembre | C112: 875 | D112: 840 | E112: =C112-D112 -> 35
B113: Octubre | C113: 1295 | D113: 1165 | E113: =C113-D113 -> 130
B114: Noviembre | C114: 875 | D114: 1025 | E114: =C114-D114 -> -150
B115: Diciembre | C115: 1540 | D115: 1090 | E115: =C115-D115 -> 450
A116: 1997 | B116: Ene 97 | C116: 875 | D116: 610 | E116: =C116-D116 -> 265
B117: Febrero | C117: 875 | D117: 1745 | E117: =C117-D117 -> -870
B118: Marzo | C118: 605 | D118: 605 | E118: =C118-D118 -> 0
B119: Abril | C119: 905 | D119: 1140 | E119: =C119-D119 -> -235
B120: Mayo | C120: 1145 | D120: 1170 | E120: =C120-D120 -> -25
B121: Junio | C121: 3545 | D121: 2060 | E121: =C121-D121 -> 1485
B122: Julio | C122: 305 | D122: 745 | E122: =C122-D122 -> -440
B123: Agosto | C123: 815 | D123: 665 | E123: =C123-D123 -> 150
B124: Septiembre | C124: 815 | D124: 710 | E124: =C124-D124 -> 105
B125: Octubre | C125: 815 | D125: 525 | E125: =C125-D125 -> 290
B126: Noviembre | C126: 815 | D126: 1340 | E126: =C126-D126 -> -525
B127: Diciembre | C127: 815 | D127: 945 | E127: =C127-D127 -> -130
A128: 1998 | B128: Ene 98 | C128: 815 | D128: 1035 | E128: =C128-D128 -> -220
B129: Febrero | C129: 815 | D129: 945 | E129: =C129-D129 -> -130
B130: Marzo | C130: 1055 | D130: 945 | E130: =C130-D130 -> 110
B131: Abril | C131: 1055 | D131: 1180 | E131: =C131-D131 -> -125
B132: Mayo | C132: 1055 | D132: 945 | E132: =C132-D132 -> 110
B133: Junio | C133: 1025 | D133: 755 | E133: =C133-D133 -> 270
B134: Julio | C134: 1025 | D134: 1325 | E134: =C134-D134 -> -300
...

Sheet Ordenes
B4: Fecha | C4: Producto | D4: ISIN | E4: Bolsa | F4: Centro | G4: Número | H4: Precio | I4: Valor local | J4: Costes transac. | K4: Total
B20: 46113 | C20: ELECNOR | D20: ES0129743318 | E20: MAD | F20: XMAD | G20: 5 | H20: 34.9 | I20: =H20*G20 -> 174.5 | J20: -10.3 | K20: =-I20+J20 -> -184.8
B21: 46113 | C21: ACS | D21: ES0167050915 | E21: MAD | F21: XMAD | G21: 5 | H21: 112.35 | I21: =H21*G21 -> 561.75 | J21: -11 | K21: =-I21+J21 -> -572.75
B22: 46099 | C22: PFIZER | D22: US7170811035 | E22: XET | F22: XETB | G22: 5 | H22: 23.59 | I22: =H22*G22 -> 117.95 | J22: -3.9 | K22: =-I22+J22 -> -121.85
B23: 46099 | C23: ISHARES MSCI WOR D | D23: IE00B0M62Q58 | E23: EAM | F23: XAMS | G23: 5 | H23: 80.765 | I23: =H23*G23 -> 403.825 | J23: -3 | K23: =-I23+J23 -> -406.825
B24: 46099 | C24: ISHARES STOXX EUROPE 600 UCITS ETF (DE) | D24: DE0002635307 | E24: XET | F24: XETA | G24: 5 | H24: 59.18 | I24: =H24*G24 -> 295.9 | J24: -3 | K24: =-I24+J24 -> -298.9
B25: 46099 | C25: LTC PROPERTIES INC | D25: US5021751020 | E25: TDG | F25: XGAT | G25: 5 | H25: 33.64 | I25: =H25*G25 -> 168.2 | J25: -3.9 | K25: =-I25+J25 -> -172.1
B26: 46075 | C26: LOGISTA | D26: ES0105027009 | E26: MAD | F26: XMAD | G26: 5 | H26: 33.54 | I26: =H26*G26 -> 167.7 | J26: -10.3 | K26: =-I26+J26 -> -178
B27: 46065 | C27: Kraft Heinz Co | D27: US5007541064 | E27: TDG | F27: XGAT | G27: 5 | H27: 20.61 | I27: =H27*G27 -> 103.05 | J27: -3.9 | K27: =-I27+J27 -> -106.95
B28: 46046 | C28: ELECNOR | D28: ES0129743318 | E28: MAD | F28: XMAD | G28: 5 | H28: 25.9 | I28: =H28*G28 -> 129.5 | J28: -10.3 | K28: =-I28+J28 -> -139.8
B29: 46032 | C29: ISHARES PROP GLO | D29: IE00B1FZS350 | E29: EAM | F29: XAMS | G29: 5 | H29: 21.07 | I29: =H29*G29 -> 105.35 | J29: -3 | K29: =-I29+J29 -> -108.35 | L29: 2026 | M29: Año V
B30: 46032 | C30: DIAGEO | D30: GB0002374006 | E30: TDG | F30: XGAT | G30: 5 | H30: 19 | I30: =H30*G30 -> 95 | J30: -3.9 | K30: =-I30+J30 -> -98.9 | L30: =SUM(K6:K31) -> -2432.785 | M30: =SUM(I6:I31) -> 2322.725 | O30: comprobacion
B31: 46024 | C31: CUSTODIA DE VALORES | D31: ****** | E31: --- | F31: --- | G31: --- | H31: ---- | I31: --- | J31: -43.56 | K31: -43.56 | L31: Gasto | M31: Cartera | N31: =-L30-M30 -> 110.06 | O31: =SUM(J6:J31) -> -110.06
B32: 46012 | C32: LOGISTA | D32: ES0105027009 | E32: MAD | F32: XMAD | G32: 5 | H32: 29.66 | I32: =H32*G32 -> 148.3 | J32: -10.3 | K32: =-I32+J32 -> -158.6 | N32: Costes(comisiones)
B33: 45997 | C33: AT&T INC | D33: US00206R1023 | E33: TDG | F33: XGAT | G33: 5 | H33: 21.7 | I33: =H33*G33 -> 108.5 | J33: -3.9 | K33: =-I33+J33 -> -112.4
B34: 45997 | C34: ISHARES STOXX EUROPE 600 UCITS ETF (DE) | D34: DE0002635307 | E34: XET | F34: XETA | G34: 3 | H34: 57.48 | I34: =H34*G34 -> 172.44 | J34: -3 | K34: =-I34+J34 -> -175.44
B35: 45977 | C35: RED ELECTRICA | D35: ES0173093024 | E35: MAD | F35: XMAD | G35: 10 | H35: 15.08 | I35: =H35*G35 -> 150.8 | J35: -10.3 | K35: =-I35+J35 -> -161.1
B36: 45959 | C36: ISHARES STOXX EUROPE 600 UCITS ETF (DE) | D36: DE0002635307 | E36: XET | F36: XETA | G36: 2 | H36: 57.07 | I36: =H36*G36 -> 114.14 | J36: -3 | K36: =-I36+J36 -> -117.14
B37: 45959 | C37: COMCAST CORP | D37: US20030N1019 | E37: TDG | F37: XGAT | G37: 5 | H37: 24.705 | I37: =H37*G37 -> 123.525 | J37: -3.9 | K37: =-I37+J37 -> -127.425
B38: 45950 | C38: ENAGAS | D38: ES0130960018 | E38: MAD | F38: XMAD | G38: 10 | H38: 13.875 | I38: =H38*G38 -> 138.75 | J38: -10.3 | K38: =-I38+J38 -> -149.05
B39: 45932 | C39: INVESCO S&P 500 HIGH DIV LOW VOL UCITS ETF DIS | D39: IE00BWTN6Y99 | E39: XET | F39: XETA | G39: 5 | H39: 31.47 | I39: =H39*G39 -> 157.35 | J39: -3 | K39: =-I39+J39 -> -160.35
B40: 45931 | C40: PFIZER | D40: US7170811035 | E40: XET | F40: XETB | G40: 5 | H40: 21.9 | I40: =H40*G40 -> 109.5 | J40: -4.9 | K40: =-I40+J40 -> -114.4
B41: 45924 | C41: IBERDROLA | D41: ES0144580Y14 | E41: MAD | F41: XMAD | G41: 10 | H41: 15.64 | I41: =H41*G41 -> 156.4 | J41: -10.3 | K41: =-I41+J41 -> -166.7
B42: 45904 | C42: VERIZON COMMUNICATIONS INC | D42: US92343V1044 | E42: XET | F42: XETB | G42: 5 | H42: 37.68 | I42: =H42*G42 -> 188.4 | J42: -4.9 | K42: =-I42+J42 -> -193.3
B43: 45901 | C43: ISHARES PROP GLO | D43: IE00B1FZS350 | E43: EAM | F43: XAMS | G43: 5 | H43: 20.875 | I43: =H43*G43 -> 104.375 | J43: -1 | K43: =-I43+J43 -> -105.375
B44: 45901 | C44: SHELL PLC | D44: GB00BP6MXD84 | E44: EAM | F44: XAMS | G44: 5 | H44: 31.565 | I44: =H44*G44 -> 157.825 | J44: -4.9 | K44: =-I44+J44 -> -162.725
... B47: 45852 | C47: LOGISTA | D47: ES0105027009 | E47: MAD | F47: XMAD | G47: 5 | H47: 27.91 | I47: =H47*G47 -> 139.55 | J47: -10.3 | K47: =-I47+J47 -> -149.85
B48: 45839 | C48: CUSTODIA DE VALORES | D48: ****** | E48: --- | F48: --- | G48: --- | H48: ---- | I48: --- | J48: -43.56 | K48: -43.56
B49: 45835 | C49: INVESCO S&P 500 HIGH DIV LOW VOL UCITS ETF DIS | D49: IE00BWTN6Y99 | E49: XET | F49: XETA | G49: 5 | H49: 30 | I49: =H49*G49 -> 150 | J49: -3 | K49: =-I49+J49 -> -153
B50: 45835 | C50: LTC PROPERTIES INC | D50: US5021751020 | E50: TDG | F50: XGAT | G50: 5 | H50: 29.75 | I50: =H50*G50 -> 148.75 | J50: -3.9 | K50: =-I50+J50 -> -152.65
B51: 45820 | C51: RED ELECTRICA | D51: ES0173093024 | E51: MAD | F51: XMAD | G51: 10 | H51: 17.86 | I51: =H51*G51 -> 178.6 | J51: -10.36 | K51: =-I51+J51 -> -188.96
B52: 45794 | C52: ENAGAS | D52: ES0130960018 | E52: MAD | F52: XMAD | G52: 10 | H52: 13.445 | I52: =H52*G52 -> 134.45 | J52: -10.3 | K52: =-I52+J52 -> -144.75
B53: 45782 | C53: INVESCO S&P 500 HIGH DIV LOW VOL UCITS ETF DIS | D53: IE00BWTN6Y99 | E53: XET | F53: XETA | G53: 5 | H53: 31.5 | I53: =H53*G53 -> 157.5 | J53: -3 | K53: =-I53+J53 -> -160.5
B54: 45782 | C54: INTEL CORP | D54: US4581401001 | E54: TDG | F54: XGAT | G54: 5 | H54: 18 | I54: =H54*G54 -> 90 | J54: -3.9 | K54: =-I54+J54 -> -93.9
B55: 45782 | C55: DIAGEO | D55: GB0002374006 | E55: TDG | F55: XGAT | G55: 5 | H55: 25.215 | I55: =H55*G55 -> 126.075 | J55: -3.9 | K55: =-I55+J55 -> -129.975
B56: 45773 | C56: ISHARES PROP GLO | D56: IE00B1FZS350 | E56: EAM | F56: XAMS | G56: 5 | H56: 20.3 | I56: =H56*G56 -> 101.5 | J56: -1 | K56: =-I56+J56 -> -102.5
B57: 45773 | C57: UNILEVER | D57: GB00B10RZP78 | E57: EAM | F57: XAMS | G57: 5 | H57: 55 | I57: =H57*G57 -> 275 | J57: -4.9 | K57: =-I57+J57 -> -279.9
B58: 45771 | C58: IBERDROLA | D58: ES0144580Y14 | E58: MAD | F58: XMAD | G58: 10 | H58: 15.33 | I58: =H58*G58 -> 153.3 | J58: -10.3 | K58: =-I58+J58 -> -163.6
B59: 45743 | C59: ELECNOR | D59: ES0129743318 | E59: MAD | F59: XMAD | G59: 10 | H59: 17.62 | I59: =H59*G59 -> 176.2 | J59: -10 | K59: =-I59+J59 -> -186.2
B60: 45741 | C60: INVESCO S&P 500 HIGH DIV LOW VOL UCITS ETF DIS | D60: IE00BWTN6Y99 | E60: XET | F60: XETA | G60: 5 | H60: 34.5 | I60: =H60*G60 -> 172.5 | J60: -3 | K60: =-I60+J60 -> -175.5
... B68: 45716 | C68: UNILEVER | D68: GB00B10RZP78 | E68: EAM | F68: XAMS | G68: 5 | H68: 54.16 | I68: =H68*G68 -> 270.8 | J68: -4.9 | K68: =-I68+J68 -> -275.7
B69: 45679 | C69: LOGISTA | D69: ES0105027009 | E69: MAD | F69: XMAD | G69: 5 | H69: 30 | I69: =H69*G69 -> 150 | J69: -10.3 | K69: =-I69+J69 -> -160.3 | L69: 2025 | M69: Año IV
B70: 45692 | C70: WALGREENS BOOTS ALLIANCE INC | D70: US9314271084 | E70: TDG | F70: XGAT | G70: 10 | H70: 9.42 | I70: =H70*G70 -> 94.2 | J70: -3.9 | K70: =-I70+J70 -> -98.1 | L70: =SUM(K32:K71) -> -6677.43 | M70: =SUM(I32:I71) -> 6416.73 | O70: comprobacion
B71: 45692 | C71: ISHARES PROP GLO | D71: IE00B1FZS350 | E71: EAM | F71: XAMS | G71: 5 | H71: 22.32 | I71: =H71*G71 -> 111.6 | J71: -1 | K71: =-I71+J71 -> -112.6 | L71: Gasto | M71: Cartera | N71: =-L70-M70 -> 260.7 | O71: =SUM(J32:J71) -> -260.7
B72: 45653 | C72: SHELL PLC | D72: GB00BP6MXD84 | E72: EAM | F72: XAMS | G72: 2 | H72: 30 | I72: =H72*G72 -> 60 | J72: -4.9 | K72: =-I72+J72 -> -64.9 | N72: Costes(comisiones)
B73: 45653 | C73: UNILEVER | D73: GB00B10RZP78 | E73: EAM | F73: XAMS | G73: 5 | H73: 55 | I73: =H73*G73 -> 275 | J73: -4.9 | K73: =-I73+J73 -> -279.9
B74: 45653 | C74: Kraft Heinz Co | D74: US5007541064 | E74: TDG | F74: XGAT | G74: 3 | H74: 30 | I74: =H74*G74 -> 90 | J74: -3.9 | K74: =-I74+J74 -> -93.9
B75: 45647 | C75: ACS | D75: ES0167050915 | E75: MAD | F75: XMAD | G75: 5 | H75: 47.46 | I75: =H75*G75 -> 237.3 | J75: -10.5 | K75: =-I75+J75 -> -247.8
B76: 45623 | C76: LOGISTA | D76: ES0105027009 | E76: MAD | F76: XMAD | G76: 5 | H76: 30 | I76: =H76*G76 -> 150 | J76: -10.3 | K76: =-I76+J76 -> -160.3
B77: 45565 | C77: ELECNOR | D77: ES0129743318 | E77: MAD | F77: XMAD | G77: 10 | H77: 19.04 | I77: =H77*G77 -> 190.4 | J77: -10.38 | K77: =-I77+J77 -> -200.78
B78: 45565 | C78: DIAGEO | D78: GB0002374006 | E78: TDG | F78: XGAT | G78: 5 | H78: 31.995 | I78: =H78*G78 -> 159.975 | J78: -3.9 | K78: =-I78+J78 -> -163.875
B79: 45565 | C79: INTEL CORP | D79: US4581401001 | E79: TDG | F79: XGAT | G79: 5 | H79: 21.465 | I79: =H79*G79 -> 107.325 | J79: -3.9 | K79: =-I79+J79 -> -111.225
B80: 45565 | C80: LTC PROPERTIES INC | D80: US5021751020 | E80: TDG | F80: XGAT | G80: 4 | H80: 33 | I80: =H80*G80 -> 132 | J80: -3.9 | K80: =-I80+J80 -> -135.9
B81: 45565 | C81: ISHARES PROP GLO | D81: IE00B1FZS350 | E81: EAM | F81: XAMS | G81: 5 | H81: 22.7 | I81: =H81*G81 -> 113.5 | J81: -1 | K81: =-I81+J81 -> -114.5
B82: 45458 | C82: RED ELECTRICA | D82: ES0173093024 | E82: MAD | F82: XMAD | G82: 10 | H82: 17.4 | I82: =H82*G82 -> 174 | J82: -10.5 | K82: =-I82+J82 -> -184.5
B83: 45456 | C83: WALGREENS BOOTS ALLIANCE INC | D83: US9314271084 | E83: TDG | F83: XGAT | G83: 10 | H83: 14.498 | I83: =H83*G83 -> 144.98 | J83: -3.9 | K83: =-I83+J83 -> -148.88
B84: 45456 | C84: ISHARES MSCI WOR D | D84: IE00B0M62Q58 | E84: EAM | F84: XAMS | G84: 3 | H84: 69.095 | I84: =H84*G84 -> 207.285 | J84: -3 | K84: =-I84+J84 -> -210.285
... B95: 45372 | C95: ACS | D95: ES0167050915 | E95: MAD | F95: XMAD | G95: 5 | H95: 39.6 | I95: =H95*G95 -> 198 | J95: -10.4 | K95: =-I95+J95 -> -208.4
B96: 45323 | C96: COMISION DEGIRO | D96: --- | E96: --- | F96: --- | G96: --- | H96: ---- | I96: --- | J96: -7.5 | K96: -7.5
B97: 45347 | C97: ENAGAS | D97: ES0130960018 | E97: MAD | F97: XMAD | G97: 5 | H97: 14.82 | I97: =H97*G97 -> 74.1 | J97: -10.1 | K97: =-I97+J97 -> -84.2 | L97: 2024 | M97: Año III
B98: 45314 | C98: LOGISTA | D98: ES0105027009 | E98: MAD | F98: XMAD | G98: 5 | H98: 25.32 | I98: =H98*G98 -> 126.6 | J98: -10.2 | K98: =-I98+J98 -> -136.8 | L98: =SUM(K72:K99) -> -3915.675 | M98: =SUM(I72:I99) -> 3715.795 | O98: comprobacion
B99: 45292 | C99: CUSTODIA DE VALORES | D99: ******** | E99: --- | F99: --- | G99: --- | H99: ---- | I99: --- | J99: -38 | K99: -38 | L99: Gasto | M99: Cartera | N99: =-L98-M98 -> 199.88 | O99: =SUM(J72:J99) -> -199.88
B100: 45653 | C100: Kraft Heinz Co | D100: US5007541064 | E100: TDG | F100: XGAT | G100: 5 | H100: 33.14 | I100: =H100*G100 -> 165.7 | J100: -3.9 | K100: =-I100+J100 -> -169.6 | N100: Costes(comisiones)
B101: 45653 | C101: INVESCO S&P 500 HIGH DIV LOW VOL UCITS ETF DIS | D101: IE00BWTN6Y99 | E101: XET | F101: XETA | G101: 5 | H101: 29 | I101: =H101*G101 -> 145 | J101: -3 | K101: =-I101+J101 -> -148
B102: 45653 | C102: LTC PROPERTIES INC | D102: US5021751020 | E102: TDG | F102: XGAT | G102: 3 | H102: 29.6 | I102: =H102*G102 -> 88.8 | J102: -3.9 | K102: =-I102+J102 -> -92.7
B103: 45653 | C103: LOGISTA | D103: ES0105027009 | E103: MAD | F103: XMAD | G103: 5 | H103: 24.06 | I103: =H103*G103 -> 120.3 | J103: -10.2 | K103: =-I103+J103 -> -130.5
B104: 45253 | C104: ENAGAS | D104: ES0130960018 | E104: MAD | F104: XMAD | G104: 5 | H104: 16.58 | I104: =H104*G104 -> 82.9 | J104: -10.8 | K104: =-I104+J104 -> -93.7
B105: 45231 | C105: ISHARES MSCI WOR D | D105: IE00B0M62Q58 | E105: EAM | F105: XAMS | G105: 20 | H105: 57 | I105: =H105*G105 -> 1140 | J105: -1 | K105: =-I105+J105 -> -1141
B106: 45231 | C106: ISHARES MSCI WOR A | D106: IE00B4L5Y983 | E106: EAM | F106: XAMS | G106: -15 | H106: 76 | I106: =H106*G106 -> -1140 | J106: -1 | K106: =-I106+J106 -> 1139 | L106: Venta de todo MSCI WORLD
B107: 45223 | C107: ACS | D107: ES0167050915 | E107: MAD | F107: XMAD | G107: 10 | H107: 32.4 | I107: =H107*G107 -> 324 | J107: -10.2 | K107: =-I107+J107 -> -334.2
B108: 45194 | C108: SHELL PLC | D108: GB00BP6MXD84 | E108: EAM | F108: XAMS | G108: 5 | H108: 30.3 | I108: =H108*G108 -> 151.5 | J108: -4.9 | K108: =-I108+J108 -> -156.4
B109: 45194 | C109: ISHARES PROP GLO | D109: IE00B1FZS350 | E109: EAM | F109: XAMS | G109: 5 | H109: 19.5 | I109: =H109*G109 -> 97.5 | J109: -1 | K109: =-I109+J109 -> -98.5
B110: 45194 | C110: VERIZON COMMUNICATIONS INC | D110: US92343V1044 | E110: XET | F110: XETB | G110: 5 | H110: 31.33 | I110: =H110*G110 -> 156.65 | J110: -4.9 | K110: =-I110+J110 -> -161.55
B111: 45195 | C111: RED ELECTRICA | D111: ES0173093024 | E111: MAD | F111: XMAD | G111: 10 | H111: 14.9 | I111: =H111*G111 -> 149 | J111: -10 | K111: =-I111+J111 -> -159
B112: 45161 | C112: ELECNOR | D112: ES0129743318 | E112: MAD | F112: XMAD | G112: 10 | H112: 13.8 | I112: =H112*G112 -> 138 | J112: -10 | K112: =-I112+J112 -> -148
B113: 45139 | C113: LTC PROPERTIES INC | D113: US5021751020 | E113: TDG | F113: XGAT | G113: 5 | H113: 30.75 | I113: =H113*G113 -> 153.75 | J113: -3.9 | K113: =-I113+J113 -> -157.65
B114: 45139 | C114: INVESCO S&P 500 HIGH DIV LOW VOL UCITS ETF DIS | D114: IE00BWTN6Y99 | E114: XET | F114: XETA | G114: 5 | H114: 29.45 | I114: =H114*G114 -> 147.25 | J114: -1 | K114: =-I114+J114 -> -148.25
B115: 45129 | C115: IBERDROLA | D115: ES0144580Y14 | E115: MAD | F115: XMAD | G115: 20 | H115: 11.52 | I115: =H115*G115 -> 230.4 | J115: -20.4 | K115: =-I115+J115 -> -250.8
B116: 45103 | C116: INTEL CORP | D116: US4581401001 | E116: TDG | F116: XGAT | G116: 8 | H116: 30.4 | I116: =H116*G116 -> 243.2 | J116: -3.9 | K116: =-I116+J116 -> -247.1
B117: 45103 | C117: ISHARES PROP GLO | D117: IE00B1FZS350 | E117: EAM | F117: XAMS | G117: 5 | H117: 19.36 | I117: =H117*G117 -> 96.8 | J117: -1 | K117: =-I117+J117 -> -97.8
B118: 45103 | C118: WALGREENS BOOTS ALLIANCE INC | D118: US9314271084 | E118: TDG | F118: XGAT | G118: 3 | H118: 29 | I118: =H118*G118 -> 87 | J118: -3.9 | K118: =-I118+J118 -> -90.9
... B120: 45081 | C120: ENAGAS | D120: ES0130960018 | E120: MAD | F120: XMAD | G120: 6 | H120: 18.2 | I120: =H120*G120 -> 109.2 | J120: -10.2 | K120: =-I120+J120 -> -119.4
B121: 45048 | C121: INVESCO S&P 500 HIGH DIV LOW VOL UCITS ETF DIS | D121: IE00BWTN6Y99 | E121: XET | F121: XETA | G121: 3 | H121: 28.425 | I121: =H121*G121 -> 85.275 | K121: =-I121+J121 -> -85.275
B122: 45048 | C122: ISHARES STOXX EUROPE 600 UCITS ETF (DE) | D122: DE0002635307 | E122: XET | F122: XETA | G122: 2 | H122: 46.16 | I122: =H122*G122 -> 92.32 | K122: =-I122+J122 -> -92.32
B123: 45048 | C123: COMCAST CORP | D123: US20030N1019 | E123: TDG | F123: XGAT | G123: 8 | H123: 37.43 | I123: =H123*G123 -> 299.44 | J123: -3.9 | K123: =-I123+J123 -> -303.34
B124: 45048 | C124: ELECNOR | D124: ES0129743318 | E124: MAD | F124: XMAD | G124: 6 | H124: 11.85 | I124: =H124*G124 -> 71.1 | J124: -10 | K124: =-I124+J124 -> -81.1
B125: 45048 | C125: LOGISTA | D125: ES0105027009 | E125: MAD | F125: XMAD | G125: 6 | H125: 24.32 | I125: =H125*G125 -> 145.92 | J125: -10 | K125: =-I125+J125 -> -155.92
B126: 45035 | C126: AT&T INC | D126: US00206R1023 | E126: TDG | F126: XGAT | G126: 8 | H126: 18.115 | I126: =H126*G126 -> 144.92 | J126: -3.9 | K126: =-I126+J126 -> -148.82
B127: 45035 | C127: ISHARES PROP GLO | D127: IE00B1FZS350 | E127: EAM | F127: XAMS | G127: 2 | H127: 20.244 | I127: =H127*G127 -> 40.488 | J127: -1 | K127: =-I127+J127 -> -41.488
B128: 45035 | C128: ISHARES STOXX EUROPE 600 UCITS ETF (DE) | D128: DE0002635307 | E128: XET | F128: XETA | G128: 2 | H128: 46.33 | I128: =H128*G128 -> 92.66 | J128: -1 | K128: =-I128+J128 -> -93.66
B129: 45035 | C129: INVESCO S&P 500 HIGH DIV LOW VOL UCITS ETF DIS | D129: IE00BWTN6Y99 | E129: XET | F129: XETA | G129: 2 | H129: 29.46 | I129: =H129*G129 -> 58.92 | J129: -1 | K129: =-I129+J129 -> -59.92
B130: 45021 | C130: RED ELECTRICA | D130: ES0173093024 | E130: MAD | F130: XMAD | G130: 2 | H130: 16.3 | I130: =H130*G130 -> 32.6 | J130: -10 | K130: =-I130+J130 -> -42.6
B131: 45021 | C131: ENAGAS | D131: ES0130960018 | E131: MAD | F131: XMAD | G131: 2 | H131: 17.8 | I131: =H131*G131 -> 35.6 | J131: -10 | K131: =-I131+J131 -> -45.6
B132: 45021 | C132: ELECNOR | D132: ES0129743318 | E132: MAD | F132: XMAD | G132: 2 | H132: 12.1 | I132: =H132*G132 -> 24.2 | J132: -10 | K132: =-I132+J132 -> -34.2
B133: 45021 | C133: LOGISTA | D133: ES0105027009 | E133: MAD | F133: XMAD | G133: 2 | H133: 22.8 | I133: =H133*G133 -> 45.6 | J133: -10 | K133: =-I133+J133 -> -55.6
B134: 45035 | C134: Grifols SA | D134: ES0171996087 | E134: MAD | F134: XMAD | G134: 7 | H134: 9.17 | I134: =H134*G134 -> 64.19 | J134: -1 | K134: =-I134+J134 -> -65.19
B135: 45035 | C135: Kraft Heinz Co | D135: US5007541064 | E135: TDG | F135: XGAT | G135: 3 | H135: 35.94 | I135: =H135*G135 -> 107.82 | J135: -3.9 | K135: =-I135+J135 -> -111.72
B136: 03-04-2023 | C136: COMCAST CORP | D136: US20030N1019 | E136: TDG | F136: XGAT | G136: 2 | H136: 34.98 | I136: =H136*G136 -> 69.96 | J136: -3.9 | K136: =-I136+J136 -> -73.86
B137: 03-04-2023 | C137: WALGREENS BOOTS ALLIANCE INC | D137: US9314271084 | E137: TDG | F137: XGAT | G137: 2 | H137: 32.24 | I137: =H137*G137 -> 64.48 | J137: -3.9 | K137: =-I137+J137 -> -68.38
B138: 03-04-2023 | C138: ISHARES STOXX EUROPE 600 UCITS ETF (DE) | D138: DE0002635307 | E138: XET | F138: XETA | G138: 3 | H138: 45.37 | I138: =H138*G138 -> 136.11 | K138: =-I138+J138 -> -136.11
...

Sheet Inversiones
C3: Google Finance
C4: Yahoo Finanzas
C8: CARTERA DE INVERSION | P8: Symbol | Q8: Title | S8: Shares | T8: Precio actual | U8: Total | V8: Dividend | W8: % | X8: % | AB8: ESTIMACIONES ANUALES (por acción)
O9: ETFs y PP | AE9: ENE | AF9: FEB | AG9: MAR | AH9: ABR | AI9: MAY | AJ9: JUN | AK9: JUL | AL9: AGO | AM9: SEP | AN9: OCT | AO9: NOV | AP9: DIC
C10: ETF/FONDO | D10: TÍTULO | J10: SIMBOL | K10: % | M10: EUR | N10: 1 | P10: Novartis PPE | Q10: SANTANDER PPE | S10: 63 | T10: 120 | U10: =S10*T10 -> 7560 | V10: NO | W10: =U10/$R$45 -> #VALUE! | AC10: HDLV.DE | AD10: #VALUE! | AG10: Xxx | AJ10: Xxx | AM10: Xxx | AP10: Xxx
C11: BBVA FS | D11: Futuro:bono Nocional Usa 10 Años Física | J11: N/A | K11: 10.09% | M11: EUR | N11: 2 | P11: 0P0000RYC6.F | Q11: CAIXABANK Tendencias PP | S11: 607.4 | T11: 33 | U11: =S11*T11 -> 20044.2 | V11: NO | W11: =U11/$R$45 -> #VALUE! | AC11: IWDP.AS | AD11: #VALUE! | AI11: 0.165 | AO11: 0.166
C12: BBVA FS | D12: Futuro:bono Nocional Aleman 10 Años Física | J12: N/A | K12: 8.10% | M12: EUR | N12: 3 | P12: 0P00000VSG.F | Q12: #VALUE! | S12: 7.3 | T12: 973.8 | U12: =S12*T12 -> 7108.74 | V12: NO | W12: =U12/$R$45 -> #VALUE! | AC12: EXSA.DE | AD12: #VALUE! | AG12: Xxx | AJ12: Xxx | AM12: Xxx | AP12: Xxx
C13: BBVA FS | D13: Xtrackers MSCI World ETF 1C | J13: XDWD.IR | K13: 5.62% | M13: {=_FV(Q13,"Currency",TRUE)} -> #VALUE! | N13: 4 | P13: HDLV.DE | Q13: #VALUE! | S13: 55 | T13: {=_FV(Q13,"Price")} -> #VALUE! | U13: =S13*T13 -> #VALUE! | V13: YES | W13: =U13/$R$45 -> #VALUE! | AC13: IWRD.AS | AD13: #VALUE! | AG13: 0.14 | AJ13: 0.14 | AM13: 0.14 | AP13: 0.14
C14: BBVA FS | D14: iShares Core MSCI World ETF USD Acc | J14: IWDA | K14: 5.62% | M14: {=_FV(Q14,"Currency",TRUE)} -> #VALUE! | N14: 5 | P14: IWDP.AS | Q14: #VALUE! | S14: 60 | T14: {=_FV(Q14,"Price")} -> #VALUE! | U14: =S14*T14 -> #VALUE! | V14: YES | W14: =U14/$R$45 -> #VALUE! | AC14: {=_FV(AD14,"Ticker symbol",TRUE)} -> #VALUE! | AD14: #VALUE! | AJ14: 0.27 | AP14: 0.06
C15: BBVA FS | D15: Amundi MSCI Wld Climt Trnstn CTB ETFDR € | J15: LWCR.IR | K15: 4.47% | M15: {=_FV(Q15,"Currency",TRUE)} -> #VALUE! | N15: 6 | P15: IWRD.AS | Q15: #VALUE! | S15: 25 | T15: {=_FV(Q15,"Price")} -> #VALUE! | U15: =S15*T15 -> #VALUE! | V15: YES | W15: =U15/$R$45 -> #VALUE! | AC15: {=_FV(AD15,"Ticker symbol",TRUE)} -> #VALUE! | AD15: #VALUE! | AF15: 0.4 | AL15: 0.8
C16: BBVA FS | D16: Futuro:msci World Nr | J16: N/A | K16: 4.45% | M16: {=_FV(Q16,"Currency",TRUE)} -> #VALUE! | N16: 7 | P16: EXSA.DE | Q16: #VALUE! | S16: 35 | T16: {=_FV(Q16,"Price")} -> #VALUE! | U16: =S16*T16 -> #VALUE! | V16: YES | W16: =U16/$R$45 -> #VALUE! | AC16: {=_FV(AD16,"Ticker symbol",TRUE)} -> #VALUE! | AD16: #VALUE! | AK16: 0.7 | AP16: 1
C17: BBVA FS | D17: Xtrackers MSCI WORLD ESG ETF 1C | J17: XZW0 | K17: 3.54% | AC17: {=_FV(AD17,"Ticker symbol",TRUE)} -> #VALUE! | AD17: #VALUE!
C18: BBVA FS | D18: iShares JP Morgan $ EM Bd ETF USD Acc | J18: JPEA | K18: 3.50% | T18: Total ETFs, Fondos y Planes | U18: =SUM(U10:U17) -> #VALUE! | X18: =U18/$R$45 -> #VALUE! | AC18: {=_FV(AD18,"Ticker symbol",TRUE)} -> #VALUE! | AD18: #VALUE! | AE18: 0.29 | AK18: 0.29
C19: BBVA FS | D19: BNPP Insticash EUR 1D ST VNAV I Cap | J19: N/A | K19: 3.48% | O19: ACCIONES | AC19: {=_FV(AD19,"Ticker symbol",TRUE)} -> #VALUE! | AD19: #VALUE! | AE19: 0.27 | AJ19: 0.72
C20: BBVA FS | D20: FONDO:BETAMINER BEHEDGED | J20: N/A | K20: 2.45% | AC20: {=_FV(AD20,"Ticker symbol",TRUE)} -> #VALUE! | AD20: #VALUE! | AF20: 0.45 | AK20: 1.45
C21: CABK | D21: CS (Lux) Digital Health Equity IB USD | J21: N/A | K21: 6.40% | M21: {=_FV(Q21,"Currency",TRUE)} -> #VALUE! | N21: 1 | P21: {=_FV(Q21,"Ticker symbol",TRUE)} -> #VALUE! | Q21: #VALUE! | S21: 45 | T21: {=_FV(Q21,"Price")} -> #VALUE! | U21: =S21*T21 -> #VALUE! | V21: YES | W21: =U21/$R$45 -> #VALUE! | X21: ELECNOR | AC21: {=_FV(AD21,"Ticker symbol",TRUE)} -> #VALUE! | AD21: #VALUE! | AF21: 0.28 | AI21: 0.28 | AL21: 0.28 | AO21: 0.28
C22: CABK | D22: Invesco Glbl Consmr Trnds C USD Acc | J22: N/A | K22: 5.94% | M22: {=_FV(Q22,"Currency",TRUE)} -> #VALUE! | N22: 2 | P22: {=_FV(Q22,"Ticker symbol",TRUE)} -> #VALUE! | Q22: #VALUE! | S22: 50 | T22: {=_FV(Q22,"Price")} -> #VALUE! | U22: =S22*T22 -> #VALUE! | V22: YES | W22: =U22/$R$45 -> #VALUE! | X22: LOGISTA | AC22: {=_FV(AD22,"Ticker symbol",TRUE)} -> #VALUE! | AD22: #VALUE! | AE22: 0.087 | AH22: 0.087 | AK22: 0.087 | AN22: 0.087
C23: CABK | D23: RobecoSAM Smart Materials Eqs I EUR | J23: N/A | K23: 4.44% | M23: {=_FV(Q23,"Currency",TRUE)} -> #VALUE! | N23: 3 | P23: {=_FV(Q23,"Ticker symbol",TRUE)} -> #VALUE! | Q23: #VALUE! | S23: 50 | T23: {=_FV(Q23,"Price")} -> #VALUE! | U23: =S23*T23 -> #VALUE! | V23: YES | W23: =U23/$R$45 -> #VALUE! | X23: ENAGAS | AC23: {=_FV(AD23,"Ticker symbol",TRUE)} -> #VALUE! | AD23: #VALUE! | AG23: 0.125 | AJ23: 0.125 | AM23: 0.125 | AP23: 0.125
C24: CABK | D24: Pictet - Robotics I EUR | J24: N/A | K24: 4.41% | M24: {=_FV(Q24,"Currency",TRUE)} -> #VALUE! | N24: 4 | P24: {=_FV(Q24,"Ticker symbol",TRUE)} -> #VALUE! | Q24: #VALUE! | S24: 0 | T24: {=_FV(Q24,"Price")} -> #VALUE! | U24: =S24*T24 -> #VALUE! | V24: NO | W24: =U24/$R$45 -> #VALUE! | AC24: {=_FV(AD24,"Ticker symbol",TRUE)} -> #VALUE! | AD24: #VALUE! | AG24: 0.4 | AJ24: 0.4 | AM24: 0.4 | AP24: 0.4
C25: CABK | D25: JPM Global Natural Resources C (acc) USD | J25: N/A | K25: 4.04% | M25: {=_FV(Q25,"Currency",TRUE)} -> #VALUE! | N25: 5 | P25: {=_FV(Q25,"Ticker symbol",TRUE)} -> #VALUE! | Q25: #VALUE! | S25: 50 | T25: {=_FV(Q25,"Price")} -> #VALUE! | U25: =S25*T25 -> #VALUE! | V25: YES | W25: =U25/$R$45 -> #VALUE! | X25: REDEIA | AC25: {=_FV(AD25,"Ticker symbol",TRUE)} -> #VALUE! | AD25: #VALUE!
C26: CABK | D26: BGF Sustainable Energy A2 | J26: N/A | K26: 3.91% | M26: {=_FV(Q26,"Currency",TRUE)} -> #VALUE! | N26: 6 | P26: {=_FV(Q26,"Ticker symbol",TRUE)} -> #VALUE! | Q26: #VALUE! | S26: 51 | T26: {=_FV(Q26,"Price")} -> #VALUE! | U26: =S26*T26 -> #VALUE! | V26: YES | W26: =U26/$R$45 -> #VALUE! | X26: IBERDROLA | AC26: {=_FV(AD26,"Ticker symbol",TRUE)} -> #VALUE! | AD26: #VALUE! | AE26: 0.19 | AF26: 0.19 | AG26: 0.19 | AH26: 0.19 | AI26: 0.19 | AJ26: 0.19 | AK26: 0.19 | AL26: 0.19 | AM26: 0.19 | AN26: 0.19 | AO26: 0.19 | AP26: 0.19
C27: CABK | D27: Nordea 1 - Global Climate & Envir BI EUR | J27: N/A | K27: 3.91% | M27: {=_FV(Q27,"Currency",TRUE)} -> #VALUE! | N27: 7 | P27: {=_FV(Q27,"Ticker symbol",TRUE)} -> #VALUE! | Q27: #VALUE! | S27: 30 | T27: {=_FV(Q27,"Price")} -> #VALUE! | U27: =S27*T27 -> #VALUE! | V27: YES | W27: =U27/$R$45 -> #VALUE! | X27: ACS | AC27: {=_FV(AD27,"Ticker symbol",TRUE)} -> #VALUE! | AD27: #VALUE! | AG27: 0.31 | AJ27: 0.33 | AM27: 0.33 | AP27: 0.33
C28: CABK | D28: Robeco New World Financials I $ | J28: N/A | K28: 3.91% | M28: {=_FV(Q28,"Currency",TRUE)} -> #VALUE! | N28: 8 | P28: {=_FV(Q28,"Ticker symbol",TRUE)} -> #VALUE! | Q28: #VALUE! | S28: 25 | T28: {=_FV(Q28,"Price")} -> #VALUE! | U28: =S28*T28 -> #VALUE! | V28: YES | W28: =U28/$R$45 -> #VALUE! | X28: ATT | AC28: {=_FV(AD28,"Ticker symbol",TRUE)} -> #VALUE! | AD28: #VALUE! | AG28: 0.36 | AJ28: 0.37 | AM28: 0.37 | AO28: 0.37
C29: CABK | D29: BNP Paribas Aqua I C | J29: N/A | K29: 3.72% | M29: {=_FV(Q29,"Currency",TRUE)} -> #VALUE! | N29: 9 | P29: {=_FV(Q29,"Ticker symbol",TRUE)} -> #VALUE! | Q29: #VALUE! | S29: 20 | T29: {=_FV(Q29,"Price")} -> #VALUE! | U29: =S29*T29 -> #VALUE! | V29: YES | W29: =U29/$R$45 -> #VALUE! | X29: INTEL | AC29: {=_FV(AD29,"Ticker symbol",TRUE)} -> #VALUE! | AD29: #VALUE! | AE29: 0.66 | AH29: 0.66 | AK29: 0.66 | AN29: 0.66
C30: CABK | D30: Franklin Technology I Acc EUR | J30: N/A | K30: 3.71% | M30: {=_FV(Q30,"Currency",TRUE)} -> #VALUE! | N30: 10 | P30: {=_FV(Q30,"Ticker symbol",TRUE)} -> #VALUE! | Q30: #VALUE! | S30: 25 | T30: {=_FV(Q30,"Price")} -> #VALUE! | U30: =S30*T30 -> #VALUE! | V30: YES | W30: =U30/$R$45 -> #VALUE! | X30: KRAFT | AC30: {=_FV(AD30,"Ticker symbol",TRUE)} -> #VALUE! | AD30: #VALUE! | AF30: 0.48 | AI30: 0.48 | AL30: 0.48 | AO30: 0.48
C31: EXSA | D31: #VALUE! | J31: NESN | K31: 3.02% | M31: {=_FV(Q31,"Currency",TRUE)} -> #VALUE! | N31: 11 | P31: {=_FV(Q31,"Ticker symbol",TRUE)} -> #VALUE! | Q31: #VALUE! | S31: 20 | T31: {=_FV(Q31,"Price")} -> #VALUE! | U31: =S31*T31 -> #VALUE! | V31: YES | W31: =U31/$R$45 -> #VALUE! | X31: LTC
C32: EXSA | D32: #VALUE! | J32: ASML | K32: 2.42% | M32: {=_FV(Q32,"Currency",TRUE)} -> #VALUE! | N32: 12 | P32: {=_FV(Q32,"Ticker symbol",TRUE)} -> #VALUE! | Q32: #VALUE! | S32: 25 | T32: {=_FV(Q32,"Price")} -> #VALUE! | U32: =S32*T32 -> #VALUE! | V32: YES | W32: =U32/$R$45 -> #VALUE! | X32: DIAGEO | AD32: Total mes /accion | AE32: =SUM(AE10:AE31) -> 1.497 | AF32: =SUM(AF10:AF31) -> 1.8 | AG32: =SUM(AG10:AG31) -> 1.525 | AH32: =SUM(AH10:AH31) -> 0.937 | AI32: =SUM(AI10:AI31) -> 1.115 | AJ32: =SUM(AJ10:AJ31) -> 2.545 | AK32: =SUM(AK10:AK31) -> 3.377 | AL32: =SUM(AL10:AL31) -> 1.75 | ... AP32: =SUM(AP10:AP31) -> 2.245
C33: EXSA | D33: #VALUE! | J33: ROG | K33: 2.23% | M33: {=_FV(Q33,"Currency",TRUE)} -> #VALUE! | N33: 13 | P33: {=_FV(Q33,"Ticker symbol",TRUE)} -> #VALUE! | Q33: #VALUE! | S33: 20 | T33: {=_FV(Q33,"Price")} -> #VALUE! | U33: =S33*T33 -> #VALUE! | V33: YES | W33: =U33/$R$45 -> #VALUE! | X33: SHELL | AB33: Total / accion | AD33: =SUM(AE32:AP32) -> 20.769
C34: EXSA | D34: #VALUE! | J34: NOVN | K34: 1.89% | M34: {=_FV(Q34,"Currency",TRUE)} -> #VALUE! | N34: 14 | P34: {=_FV(Q34,"Ticker symbol",TRUE)} -> #VALUE! | Q34: #VALUE! | S34: 17 | T34: {=_FV(Q34,"Price")} -> #VALUE! | U34: =S34*T34 -> #VALUE! | V34: YES | W34: =U34/$R$45 -> #VALUE! | X34: UNILEVER
C35: EXSA | D35: #VALUE! | J35: MC.PA | K35: 1.75% | M35: {=_FV(Q35,"Currency",TRUE)} -> #VALUE! | N35: 15 | P35: {=_FV(Q35,"Ticker symbol",TRUE)} -> #VALUE! | Q35: #VALUE! | S35: 25 | T35: {=_FV(Q35,"Price")} -> #VALUE! | U35: =S35*T35 -> #VALUE! | V35: YES | W35: =U35/$R$45 -> #VALUE! | X35: VERIZON
C36: EXSA | D36: #VALUE! | J36: AZN.L | K36: 1.32% | M36: {=_FV(Q36,"Currency",TRUE)} -> #VALUE! | N36: 16 | P36: {=_FV(Q36,"Ticker symbol",TRUE)} -> #VALUE! | Q36: #VALUE! | S36: 0 | T36: {=_FV(Q36,"Price")} -> #VALUE! | U36: =S36*T36 -> #VALUE! | V36: NO | W36: =U36/$R$45 -> #VALUE!
C37: EXSA | D37: #VALUE! | J37: SAP.DE | K37: 1.29% | M37: {=_FV(Q37,"Currency",TRUE)} -> #VALUE! | N37: 17 | P37: {=_FV(Q37,"Ticker symbol",TRUE)} -> #VALUE! | Q37: #VALUE! | S37: 25 | T37: {=_FV(Q37,"Price")} -> #VALUE! | U37: =S37*T37 -> #VALUE! | V37: YES | W37: =U37/$R$45 -> #VALUE! | X37: COMCAST
C38: EXSA | D38: #VALUE! | J38: ULVR.L | K38: 1.29% | M38: EUR | N38: 18 | P38: PFE | Q38: #VALUE! | S38: 20 | T38: {=_FV(Q38,"Price")} -> #VALUE! | U38: =S38*T38 -> #VALUE! | V38: YES | W38: =U38/$R$45 -> #VALUE! | X38: PFIZER
C39: EXSA | D39: #VALUE! | J39: LIN.L | K39: 1.26%
C40: EXSA | D40: #VALUE! | J40: NOVO B | K40: 1.17% | W40: =SUM(W10:W38) -> #VALUE!
C41: HDLV | D41: #VALUE! | J41: IRM | K41: 3.69% | T41: Total Acciones | U41: =SUM(U21:U40) -> #VALUE! | X41: =U41/$R$45 -> #VALUE!
C42: HDLV | D42: #VALUE! | J42: XOM | K42: 3.50%
C43: HDLV | D43: #VALUE! | J43: LUMN | K43: 3.20% | Q43: Total Posiciones | R43: =COUNTA(S9:S40) -> 25
C44: HDLV | D44: #VALUE! | J44: KMI | K44: 3.13% | Q44: Total Shares | R44: =SUM(S10:S40) -> 1350.7
C45: HDLV | D45: #VALUE! | J45: MO | K45: 3.00% | Q45: Total invertido | R45: =U18+U41 -> #VALUE!
C46: HDLV | D46: #VALUE! | J46: PM | K46: 2.73%
C47: HDLV | D47: #VALUE! | J47: CVX | K47: 2.71%
C48: HDLV | D48: People's United Financial Inc | J48: PBCT | K48: 2.63%
C49: HDLV | D49: #VALUE! | J49: T | K49: 2.62%
C50: HDLV | D50: #VALUE! | J50: IBM | K50: 2.48%
C51: IWRD | D51: #VALUE! | J51: {=_FV(D51,"Ticker symbol",TRUE)} -> #VALUE! | K51: 5.1%
C52: IWRD | D52: #VALUE! | J52: {=_FV(D52,"Ticker symbol",TRUE)} -> #VALUE! | K52: 4.5%
C53: IWRD | D53: #VALUE! | J53: {=_FV(D53,"Ticker symbol",TRUE)} -> #VALUE! | K53: 2.33%
C54: IWRD | D54: #VALUE! | J54: {=_FV(D54,"Ticker symbol",TRUE)} -> #VALUE! | K54: 1.96%
C55: IWRD | D55: #VALUE! | J55: {=_FV(D55,"Ticker symbol",TRUE)} -> #VALUE! | K55: 1.38%
C56: IWRD | D56: #VALUE! | J56: {=_FV(D56,"Ticker symbol",TRUE)} -> #VALUE! | K56: 1.26%
C57: IWRD | D57: #VALUE! | J57: {=_FV(D57,"Ticker symbol",TRUE)} -> #VALUE! | K57: 1.24%
C58: IWRD | D58: #VALUE! | J58: {=_FV(D58,"Ticker symbol",TRUE)} -> #VALUE! | K58: 1.14%
C59: IWRD | D59: #VALUE! | J59: {=_FV(D59,"Ticker symbol",TRUE)} -> #VALUE! | K59: 0.91%
C60: IWRD | D60: #VALUE! | J60: {=_FV(D60,"Ticker symbol",TRUE)} -> #VALUE! | K60: 0.86%
C61: IWRD | D61: #VALUE! | J61: {=_FV(D61,"Ticker symbol",TRUE)} -> #VALUE! | K61: 0.83%
C62: IWRD | D62: #VALUE! | J62: {=_FV(D62,"Ticker symbol",TRUE)} -> #VALUE! | K62: 0.80%
... C68: IWRD | D68: #VALUE! | J68: {=_FV(D68,"Ticker symbol",TRUE)} -> #VALUE! | K68: 0.60%
C69: IWDP | D69: #VALUE! | J69: PLD | K69: 5.16%
C70: IWDP | D70: #VALUE! | J70: PSA | K70: 2.66%
C71: IWDP | D71: #VALUE! | J71: SPG | K71: 2.50%
C72: IWDP | D72: #VALUE! | J72: DLR | K72: 2.46%
C73: IWDP | D73: #VALUE! | J73: VNA.DE | K73: 2.15%
C74: IWDP | D74: #VALUE! | J74: WELL | K74: 2.04%
C75: IWDP | D75: #VALUE! | J75: AVB | K75: 1.70%
C76: IWDP | D76: #VALUE! | J76: EQR | K76: 1.66%
C77: IWDP | D77: #VALUE! | J77: ARE | K77: 1.56%
C78: IWDP | D78: #VALUE! | J78: O | K78: 1.46%
B80: INFORMES ANUALES
D81: 2023
C82: Costes y Gastos | D82: CxBank | E82: % | F82: Rentabilidad
C83: ACS | D83: 13.37 | E83: 0.0401 | F83: 0.6024
C84: LOGISTA | D84: 49.18 | E84: 0.1978 | F84: 0.0373
C85: ELECNOR | D85: 49.55 | E85: 0.2368 | F85: 0.8443
C86: ENAGAS | D86: 50.21 | E86: 0.2528 | F86: -0.0167
C87: IBERDROLA | D87: 26.81 | E87: 0.1084 | F87: 0.1339
C88: REDEIA | D88: 49.09 | E88: 0.2197 | F88: -0.083
C89: Total | D89: =SUM(D83:D88) -> 238.21 | E89: 0.2825
C91: DEGIRO | D91: 2023 | E91: 2024
C92: Valor total cartera | D92: 6211.76
C93: Ganancias venta acc | D93: 64.22
C94: Perdidas venta acc | D94: 8.32
C95: Comisiones | D95: 93.7
F97: 2023 | G97: Dividendos
D98: Pais | E98: Producto | G98: 1 | H98: 2 | I98: 3 | J98: 4 | K98: TOTAL | M98: %
D99: DE | E99: iShares STOXX | G99: 2.02 | H99: 12.61 | I99: 10.55 | J99: 4.07 | K99: =SUM(G99:J99) -> 29.25 | M99: =K99/$K$113 -> 0.25866643
D100: GB | E100: Shell | G100: 0.8 | H100: 0.91 | I100: 2.46 | K100: =SUM(G100:J100) -> 4.17 | M100: =K100/$K$113 -> 0.036876548
D101: GB | E101: Unilever | G101: 0.85 | H101: 0.85 | I101: 0.85 | K101: =SUM(G101:J101) -> 2.55 | M101: =K101/$K$113 -> 0.022550407
D102: IE | E102: Invesco SP500 | G102: 1.35 | H102: 6.16 | I102: 8.08 | J102: 7.46 | K102: =SUM(G102:J102) -> 23.05 | M102: =K102/$K$113 -> 0.20383799
D103: IE | E103: iShares DevMark | G103: 2.89 | H103: 3.46 | I103: 3.78 | K103: =SUM(G103:J103) -> 10.13 | M103: =K103/$K$113 -> 0.089582596
D104: IE | E104: iShares World | G104: 3.46 | K104: =SUM(G104:J104) -> 3.46 | M104: =K104/$K$113 -> 0.030597807
D105: US | E105: ATT | G105: 0.51 | H105: 2.53 | I105: 2.62 | K105: =SUM(G105:J105) -> 5.66 | M105: =K105/$K$113 -> 0.05005306
D106: US | E106: Comcast | G106: 0.53 | H106: 2.62 | I106: 2.74 | K106: =SUM(G106:J106) -> 5.89 | M106: =K106/$K$113 -> 0.052087018
D107: US | E107: Intel | G107: 0.23 | H107: 1.16 | I107: 1.15 | K107: =SUM(G107:J107) -> 2.54 | M107: =K107/$K$113 -> 0.022461974
D108: US | E108: Kraft | G108: 1.1 | H108: 1.13 | I108: 1.09 | K108: =SUM(G108:J108) -> 3.32 | M108: =K108/$K$113 -> 0.029359745
D109: US | E109: LTC | G109: 1.04 | H109: 1.04 | I109: 2.84 | J109: 4.22 | K109: =SUM(G109:J109) -> 9.14 | M109: =K109/$K$113 -> 0.080827733
D110: US | E110: Verizon | G110: 1.79 | H110: 1.78 | I110: 5.01 | K110: =SUM(G110:J110) -> 8.58 | M110: =K110/$K$113 -> 0.075875486
D111: US | E111: Walgreens | G111: 0.89 | H111: 2.23 | I111: 2.22 | K111: =SUM(G111:J111) -> 5.34 | M111: =K111/$K$113 -> 0.047223205
J113: TOTAL | K113: =SUM(K99:K112) -> 113.08

Sheet Dividendo
C3: Cartera de Inversion (2022 - 2026)
D6: Symbol | E6: Title | G6: Broker | H6: Shares | I6: Avg Cost / Share | J6: Total | K6: Dividend/accion | L6: En cartera | M6: Favorito | N6: Fecha entrada | O6: 2023 | P6: 2024 | Q6: 2025 | R6: 2026
C8: 1 | D8: {=_FV(E8,"Ticker symbol",TRUE)} -> #VALUE! | E8: #VALUE! | F8: Contruct&Engin | G8: CaixaBank | H8: 30 | I8: {=_FV(E8,"Price")} -> #VALUE! | J8: =H8*I8 -> #VALUE! | K8: 1 | L8: =IF(H8>0,"YES","NO") -> YES | M8: 1 | N8: 45200 | P8: =G94 -> 1.43 | Q8: =G126 -> 37.42 | R8: =G156 -> 9.45 | S8: #VALUE!
C9: 2 | D9: {=_FV(E9,"Ticker symbol",TRUE)} -> #VALUE! | E9: #VALUE! | F9: Telecommunic | G9: DeGiro | H9: 25 | I9: {=_FV(E9,"Price")} -> #VALUE! | J9: =H9*I9 -> #VALUE! | K9: 0.28 | L9: =IF(H9>0,"YES","NO") -> YES | M9: 1 | N9: 44986 | O9: =G48 -> 5.66 | P9: =G79 -> 9.17 | Q9: =G110 -> 11.14 | R9: =G140 -> 4.86 | S9: #VALUE!
C10: 3 | D10: {=_FV(E10,"Ticker symbol",TRUE)} -> #VALUE! | E10: #VALUE! | F10: Telecommunic | G10: DeGiro | H10: 25 | I10: {=_FV(E10,"Price")} -> #VALUE! | J10: =H10*I10 -> #VALUE! | K10: 0.29 | L10: =IF(H10>0,"YES","NO") -> YES | M10: 1 | N10: 45017 | O10: =SUM(H56:V56) -> 5.89 | P10: =G87 -> 9.98 | Q10: =G118 -> 14.08 | R10: =G148 -> 5.77 | S10: #VALUE!
C11: 4 | D11: {=_FV(E11,"Ticker symbol",TRUE)} -> #VALUE! | E11: #VALUE! | F11: Contruct&Engin | G11: CaixaBank | H11: 45 | I11: {=_FV(E11,"Price")} -> #VALUE! | J11: =H11*I11 -> #VALUE! | K11: 1.6 | L11: =IF(H11>0,"YES","NO") -> YES | M11: 1 | N11: 44986 | O11: =SUM(H57:V57) -> 1.8 | P11: =G89 -> 158.97 | Q11: =G121 -> 102 | R11: =G151 -> 0 | S11: #VALUE!
C12: 5 | D12: LOG | E12: #VALUE! | F12: Logistics | G12: CaixaBank | H12: 50 | I12: {=_FV(E12,"Price")} -> #VALUE! | J12: =H12*I12 -> #VALUE! | K12: 1.4 | L12: =IF(H12>0,"YES","NO") -> YES | M12: 1 | N12: 44986 | O12: =SUM(H59:V59) -> 2.76 | P12: =G91 -> 28.68 | Q12: =G123 -> 52.9 | R12: =G153 -> 60.75 | S12: #VALUE!
C13: 6 | D13: {=_FV(E13,"Ticker symbol",TRUE)} -> #VALUE! | E13: #VALUE! | F13: Oil&Gas | G13: CaixaBank | H13: 50 | I13: {=_FV(E13,"Price")} -> #VALUE! | J13: =H13*I13 -> #VALUE! | K13: 1.25 | L13: =IF(H13>0,"YES","NO") -> YES | M13: 1 | N13: 44986 | O13: =SUM(H58:V58) -> 14.4 | P13: =G90 -> 32.66 | Q13: =G122 -> 33 | R13: =G152 -> 0 | S13: #VALUE!
C14: 7 | D14: {=_FV(E14,"Ticker symbol",TRUE)} -> #VALUE! | E14: #VALUE! | F14: Electrical | G14: CaixaBank | H14: 51 | I14: {=_FV(E14,"Price")} -> #VALUE! | J14: =H14*I14 -> #VALUE! | K14: 0.32 | L14: =IF(H14>0,"YES","NO") -> YES | M14: 1 | N14: 45108 | O14: =SUM(H61:V61) -> 0 | P14: =G93 -> 1.13 | Q14: =G125 -> 3.51 | R14: =G155 -> 8.38 | S14: #VALUE!
C15: 8 | D15: {=_FV(E15,"Ticker symbol",TRUE)} -> #VALUE! | E15: #VALUE! | F15: IT Technology | G15: DeGiro | H15: 20 | I15: {=_FV(E15,"Price")} -> #VALUE! | J15: =H15*I15 -> #VALUE! | K15: 0.12 | L15: =IF(H15>0,"YES","NO") -> YES | M15: 1 | N15: 44986 | O15: =SUM(H49:V49) -> 2.54 | P15: =G80 -> 3.19 | Q15: =G111 -> 0 | R15: =G141 -> 0 | S15: #VALUE!
C16: 9 | D16: {=_FV(E16,"Ticker symbol",TRUE)} -> #VALUE! | E16: #VALUE! | F16: Foods | G16: DeGiro | H16: 25 | I16: {=_FV(E16,"Price")} -> #VALUE! | J16: =H16*I16 -> #VALUE! | K16: 0.4 | L16: =IF(H16>0,"YES","NO") -> YES | M16: 1 | N16: 45017 | O16: =SUM(H50:V50) -> 3.32 | P16: =G81 -> 16.71 | Q16: =G112 -> 17.1 | R16: =G142 -> 0 | S16: #VALUE!
C17: 10 | D17: {=_FV(E17,"Ticker symbol",TRUE)} -> #VALUE! | E17: #VALUE! | F17: REIT | G17: DeGiro | H17: 20 | I17: {=_FV(E17,"Price")} -> #VALUE! | J17: =H17*I17 -> #VALUE! | K17: 0.19 | L17: =IF(H17>0,"YES","NO") -> YES | M17: 1 | N17: 44986 | O17: =SUM(H51:V51) -> 9.15 | P17: =G82 -> 20.45 | Q17: =G113 -> 24.27 | R17: =G143 -> 4.91 | S17: #VALUE!
C18: 11 | D18: {=_FV(E18,"Ticker symbol",TRUE)} -> #VALUE! | E18: #VALUE! | F18: Electrical | G18: CaixaBank | H18: 50 | I18: {=_FV(E18,"Price")} -> #VALUE! | J18: =H18*I18 -> #VALUE! | K18: 1 | L18: =IF(H18>0,"YES","NO") -> YES | M18: 1 | N18: 44986 | O18: =SUM(H60:V60) -> 4.68 | P18: =G92 -> 19.65 | Q18: =G124 -> 21.88 | R18: =G154 -> 6.89 | S18: #VALUE!
C19: 12 | D19: {=_FV(E19,"Ticker symbol",TRUE)} -> #VALUE! | E19: #VALUE! | F19: Oil&Gas | G19: DeGiro | H19: 20 | I19: {=_FV(E19,"Price")} -> #VALUE! | J19: =H19*I19 -> #VALUE! | K19: 0.33 | L19: =IF(H19>0,"YES","NO") -> YES | M19: 1 | N19: 44986 | O19: =SUM(H52:V52) -> 4.17 | P19: =G83 -> 10.18 | Q19: =G114 -> 20.58 | R19: =G144 -> 0 | S19: #VALUE!
C20: 13 | D20: {=_FV(E20,"Ticker symbol",TRUE)} -> #VALUE! | E20: #VALUE! | F20: Drinks | G20: DeGiro | H20: 25 | I20: {=_FV(E20,"Price")} -> #VALUE! | J20: =H20*I20 -> #VALUE! | K20: 0.8 | L20: YES | M20: 1 | N20: 45352 | P20: =G88 -> 11.34 | Q20: =G119 -> 16.66 | R20: =G149 -> 0 | S20: #VALUE!
C21: 14 | D21: {=_FV(E21,"Ticker symbol",TRUE)} -> #VALUE! | E21: #VALUE! | F21: Household | G21: DeGiro | H21: 17 | I21: {=_FV(E21,"Price")} -> #VALUE! | J21: =H21*I21 -> #VALUE! | K21: 0.37 | L21: =IF(H21>0,"YES","NO") -> YES | M21: 1 | N21: 44986 | O21: =SUM(H53:V53) -> 2.55 | P21: =G84 -> 7.36 | Q21: =G115 -> 31.64 | R21: =G145 -> 0 | S21: #VALUE!
C22: 15 | D22: {=_FV(E22,"Ticker symbol",TRUE)} -> #VALUE! | E22: #VALUE! | F22: Telecommunic | G22: DeGiro | H22: 25 | I22: {=_FV(E22,"Price")} -> #VALUE! | J22: =H22*I22 -> #VALUE! | K22: 0.66 | L22: =IF(H22>0,"YES","NO") -> YES | M22: 1 | N22: 44986 | O22: =SUM(H54:V54) -> 8.58 | P22: =G85 -> 26.31 | Q22: =G116 -> 33.85 | R22: =G146 -> 12.07 | S22: #VALUE!
C23: 16 | D23: {=_FV(E23,"Ticker symbol",TRUE)} -> #VALUE! | E23: #VALUE! | F23: Drug Retail | G23: DeGiro | H23: 0 | I23: {=_FV(E23,"Price")} -> #VALUE! | J23: =H23*I23 -> #VALUE! | K23: 0.48 | L23: =IF(H23>0,"YES","NO") -> NO | M23: 1 | N23: 45017 | O23: =SUM(H55:V55) -> 5.34 | P23: =G86 -> 6.9 | Q23: =G117 -> 0 | R23: =G147 -> 0 | S23: #VALUE!
C24: 17 | D24: {=_FV(E24,"Ticker symbol",TRUE)} -> #VALUE! | E24: #VALUE! | F24: Drug Retail | G24: DeGiro | H24: 20 | I24: {=_FV(E24,"Price")} -> #VALUE! | J24: =H24*I24 -> #VALUE! | L24: YES | M24: 1 | N24: 45748 | Q24: =G120 -> 10.77 | R24: =G150 -> 0 | S24: =E24 -> #VALUE!
C27: 1 | D27: {=_FV(E27,"Símbolo bursátil",TRUE)} -> #VALUE! | E27: #VALUE! | F27: ETF | G27: DeGiro | H27: 25 | I27: {=_FV(E27,"Precio",TRUE)} -> #VALUE! | J27: =H27*I27 -> #VALUE! | K27: 0 | L27: YES | M27: 1 | N27: 45231 | O27: =G47 -> 0 | P27: =G78 -> 22.04 | Q27: =G109 -> 19.17 | R27: =G139 -> 0 | S27: #VALUE!
C28: 2 | D28: {=_FV(E28,"Ticker symbol",TRUE)} -> #VALUE! | E28: #VALUE! | F28: {=_FV(E28,"Instrument type",TRUE)} -> #VALUE! | G28: DeGiro | H28: 55 | I28: {=_FV(E28,"Price")} -> #VALUE! | J28: =H28*I28 -> #VALUE! | K28: =O28/H28 -> 0.41909091 | L28: =IF(H28>0,"YES","NO") -> YES | M28: 1 | N28: 44958 | O28: =SUM(H44:V44) -> 23.05 | P28: =G75 -> 35.56 | Q28: =G106 -> 53.31 | R28: =G136 -> 0 | S28: #VALUE!
C29: 3 | D29: {=_FV(E29,"Ticker symbol",TRUE)} -> #VALUE! | E29: #VALUE! | F29: {=_FV(E29,"Instrument type",TRUE)} -> #VALUE! | G29: DeGiro | H29: 35 | I29: {=_FV(E29,"Price")} -> #VALUE! | J29: =H29*I29 -> #VALUE! | K29: =O29/H29 -> 0.83571429 | L29: =IF(H29>0,"YES","NO") -> YES | M29: 1 | N29: 44805 | O29: =SUM(H45:V45) -> 29.25 | P29: =G76 -> 28.85 | Q29: =G107 -> 44.7 | R29: =G137 -> 0 | S29: #VALUE!
C30: 4 | D30: {=_FV(E30,"Ticker symbol",TRUE)} -> #VALUE! | E30: #VALUE! | F30: {=_FV(E30,"Instrument type",TRUE)} -> #VALUE! | G30: DeGiro | H30: 60 | I30: {=_FV(E30,"Price")} -> #VALUE! | J30: =H30*I30 -> #VALUE! | K30: 0.19 | L30: =IF(H30>0,"YES","NO") -> YES | M30: 1 | N30: 44958 | O30: =SUM(H46:V46) -> 10.13 | P30: =G77 -> 21.21 | Q30: =G108 -> 32.14 | R30: =G138 -> 8.79 | S30: #VALUE!
H33: =SUMIF(L8:L32,"YES",H8:H32) -> 673 | I33: =AVERAGEIF(L8:L32,"YES",I8:I32) -> #VALUE! | J33: =SUMIF(L8:L32,"YES",J8:J32) -> #VALUE! | L33: =COUNTIF(L8:L31,"YES") -> 20 | O33: =SUM(O8:O31) -> 133.27 | P33: =SUM(P8:P31) -> 471.77 | Q33: =SUM(Q8:Q31) -> 580.12 | R33: =SUM(R8:R31) -> 121.87
H34: Acciones | I34: Promedio | J34: Importe | L34: Posiciones | O34: Dividendos
J35: =AVERAGEIF(L9:L34,"YES",J9:J34) -> #VALUE! | O35: ANUAL
J36: Promedio
J38: Estimacion compra una accion de cada favorito | K38: =SUMIF(M8:M31,1,I8:I31) -> #VALUE! | L38: Dividendos totales desde inicio | P38: =SUM(O33:R33) -> 1307.03
G41: 2023 | I41: Ingreso bruto
G42: TOTAL | H42: Ene | I42: Feb | J42: Mar | K42: Abr | N42: May | O42: Jun | P42: Jul | Q42: Ago | S42: Sep | T42: Oct | U42: Nov | V42: Dic | W42: TOTAL
B43: DIVIDENDEROS
B44: =H28 -> 55 | C44: 1 | D44: {=_FV(E44,"Ticker symbol",TRUE)} -> #VALUE! | E44: =E28 -> #VALUE! | F44: {=_FV(E44,"Exchange abbreviation",TRUE)} -> #VALUE! | G44: =SUM(H44:V44) -> 23.05 | J44: 1.35 | O44: 6.16 | S44: 8.08 | V44: 7.46 | W44: =SUM(H44:V44) -> 23.05 | X44: #VALUE! | AC44: =W44/$W$64 -> 0.17295715
B45: =H29 -> 35 | C45: 2 | D45: {=_FV(E45,"Ticker symbol",TRUE)} -> #VALUE! | E45: =E29 -> #VALUE! | F45: {=_FV(E45,"Exchange abbreviation",TRUE)} -> #VALUE! | G45: =SUM(H45:V45) -> 29.25 | J45: 2.02 | O45: 12.61 | S45: 10.55 | V45: 4.07 | W45: =SUM(H45:V45) -> 29.25 | X45: #VALUE! | AC45: =W45/$W$64 -> 0.21947925
B46: =H30 -> 60 | C46: 3 | D46: {=_FV(E46,"Ticker symbol",TRUE)} -> #VALUE! | E46: =E30 -> #VALUE! | F46: {=_FV(E46,"Exchange abbreviation",TRUE)} -> #VALUE! | G46: =SUM(H46:V46) -> 10.13 | H46: 2.89 | N46: 3.46 | S46: 3.78 | W46: =SUM(H46:V46) -> 10.13 | X46: #VALUE! | AC46: =W46/$W$64 -> 0.076011105
B47: =H27 -> 25 | C47: 4 | D47: {=_FV(E47,"Símbolo bursátil",TRUE)} -> #VALUE! | E47: =E27 -> #VALUE! | F47: XAMS | G47: =SUM(H47:V47) -> 0 | W47: =SUM(H47:V47) -> 0 | X47: =E27 -> #VALUE! | AC47: =W47/$W$64 -> 0
B48: =H9 -> 25 | C48: 5 | D48: {=_FV(E48,"Ticker symbol",TRUE)} -> #VALUE! | E48: =E9 -> #VALUE! | F48: {=_FV(E48,"Exchange abbreviation",TRUE)} -> #VALUE! | G48: =SUM(H48:V48) -> 5.66 | N48: 0.51 | Q48: 2.53 | U48: 2.62 | W48: =SUM(H48:V48) -> 5.66 | X48: #VALUE! | AC48: =W48/$W$64 -> 0.042470173
B49: =H15 -> 20 | C49: 6 | D49: {=_FV(E49,"Ticker symbol",TRUE)} -> #VALUE! | E49: =E15 -> #VALUE! | F49: {=_FV(E49,"Exchange abbreviation",TRUE)} -> #VALUE! | G49: =SUM(H49:V49) -> 2.54 | N49: 0.23 | S49: 1.16 | V49: 1.15 | W49: =SUM(H49:V49) -> 2.54 | X49: #VALUE! | AC49: =W49/$W$64 -> 0.019059053
B50: =H16 -> 25 | C50: 7 | D50: {=_FV(E50,"Ticker symbol",TRUE)} -> #VALUE! | E50: =E16 -> #VALUE! | F50: {=_FV(E50,"Exchange abbreviation",TRUE)} -> #VALUE! | G50: =SUM(H50:V50) -> 3.32 | P50: 1.1 | S50: 1.13 | T50: 1.09 | W50: =SUM(H50:V50) -> 3.32 | X50: #VALUE! | AC50: =W50/$W$64 -> 0.024911833
B51: =H17 -> 20 | C51: 8 | D51: {=_FV(E51,"Ticker symbol",TRUE)} -> #VALUE! | E51: =E17 -> #VALUE! | F51: {=_FV(E51,"Exchange abbreviation",TRUE)} -> #VALUE! | G51: =SUM(H51:V51) -> 9.15 | K51: 0.52 | N51: 0.53 | O51: 0.52 | P51: 0.52 | Q51: 1.4 | S51: 1.44 | T51: 1.44 | U51: 1.4 | V51: 1.38 | W51: =SUM(H51:V51) -> 9.15 | X51: #VALUE! | AC51: =W51/$W$64 -> 0.068657612
B52: =H19 -> 20 | C52: 9 | D52: {=_FV(E52,"Ticker symbol",TRUE)} -> #VALUE! | E52: =E19 -> #VALUE! | F52: {=_FV(E52,"Exchange abbreviation",TRUE)} -> #VALUE! | G52: =SUM(H52:V52) -> 4.17 | O52: 0.8 | S52: 0.91 | V52: 2.46 | W52: =SUM(H52:V52) -> 4.17 | X52: #VALUE! | AC52: =W52/$W$64 -> 0.031289863
B53: =H21 -> 17 | C53: 10 | D53: {=_FV(E53,"Ticker symbol",TRUE)} -> #VALUE! | E53: =E21 -> #VALUE! | F53: {=_FV(E53,"Exchange abbreviation",TRUE)} -> #VALUE! | G53: =SUM(H53:V53) -> 2.55 | O53: 0.85 | S53: 0.85 | V53: 0.85 | W53: =SUM(H53:V53) -> 2.55 | X53: #VALUE! | AC53: =W53/$W$64 -> 0.019134089
B54: =H22 -> 25 | C54: 11 | D54: {=_FV(E54,"Ticker symbol",TRUE)} -> #VALUE! | E54: =E22 -> #VALUE! | F54: {=_FV(E54,"Exchange abbreviation",TRUE)} -> #VALUE! | G54: =SUM(H54:V54) -> 8.58 | N54: 1.79 | Q54: 1.78 | U54: 5.01 | W54: =SUM(H54:V54) -> 8.58 | X54: #VALUE! | AC54: =W54/$W$64 -> 0.064380581
B55: =H23 -> 0 | C55: 12 | D55: {=_FV(E55,"Ticker symbol",TRUE)} -> #VALUE! | E55: =E23 -> #VALUE! | F55: {=_FV(E55,"Exchange abbreviation",TRUE)} -> #VALUE! | G55: =SUM(H55:V55) -> 5.34 | O55: 0.89 | S55: 2.23 | V55: 2.22 | W55: =SUM(H55:V55) -> 5.34 | X55: #VALUE! | AC55: =W55/$W$64 -> 0.040069033
B56: =H10 -> 25 | C56: 13 | D56: {=_FV(E56,"Ticker symbol",TRUE)} -> #VALUE! | E56: =E10 -> #VALUE! | F56: {=_FV(E56,"Exchange abbreviation",TRUE)} -> #VALUE! | G56: =SUM(H56:V56) -> 5.89 | K56: 0.53 | P56: 2.62 | T56: 2.74 | W56: =SUM(H56:V56) -> 5.89 | X56: #VALUE! | AC56: =W56/$W$64 -> 0.044195993
B57: =H11 -> 45 | C57: 14 | D57: {=_FV(E57,"Ticker symbol",TRUE)} -> #VALUE! | E57: =E11 -> #VALUE! | F57: {=_FV(E57,"Exchange abbreviation",TRUE)} -> #VALUE! | G57: =SUM(H57:V57) -> 1.8 | N57: 1.79 | V57: 0.01 | W57: =SUM(H57:V57) -> 1.8 | X57: #VALUE! | AC57: =W57/$W$64 -> 0.013506416
B58: =H13 -> 50 | C58: 15 | D58: {=_FV(E58,"Ticker symbol",TRUE)} -> #VALUE! | E58: =E13 -> #VALUE! | F58: {=_FV(E58,"Exchange abbreviation",TRUE)} -> #VALUE! | G58: =SUM(H58:V58) -> 14.4 | P58: 7.15 | V58: 7.25 | W58: =SUM(H58:V58) -> 14.4 | X58: #VALUE! | AC58: =W58/$W$64 -> 0.10805132
B59: =H12 -> 50 | C59: 17 | D59: {=_FV(E59,"Ticker symbol",TRUE)} -> #VALUE! | E59: =E12 -> #VALUE! | F59: {=_FV(E59,"Exchange abbreviation",TRUE)} -> #VALUE! | G59: =SUM(H59:V59) -> 2.76 | Q59: 2.76 | W59: =SUM(H59:V59) -> 2.76 | X59: #VALUE! | AC59: =W59/$W$64 -> 0.020709837
B60: =H18 -> 50 | C60: 18 | D60: {=_FV(E60,"Ticker symbol",TRUE)} -> #VALUE! | E60: =E18 -> #VALUE! | F60: {=_FV(E60,"Exchange abbreviation",TRUE)} -> #VALUE! | G60: =SUM(H60:V60) -> 4.68 | P60: 4.68 | W60: =SUM(H60:V60) -> 4.68 | X60: #VALUE! | AC60: =W60/$W$64 -> 0.03511668
B61: =H14 -> 51 | C61: 19 | D61: {=_FV(E61,"Ticker symbol",TRUE)} -> #VALUE! | E61: =E14 -> #VALUE! | F61: {=_FV(E61,"Exchange abbreviation",TRUE)} -> #VALUE! | G61: =SUM(H61:V61) -> 0 | W61: =SUM(H61:V61) -> 0 | X61: #VALUE! | AC61: =W61/$W$64 -> 0
B62: =H8 -> 30 | C62: 20 | D62: {=_FV(E62,"Ticker symbol",TRUE)} -> #VALUE! | E62: =E8 -> #VALUE! | F62: {=_FV(E62,"Exchange abbreviation",TRUE)} -> #VALUE! | G62: =SUM(H62:V62) -> 0 | W62: =SUM(H62:V62) -> 0 | X62: #VALUE! | AC62: =W62/$W$64 -> 0
B63: =H20 -> 25 | C63: 21 | D63: {=_FV(E88,"Ticker symbol",TRUE)} -> #VALUE!
B64: =H24 -> 20 | C64: 22 | D64: {=_FV(E120,"Ticker symbol",TRUE)} -> #VALUE! | F64: TOTAL | G64: =SUM(H64:V64) -> 133.27 | H64: =SUM(H44:H63) -> 2.89 | I64: =SUM(I44:I63) -> 0 | J64: =SUM(J44:J63) -> 3.37 | K64: =SUM(K44:K63) -> 1.05 | N64: =SUM(N44:N63) -> 8.31 | O64: =SUM(O44:O63) -> 21.83 | P64: =SUM(P44:P63) -> 16.07 | Q64: =SUM(Q44:Q63) -> 8.47 | S64: =SUM(S44:S63) -> 30.13 | T64: =SUM(T44:T63) -> 5.27 | U64: =SUM(U44:U63) -> 9.03 | V64: =SUM(V44:V63) -> 26.85 | W64: =SUM(W44:W63) -> 133.27
F65: Solo BMEX | G65: =SUM(G57:G61) -> 23.64
F66: Solo Degiro | G66: =SUM(G44:G56) -> 109.63
B67: =SUM(B44:B66) -> 673
C69: XFRA | D69: Deutsche Borse
C70: XAMS | D70: Euronext Amsterdam | G70: Retenciones | N70: 0.93 | O70: 0.46 | P70: 1.4 | Q70: 1.59 | S70: 1.92 | T70: =0.87+0.46+0.36 -> 1.69 | U70: =0.79+1.51+0.44 -> 2.74 | V70: =0.38+0.46+0.72 -> 1.56 | W70: =SUM(H70:V70) -> 12.29
C71: XNAS | D71: NASDAQ
C72: BMEX | D72: Bolsa Madrid | G72: 2024 | I72: Ingreso bruto
G73: TOTAL | H73: Ene | I73: Feb | J73: Mar | K73: Abr | N73: May | O73: Jun | P73: Jul | Q73: Ago | S73: Sep | T73: Oct | U73: Nov | V73: Dic | W73: TOTAL
E75: =E28 -> #VALUE! | F75: {=_FV(E75,"Exchange abbreviation",TRUE)} -> #VALUE! | G75: =SUM(H75:V75) -> 35.56 | J75: 7.71 | O75: 9.12 | S75: 8.66 | V75: 10.07 | W75: =SUM(H75:V75) -> 35.56 | X75: #VALUE! | AC75: =W75/$W$96 -> 0.075375713
E76: =E29 -> #VALUE! | F76: {=_FV(E76,"Exchange abbreviation",TRUE)} -> #VALUE! | G76: =SUM(H76:V76) -> 28.85 | J76: 3.13 | O76: 14.4 | S76: 11.32 | W76: =SUM(H76:V76) -> 28.85 | X76: #VALUE! | AC76: =W76/$W$96 -> 0.06115268
E77: =E30 -> #VALUE! | F77: {=_FV(E77,"Exchange abbreviation",TRUE)} -> #VALUE! | G77: =SUM(H77:V77) -> 21.21 | I77: 4.41 | N77: 5.76 | Q77: 5.67 | U77: 5.37 | W77: =SUM(H77:V77) -> 21.21 | X77: #VALUE! | AC77: =W77/$W$96 -> 0.044958348
E78: =E27 -> #VALUE! | F78: XAMS | G78: =SUM(H78:V78) -> 22.04 | H78: 3.82 | J78: 2.53 | O78: 7.53 | S78: 3.58 | V78: 4.58 | W78: =SUM(H78:V78) -> 22.04 | X78: #VALUE! | AC78: =W78/$W$96 -> 0.04671768
E79: =E9 -> #VALUE! | F79: {=_FV(E79,"Exchange abbreviation",TRUE)} -> #VALUE! | G79: =SUM(H79:V79) -> 9.17 | I79: 2.78 | N79: 2.78 | Q79: 1.8 | U79: 1.81 | W79: =SUM(H79:V79) -> 9.17 | X79: #VALUE! | AC79: =W79/$W$96 -> 0.019437438
E80: =E15 -> #VALUE! | F80: {=_FV(E80,"Exchange abbreviation",TRUE)} -> #VALUE! | G80: =SUM(H80:V80) -> 3.19 | J80: 1.25 | O80: 1.15 | S80: 0.79 | W80: =SUM(H80:V80) -> 3.19 | X80: #VALUE! | AC80: =W80/$W$96 -> 0.0067617695
E81: =E16 -> #VALUE! | F81: {=_FV(E81,"Exchange abbreviation",TRUE)} -> #VALUE! | G81: =SUM(H81:V81) -> 16.71 | H81: 1.2 | J81: 2.94 | K81: 3.2 | O81: 3.12 | S81: 3.04 | V81: 3.21 | W81: =SUM(H81:V81) -> 16.71 | X81: #VALUE! | AC81: =W81/$W$96 -> 0.035419802
E82: =E17 -> #VALUE! | F82: {=_FV(E82,"Exchange abbreviation",TRUE)} -> #VALUE! | G82: =SUM(H82:V82) -> 20.45 | I82: 1.93 | J82: 1.93 | K82: 1.93 | N82: 1.93 | O82: 1.93 | P82: 1.93 | Q82: 1.93 | S82: 1.3 | T82: 1.84 | U82: 1.9 | V82: 1.9 | W82: =SUM(H82:V82) -> 20.45 | X82: #VALUE! | AC82: =W82/$W$96 -> 0.043347394
E83: =E19 -> #VALUE! | F83: {=_FV(E83,"Exchange abbreviation",TRUE)} -> #VALUE! | G83: =SUM(H83:V83) -> 10.18 | J83: 2.52 | O83: 2.53 | S83: 2.51 | V83: 2.62 | W83: =SUM(H83:V83) -> 10.18 | X83: #VALUE! | AC83: =W83/$W$96 -> 0.021578311
E84: =E21 -> #VALUE! | F84: {=_FV(E84,"Exchange abbreviation",TRUE)} -> #VALUE! | G84: =SUM(H84:V84) -> 7.36 | J84: 0.85 | O84: 2.15 | S84: 2.17 | V84: 2.19 | W84: =SUM(H84:V84) -> 7.36 | X84: #VALUE! | AC84: =W84/$W$96 -> 0.015600822
E85: =E22 -> #VALUE! | F85: {=_FV(E85,"Exchange abbreviation",TRUE)} -> #VALUE! | G85: =SUM(H85:V85) -> 26.31 | I85: 5.32 | N85: 7.98 | Q85: 6.43 | U85: 6.58 | W85: =SUM(H85:V85) -> 26.31 | X85: #VALUE! | AC85: =W85/$W$96 -> 0.055768701
E86: =E23 -> #VALUE! | F86: {=_FV(E86,"Exchange abbreviation",TRUE)} -> #VALUE! | G86: =SUM(H86:V86) -> 6.9 | J86: 1.25 | O86: 0.8 | S86: 2.35 | V86: 2.5 | W86: =SUM(H86:V86) -> 6.9 | X86: #VALUE! | AC86: =W86/$W$96 -> 0.014625771
E87: =E10 -> #VALUE! | F87: {=_FV(E87,"Exchange abbreviation",TRUE)} -> #VALUE! | G87: =SUM(H87:V87) -> 9.98 | H87: 2.9 | K87: 3.1 | P87: 2 | T87: 1.98 | W87: =SUM(H87:V87) -> 9.98 | X87: #VALUE! | AC87: =W87/$W$96 -> 0.021154376
E88: #VALUE! | F88: {=_FV(E88,"Exchange abbreviation",TRUE)} -> #VALUE! | G88: =SUM(H88:V88) -> 11.34 | Q88: 5.7 | T88: 5.64 | W88: =SUM(H88:V88) -> 11.34 | X88: #VALUE! | AC88: =W88/$W$96 -> 0.024037137
E89: =E11 -> #VALUE! | F89: {=_FV(E89,"Exchange abbreviation",TRUE)} -> #VALUE! | G89: =SUM(H89:V89) -> 158.97 | O89: 5.24 | V89: 153.73 | W89: =SUM(H89:V89) -> 158.97 | X89: #VALUE! | AC89: =W89/$W$96 -> 0.33696505
E90: =E13 -> #VALUE! | F90: {=_FV(E90,"Exchange abbreviation",TRUE)} -> #VALUE! | G90: =SUM(H90:V90) -> 32.66 | P90: 24.15 | V90: 8.51 | W90: =SUM(H90:V90) -> 32.66 | X90: #VALUE! | AC90: =W90/$W$96 -> 0.06922865
E91: =E12 -> #VALUE! | F91: {=_FV(E91,"Exchange abbreviation",TRUE)} -> #VALUE! | G91: =SUM(H91:V91) -> 28.68 | J91: 20.82 | S91: 7.86 | W91: =SUM(H91:V91) -> 28.68 | X91: #VALUE! | AC91: =W91/$W$96 -> 0.060792335
E92: =E18 -> #VALUE! | F92: {=_FV(E92,"Exchange abbreviation",TRUE)} -> #VALUE! | G92: =SUM(H92:V92) -> 19.65 | H92: 3.2 | P92: 16.45 | W92: =SUM(H92:V92) -> 19.65 | X92: #VALUE! | AC92: =W92/$W$96 -> 0.041651652
E93: =E14 -> #VALUE! | F93: {=_FV(E93,"Exchange abbreviation",TRUE)} -> #VALUE! | G93: =SUM(H93:V93) -> 1.13 | I93: 1.13 | W93: =SUM(H93:V93) -> 1.13 | X93: #VALUE! | AC93: =W93/$W$96 -> 0.002395235
E94: =E8 -> #VALUE! | F94: {=_FV(E94,"Exchange abbreviation",TRUE)} -> #VALUE! | G94: =SUM(H94:V94) -> 1.43 | I94: 1.43 | W94: =SUM(H94:V94) -> 1.43 | X94: #VALUE! | AC94: =W94/$W$96 -> 0.0030311381
F96: TOTAL | G96: =SUM(H96:V96) -> 471.77 | H96: =SUM(H75:H95) -> 11.12 | I96: =SUM(I75:I95) -> 17 | J96: =SUM(J75:J95) -> 44.93 | K96: =SUM(K75:K95) -> 8.23 | N96: =SUM(N75:N95) -> 18.45 | O96: =SUM(O75:O95) -> 47.97 | P96: =SUM(P75:P95) -> 44.53 | Q96: =SUM(Q75:Q95) -> 21.53 | S96: =SUM(S75:S95) -> 43.58 | T96: =SUM(T75:T95) -> 9.46 | U96: =SUM(U75:U95) -> 15.66 | V96: =SUM(V75:V95) -> 189.31 | W96: =SUM(W75:W95) -> 471.77
F97: Solo BMEX | G97: =SUM(G89:G94) -> 242.52
F98: Solo Degiro | G98: =SUM(G75:G88) -> 229.25
G103: 2025
G104: TOTAL | H104: Ene | I104: Feb | J104: Mar | K104: Abr | N104: May | O104: Jun | P104: Jul | Q104: Ago | S104: Sep | T104: Oct | U104: Nov | V104: Dic | W104: TOTAL
E106: =E28 -> #VALUE! | F106: {=_FV(E106,"Exchange abbreviation",TRUE)} -> #VALUE! | G106: =SUM(H106:V106) -> 53.31 | J106: 8.95 | O106: 14.44 | S106: 12.31 | V106: 17.61 | W106: =SUM(H106:V106) -> 53.31 | X106: #VALUE! | AC106: =W106/$W$96 -> 0.11299998
E107: =E29 -> #VALUE! | F107: {=_FV(E107,"Exchange abbreviation",TRUE)} -> #VALUE! | G107: =SUM(H107:V107) -> 44.7 | J107: 3.55 | O107: 18.13 | S107: 16.23 | V107: 6.79 | W107: =SUM(H107:V107) -> 44.7 | X107: #VALUE! | AC107: =W107/$W$96 -> 0.09474956
E108: =E30 -> #VALUE! | F108: {=_FV(E108,"Exchange abbreviation",TRUE)} -> #VALUE! | G108: =SUM(H108:V108) -> 32.14 | I108: 6.21 | N108: 8.55 | Q108: 9.13 | U108: 8.25 | W108: =SUM(H108:V108) -> 32.14 | X108: #VALUE! | AC108: =W108/$W$96 -> 0.068126418
E109: =E27 -> #VALUE! | F109: XAMS | G109: =SUM(H109:V109) -> 19.17 | J109: 2.91 | O109: 8.92 | S109: 3.3 | V109: 4.04 | W109: =SUM(H109:V109) -> 19.17 | X109: #VALUE! | AC109: =W109/$W$96 -> 0.040634207
E110: =E9 -> #VALUE! | F110: {=_FV(E110,"Exchange abbreviation",TRUE)} -> #VALUE! | G110: =SUM(H110:V110) -> 11.14 | I110: 1.9 | N110: 2.58 | Q110: 3.32 | U110: 3.34 | W110: =SUM(H110:V110) -> 11.14 | X110: #VALUE! | AC110: =W110/$W$96 -> 0.023613201
E111: =E15 -> #VALUE! | F111: {=_FV(E111,"Exchange abbreviation",TRUE)} -> #VALUE! | G111: =SUM(H111:V111) -> 0 | W111: =SUM(H111:V111) -> 0 | X111: #VALUE! | AC111: =W111/$W$96 -> 0
E112: =E16 -> #VALUE! | F112: {=_FV(E112,"Exchange abbreviation",TRUE)} -> #VALUE! | G112: =SUM(H112:V112) -> 17.1 | J112: 3.84 | O112: 3.65 | S112: 4.8 | V112: 4.81 | W112: =SUM(H112:V112) -> 17.1 | X112: #VALUE! | AC112: =W112/$W$96 -> 0.036246476
E113: =E17 -> #VALUE! | F113: {=_FV(E113,"Exchange abbreviation",TRUE)} -> #VALUE! | G113: =SUM(H113:V113) -> 24.27 | H113: 1.9 | I113: 1.7 | J113: 1.74 | K113: 1.75 | N113: 1.75 | O113: 1.75 | P113: 2.3 | Q113: 2.29 | S113: 2.26 | T113: 2.26 | U113: 2.31 | V113: 2.26 | W113: =SUM(H113:V113) -> 24.27 | X113: #VALUE! | AC113: =W113/$W$96 -> 0.05144456
E114: =E19 -> #VALUE! | F114: {=_FV(E114,"Exchange abbreviation",TRUE)} -> #VALUE! | G114: =SUM(H114:V114) -> 20.58 | J114: 5.12 | O114: 4.7 | S114: 4.61 | V114: 6.15 | W114: =SUM(H114:V114) -> 20.58 | X114: #VALUE! | AC114: =W114/$W$96 -> 0.043622952
E115: =E21 -> #VALUE! | F115: {=_FV(E115,"Exchange abbreviation",TRUE)} -> #VALUE! | G115: =SUM(H115:V115) -> 31.64 | J115: 4.58 | O115: 9.06 | S115: 9.1 | V115: 8.9 | W115: =SUM(H115:V115) -> 31.64 | X115: #VALUE! | AC115: =W115/$W$96 -> 0.067066579
E116: =E22 -> #VALUE! | F116: {=_FV(E116,"Exchange abbreviation",TRUE)} -> #VALUE! | G116: =SUM(H116:V116) -> 33.85 | I116: 6.94 | N116: 8.4 | Q116: 8.11 | U116: 10.4 | W116: =SUM(H116:V116) -> 33.85 | X116: #VALUE! | AC116: =W116/$W$96 -> 0.071751065
E117: =E23 -> #VALUE! | F117: {=_FV(E117,"Exchange abbreviation",TRUE)} -> #VALUE! | G117: =SUM(H117:V117) -> 0 | W117: =SUM(H117:V117) -> 0 | X117: #VALUE! | AC117: =W117/$W$96 -> 0
E118: =E10 -> #VALUE! | F118: {=_FV(E118,"Exchange abbreviation",TRUE)} -> #VALUE! | G118: =SUM(H118:V118) -> 14.08 | H118: 2.12 | K118: 4.1 | P118: 3.93 | T118: 3.93 | W118: =SUM(H118:V118) -> 14.08 | X118: #VALUE! | AC118: =W118/$W$96 -> 0.029845052
E119: #VALUE! | F119: {=_FV(E119,"Exchange abbreviation",TRUE)} -> #VALUE! | G119: =SUM(H119:V119) -> 16.66 | K119: 5.85 | V119: 10.81 | W119: =SUM(H119:V119) -> 16.66 | X119: #VALUE! | AC119: =W119/$W$96 -> 0.035313818
E120: #VALUE! | F120: XETR | G120: =SUM(H120:V120) -> 10.77 | O120: 3 | S120: 2.58 | V120: 5.19 | W120: =SUM(H120:V120) -> 10.77 | X120: #VALUE! | AC120: =W120/$W$96 -> 0.022828921
...

Sheet CandidatosInv
B3: Candidatos para Inversion
B5: Valor | C5: MESES DIVIDENDOS | D5: Paises | E5: Monedas | F5: SECTOR | G5: DIVIDENDO TEÓRICO | H5: Dinero bruto teórico | I5: Dividendo creciente o Vaca Lechera | J5: Yield Por Invertido | K5: Rango | L5: Adquirido
B6: 3M | C6: 3 - 6 - 9 -12 | D6: Estados unidos | E6: Dolares | F6: INDUSTRIA | G6: 5.36 | H6: 1608 | I6: Dividendo Creciente | J6: 0.4342 | K6: Más del 5%
B7: ACS | C7: 2-7 | D7: España | E7: Euros | F7: INFRAESTRUCTURAS | I7: Vaca Lechera | L7: X
B8: AHOLD DELHAIZE | C8: 4- 8 | D8: Holanda | E8: Euros | F8: ALIMENTACIÓN | G8: 0.76 | H8: 152 | I8: Dividendo Creciente | J8: 0.0616 | K8: Más del 5%
B9: ALTRIA | C9: 1 - 4 - 7 -10 | D9: Estados unidos | E9: Dolares | F9: TABACO | G9: 3.13 | H9: 313 | I9: Vaca Lechera | J9: 0.2535 | K9: Más del 5%
B10: AT&T | C10: 2 - 5 - 8 - 11 | D10: Estados unidos | E10: Dolares | F10: TELECO | G10: 1.9 | H10: 380 | I10: Dividendo Creciente | J10: 0.1539 | K10: Más del 5% | L10: X
B11: ATLANTICA YIELD | C11: 3 - 6 - 9 -12 | D11: Inglaterra | E11: Dolares | F11: UTILITIES | G11: 1.53 | H11: 459 | I11: Vaca Lechera | J11: 0.1239 | K11: Más del 5%
B12: AVIVA | C12: 4 - 8 | D12: Inglaterra | E12: Libras | F12: SEGUROS | G12: 0.07 | H12: 28 | I12: Vaca Lechera | J12: 0.0057 | K12: Menor que 3%
B13: BEIJING ENTERPRISES HOLD. | C13: 7 - 10 | D13: China | E13: Hong Kong Dolares | F13: UTILITIES | G13: 0.13 | H13: 52 | I13: Dividendo Creciente | J13: 0.0105 | K13: Menor que 3%
B14: BRITISH AMER. TOBACO | C14: 2 - 5 - 8 - 11 | D14: Inglaterra | E14: Libras | F14: TABACO | G14: 2.44 | H14: 488 | I14: Vaca Lechera | J14: 0.1976 | K14: Más del 5%
B15: BROOKFIELD INFRAESTRUC. | C15: 3 - 6 - 9 -12 | D15: Canada | E15: Dolares | F15: INFRAESTRUCTURAS | G15: 1.83 | H15: 732 | I15: Dividendo Creciente | J15: 0.1482 | K15: Más del 5%
B16: BROOKFIELD PROP. PART. | C16: 3 - 6 - 9 -12 | D16: Canada | E16: Dolares | F16: REIT | G16: 1.21 | H16: 121 | I16: Vaca Lechera | J16: 0.098 | K16: Más del 5%
B17: CHEMOURS-CO | C17: 1 - 4 - 7 -10 | D17: Estados unidos | E17: Dolares | F17: INDUSTRIA | G17: 0.91 | H17: 364 | I17: Dividendo Creciente | J17: 0.0737 | K17: Más del 5%
B18: CISCO | C18: 1 - 4 - 7 -10 | D18: Estados unidos | E18: Dolares | F18: TECNOLÓGICA | G18: 1.31 | H18: 131 | I18: Dividendo Creciente | J18: 0.1061 | K18: Más del 5%
B19: CK INFRASTRUCTURE HOLD. | C19: 5 - 9 | D19: China | E19: Hong Kong Dolares | F19: INFRAESTRUCTURAS | G19: 0.29 | H19: 58 | I19: Dividendo Creciente | J19: 0.0235 | K19: Menor que 3%
B20: COCA COLA | C20: 4-7-10-12 | D20: Estados unidos | E20: Dolares | F20: BEBIDAS Y SNACKS | G20: 1.49 | H20: 298 | I20: Dividendo Creciente | J20: 0.1207 | K20: Más del 5%
B21: COLGATE | C21: 2 - 5 - 8 - 11 | D21: Estados unidos | E21: Dolares | F21: INDUSTRIA | G21: 1.6 | H21: 320 | I21: Dividendo Creciente | J21: 0.1296 | K21: Más del 5%
B22: COMPASS MINERALS | C22: 3 - 6 - 9 -12 | D22: Estados unidos | E22: Dolares | F22: MINA | G22: 2.62 | H22: 1048 | I22: Vaca Lechera | J22: 0.2122 | K22: Más del 5%
B23: DIAGEO | C23: 4 - 10 | D23: Inglaterra | E23: Libras | F23: ALCOHOL | G23: 0.8 | H23: 240 | I23: Dividendo Creciente | J23: 0.0648 | K23: Más del 5% | L23: X
B24: DISNEY | C24: 1 - 7 | D24: Estados unidos | E24: Dolares | F24: CINE | G24: 0 | H24: 0 | I24: Dividendo Creciente | J24: 0 | K24: 0
B25: ENAGAS | C25: 7 - 12 | D25: España | E25: Euros | F25: UTILITIES | G25: 1.59 | H25: 636 | I25: Vaca Lechera | J25: 0.1288 | K25: Más del 5% | L25: X
B26: ENBRIDGE INC | C26: 3 - 6 - 9 -12 | D26: Canada | E26: Dolares | F26: UTILITIES | G26: 2.95 | H26: 295 | I26: Vaca Lechera | J26: 0.239 | K26: Más del 5%
B27: GEO GROUP | C27: 2-5-7-11 | D27: Estados unidos | E27: Dolares | F27: REIT | G27: 1.24 | H27: 496 | I27: Vaca Lechera | J27: 0.1004 | K27: Más del 5%
B28: H&R BLOCK INC | C28: 1 - 4 - 7 -10 | D28: Estados unidos | E28: Dolares | F28: GESTIÓN FISCAL | G28: 0.95 | H28: 380 | I28: Vaca Lechera | J28: 0.077 | K28: Más del 5%
B29: INNOVATI INDUST PROP INC | C29: 3 - 6 - 9 -12 | D29: Estados unidos | E29: Dolares | F29: REIT | G29: 4.26 | H29: 1278 | I29: Vaca Lechera | J29: 0.3451 | K29: Más del 5%
B30: INTEL | C30: 3 - 6 - 9 -12 | D30: Estados unidos | E30: Dolares | F30: TECNOLÓGICA | G30: 1.2 | H30: 120 | I30: Dividendo Creciente | J30: 0.0972 | K30: Más del 5% | L30: X
B31: IRON MOUNTAIN | C31: 1 - 4 - 7 -10 | D31: Estados unidos | E31: Dolares | F31: REIT | G31: 2.25 | H31: 675 | I31: Vaca Lechera | J31: 0.1823 | K31: Más del 5%
B32: JOHNSON & JOHNSON | C32: 3 - 6 - 9 -12 | D32: Estados unidos | E32: Dolares | F32: FARMACEUTICA | G32: 3.68 | H32: 1104 | I32: Dividendo Creciente | J32: 0.2981 | K32: Más del 5%
B33: KNOT OFFSHORE PARTNERS | C33: 2 - 5 - 8 - 11 | D33: Inglaterra | E33: Dolares | F33: TRANSPORTE | G33: 1.9 | H33: 570 | I33: Vaca Lechera | J33: 0.1539 | K33: Más del 5%
B34: KRAFT HEINZ CO | C34: 3-5-8-12 | D34: Estados unidos | E34: Dolares | F34: ALIMENTACIÓN | G34: 1.46 | H34: 146 | I34: Dividendo Creciente | J34: 0.1183 | K34: Más del 5% | L34: X
B35: LOGISTA | C35: 3 - 8 | D35: España | E35: Euros | F35: TRANSPORTE | G35: 1.18 | H35: 472 | I35: Vaca Lechera | J35: 0.0956 | K35: Más del 5% | L35: X
B36: MAPFRE | C36: 6-12 | D36: España | E36: Euros | F36: SEGUROS | G36: 0.15 | H36: 30 | I36: Vaca Lechera | J36: 0.0122 | K36: Menor que 3%
B37: MCDONALDS | C37: 3 - 6 - 9 - 12 | D37: Estados unidos | E37: Dolares | F37: ALIMENTACIÓN | G37: 4.56 | H37: 1368 | I37: Dividendo Creciente | J37: 0.3694 | K37: Más del 5%
B38: OFFICE PROPERTIES INCOME | C38: 2 - 5 - 8 - 11 | D38: Estados unidos | E38: Dolares | F38: REIT | G38: 2 | H38: 800 | I38: Vaca Lechera | J38: 0.162 | K38: Más del 5%
B39: PAYCHEX | C39: 2 - 5 - 8 - 11 | D39: Estados unidos | E39: Dolares | F39: EMPLEO | G39: 2.26 | H39: 226 | I39: Dividendo Creciente | J39: 0.1831 | K39: Más del 5%
B40: PEPSICOLA | C40: 1 - 3 - 6 - 9 | D40: Estados unidos | E40: Dolares | F40: BEBIDAS Y SNACKS | G40: 3.73 | H40: 1492 | I40: Dividendo Creciente | J40: 0.3021 | K40: Más del 5%
B41: PFIZER | C41: 3 - 6- 9- 12 | D41: Estados unidos | E41: Dolares | F41: FARMACEUTICA | I41: ?? | J41: ?? | K41: ?? | L41: X
B42: PHILIPS MORRIS INTL | C42: 1-4-7-10 | D42: Estados unidos | E42: Dolares | F42: TABACO | G42: 4.37 | H42: 874 | I42: Vaca Lechera | J42: 0.354 | K42: Más del 5%
B43: PRIM | C43: 1-7 | D43: España | E43: Euros | F43: INDUSTRIA | G43: 0.33 | H43: 132 | I43: Vaca Lechera | J43: 0.0267 | K43: Menor que 3%
B44: REALTY INCOME | C44: All Months | D44: Estados unidos | E44: Dolares | F44: REIT | G44: 2.55 | H44: 255 | I44: Vaca Lechera | J44: 0.2066 | K44: Más del 5%
B45: REE | C45: 1 - 7 | D45: España | E45: Euros | F45: UTILITIES | G45: 1.05 | H45: 105 | I45: Vaca Lechera | J45: 0.0851 | K45: Más del 5% | L45: X
B46: SERVENT TRENT | C46: 4 - 10 | D46: Inglaterra | E46: Libras | F46: UTILITIES | G46: 1.17 | H46: 351 | I46: Vaca Lechera | J46: 0.0948 | K46: Más del 5%
B47: T. ROWE PRICE | C47: 3 - 6 - 9 -12 | D47: Estados unidos | E47: Dolares | F47: FINANCIERA | G47: 3.28 | H47: 656 | I47: Dividendo Creciente | J47: 0.2657 | K47: Más del 5%
B48: TELEFONICA | C48: 6-12 | D48: España | E48: Euros | F48: TELECO | G48: 0.4 | H48: 80 | I48: Vaca Lechera | J48: 0.0324 | K48: Entre 3% y 5%
B49: TRITON | C49: 3 - 6 - 9 - 12 | D49: Estados unidos | E49: Dolares | F49: REIT | G49: 1.9 | H49: 760 | I49: Vaca Lechera | J49: 0.1539 | K49: Más del 5%
B50: TYSON FOODS | C50: 3 - 6 - 9 - 12 | D50: Estados unidos | E50: Dolares | F50: ALIMENTACIÓN | G50: ?? | H50: ?? | I50: Vaca Lechera | J50: ?? | K50: ??
B51: UGI | C51: 1 - 4 - 7 -10 | D51: Estados unidos | E51: Dolares | F51: UTILITIES | G51: 1.2 | H51: 240 | I51: Dividendo Creciente | J51: 0.0972 | K51: Más del 5%
B52: UNILEVER | C52: 2 - 5 - 8 - 11 | D52: Inglaterra | E52: Libras | F52: ALIMENTACIÓN | G52: 1.68 | H52: 504 | I52: Dividendo Creciente | J52: 0.1361 | K52: Más del 5% | L52: X
B53: UNITED UTILITIES | C53: 2 - 8 | D53: Inglaterra | E53: Libras | F53: UTILITIES | G53: 0.5 | H53: 150 | I53: Dividendo Creciente | J53: 0.0405 | K53: Entre 3% y 5%
B54: UPS | C54: 2 - 5 - 8 - 11 | D54: Estados unidos | E54: Dolares | F54: TRANSPORTE | G54: 3.68 | H54: 368 | I54: Dividendo Creciente | J54: 0.2981 | K54: Más del 5%
B55: VENTAS | C55: 1 - 4 - 7 -10 | D55: Estados unidos | E55: Dolares | F55: REIT | G55: 1.64 | H55: 328 | I55: Vaca Lechera | J55: 0.1328 | K55: Más del 5%
B56: VODAFONE | C56: 2 - 8 | D56: Inglaterra | E56: Libras | F56: TELECO | G56: 0.09 | H56: 27 | I56: Vaca Lechera | J56: 0.0073 | K56: Menor que 3%
B57: W.P. CAREY | C57: 3 - 6 - 9 -12 | D57: Estados unidos | E57: Dolares | F57: REIT | G57: 3.81 | H57: 762 | I57: Vaca Lechera | J57: 0.3086 | K57: Más del 5%
B58: ZARDOYA OTIS | C58: 1 - 4 - 7 | D58: España | E58: Euros | F58: ASCENSORES | G58: 0.32 | H58: 32 | I58: Vaca Lechera | J58: 0.0259 | K58: Menor que 3%
L59: =COUNTA(L6:L58) -> 10 | M59: Total Compañias adquiridas
B62: ETFs
B63: #VALUE! | E63: {=_FV(B63,"Símbolo bursátil",TRUE)} -> #VALUE! | F63: {=_FV(B63,"Precio")} -> #VALUE!
B64: #VALUE! | E64: {=_FV(B64,"Símbolo bursátil",TRUE)} -> #VALUE! | F64: {=_FV(B64,"Precio")} -> #VALUE!
B65: #VALUE! | E65: {=_FV(B65,"Símbolo bursátil",TRUE)} -> #VALUE! | F65: {=_FV(B65,"Precio")} -> #VALUE!
B66: #VALUE! | E66: {=_FV(B66,"Símbolo bursátil",TRUE)} -> #VALUE! | F66: {=_FV(B66,"Precio")} -> #VALUE!
B67: #VALUE! | E67: {=_FV(B67,"Símbolo bursátil",TRUE)} -> #VALUE! | F67: {=_FV(B67,"Precio")} -> #VALUE!
B68: #VALUE! | E68: {=_FV(B68,"Símbolo bursátil",TRUE)} -> #VALUE! | F68: {=_FV(B68,"Precio")} -> #VALUE!
B69: #VALUE! | E69: {=_FV(B69,"Símbolo bursátil",TRUE)} -> #VALUE! | F69: {=_FV(B69,"Precio")} -> #VALUE!
B70: #VALUE! | E70: {=_FV(B70,"Símbolo bursátil",TRUE)} -> #VALUE! | F70: {=_FV(B70,"Precio")} -> #VALUE!

Sheet VidaLaboral
B3: RÉGIMEN | C3: EMPRESA | D3: FECHA ALTA | E3: FECHA DE BAJA | F3: C.T. | G3: G.C. | H3: DÍAS | I3: Comprobacion / Actualizacion | J3: Meses | K3: Años
B4: GENERAL | C4: NOVARTIS FARMACEUTICA, S.A. | D4: 44197 | E4: --- | F4: 100 | G4: 1 | H4: =I4 -> 1946 | I4: =TODAY() - D4 -> 1946 | J4: =ROUND(I4/30,0) -> 65 | K4: =I4/365 -> 5.3315068 | M4: =ROUND(I4/30,0) -> 65 | N4: Actualidad meses Novartis
B5: GENERAL | C5: VACACIONES RETRIBUIDAS Y NO DISFRUTADAS | D5: 44197 | E5: 44214 | H5: 18 | I5: =E5-D5 +1 -> 18 | M5: =I4/365 -> 5.3315068 | N5: Actualidad años Novartis
B6: GENERAL | C6: VACACIONES RETRIBUIDAS Y NO DISFRUTADAS | D6: 42248 | E6: 42249 | H6: 2 | I6: =E6-D6 +1 -> 2
B7: GENERAL | C7: VACACIONES RETRIBUIDAS Y NO DISFRUTADAS | D7: 41573 | E7: 41581 | H7: 9 | I7: =E7-D7+1 -> 9
B8: GENERAL | C8: VACACIONES RETRIBUIDAS Y NO DISFRUTADAS | D8: 40543 | E8: 40552 | H8: 10 | I8: =E8-D8+1 -> 10
B9: GENERAL | C9: VACACIONES RETRIBUIDAS Y NO DISFRUTADAS | D9: 39904 | E9: 39911 | H9: 8 | I9: =E9-D9+1 -> 8
B10: GENERAL | C10: VACACIONES RETRIBUIDAS Y NO DISFRUTADAS | D10: 38974 | E10: 38978 | H10: 5 | I10: =E10-D10 +1 -> 5
B11: GENERAL | C11: VACACIONES RETRIBUIDAS Y NO DISFRUTADAS | D11: 38483 | E11: 38493 | H11: 11 | I11: =E11-D11 +1 -> 11
B12: GENERAL | C12: VACACIONES RETRIBUIDAS Y NO DISFRUTADAS | D12: 38101 | E12: 38119 | H12: 19 | I12: =E12-D12 +1 -> 19
B13: GENERAL | C13: ROCHE DIAGNOSTICS,S.L. | D13: 42248 | E13: 44196 | F13: 100 | G13: 2 | H13: 1949 | I13: =(E13-D13) +1 -> 1949 | J13: =ROUND(H13/30,1) -> 65 | K13: =H13/365 -> 5.339726 | L13: MAXIMO
B14: GENERAL | C14: ALTRAN INNOVACION,S.L. | D14: 41575 | E14: 42247 | F14: 100 | G14: 2 | H14: 673 | I14: =(E14-D14) +1 -> 673 | J14: =ROUND(H14/30,0) -> 22 | K14: =H14/365 -> 1.8438356
B15: GENERAL | C15: SOGETI ESPAñA,S.L. (Grifols) | D15: 40637 | E15: 41572 | F15: 100 | G15: 2 | H15: 936 | I15: =(E15-D15) +1 -> 936 | J15: =ROUND(H15/30,0) -> 31 | K15: =H15/365 -> 2.5643836
B16: GENERAL | C16: NEXUS INFORMATION TECNOLOGY, S.A. (H St Pau) | D16: 40364 | E16: 40542 | F16: 100 | G16: 1 | H16: 179 | I16: =(E16-D16) +1 -> 179 | J16: =ROUND(H16/30,1) -> 6 | K16: =H16/365 -> 0.49041096
B17: AUTONOMO | C17: 6201 Actividades de programación informát | D17: 39934 | E17: 40359 | H17: 426 | I17: =(E17-D17) +1 -> 426 | J17: =ROUND(H17/30,0) -> 14 | K17: =H17/365 -> 1.1671233 | L17: (Novartis Barbera)
B18: GENERAL | C18: PRESTACION DESEMPLEO. EXTINCION | D18: 39912 | E18: 39952 | G18: 3 | H18: 19 | I18: =(E18-D18) +1 -> 41
B19: GENERAL | C19: MIPS SOFTWARE IBERICA, S.L.U. (H.Clinic) | D19: 38985 | E19: 39903 | F19: 100 | G19: 3 | H19: 889 | I19: =(E19-D19) +1 -> 919 | J19: =ROUND(H19/30,0) -> 30 | K19: =H19/365 -> 2.4356164
B20: GENERAL | C20: OLIVIA SISTEMAS, S.L. | D20: 38677 | E20: 38973 | F20: 100 | G20: 3 | H20: 297 | I20: =(E20-D20) +1 -> 297 | J20: =ROUND(H20/30,0) -> 10 | K20: =H20/365 -> 0.81369863
B21: GENERAL | C21: PRESTACION DESEMPLEO. EXTINCION | D21: 38494 | E21: 38676 | G21: 1 | H21: 183 | I21: =(E21-D21) +1 -> 183
B22: GENERAL | C22: TRAKHEALTH,S.L. (H.La Paz, Madrid) | D22: 38103 | E22: 38482 | F22: 100 | G22: 1 | H22: 380 | I22: =(E22-D22) +1 -> 380 | J22: =ROUND(H22/30,0) -> 13 | K22: =H22/365 -> 1.0410959
B23: GENERAL | C23: SOCIEDAD DE VALIDACION DE SISTEMAS,S.L. | D23: 37712 | E23: 38100 | F23: 100 | G23: 3 | H23: 389 | I23: =(E23-D23) +1 -> 389 | J23: =ROUND(H23/30,1) -> 13 | K23: =H23/365 -> 1.0657534 | L23: SVS+CITS = 3'3 años
B24: GENERAL | C24: COMPLIANCE AND IT SERVICES,S.L. | D24: 37288 | E24: 37711 | F24: 100 | G24: 3 | H24: 395 | I24: =(E24-D24) +1 -> 424 | J24: =ROUND(H24/30,0) -> 13 | K24: =H24/365 -> 1.0821918
B25: GENERAL | C25: SOCIEDAD DE VALIDACION DE SISTEMAS, S.L. | D25: 36858 | E25: 37287 | F25: 109 | G25: 3 | H25: 430 | I25: =(E25-D25) +1 -> 430 | J25: =ROUND(H25/30,0) -> 14 | K25: =H25/365 -> 1.1780822
B26: REP.COMER | C26: APPEYRON RESEACH,S.A. | D26: 36213 | E26: 36854 | F26: 19 | G26: 5 | H26: 642 | I26: =(E26-D26) +1 -> 642 | J26: =ROUND(H26/30,0) -> 21 | K26: =H26/365 -> 1.7589041
B27: GENERAL | C27: AJUNTAMENT DE SANT ADRIA DE BESOS | D27: 35831 | E27: 36160 | F27: 14 | G27: 4 | H27: 325 | I27: =(E27-D27) +1 -> 330 | J27: =ROUND(H27/30,0) -> 11 | K27: =H27/365 -> 0.89041096
B28: GENERAL | C28: PRESTACION DESEMPLEO. EXTINCION | D28: 35582 | E28: 35825 | G28: 3 | H28: 244 | I28: =(E28-D28) +1 -> 244
B29: GENERAL | C29: MENARINI DIAGNOSTICOS,S.A. | D29: 35034 | E29: 35581 | F29: 100 | G29: 3 | H29: 548 | I29: =(E29-D29) +1 -> 548 | J29: =ROUND(H29/30,0) -> 18 | K29: =H29/365 -> 1.5013699
B30: GENERAL | C30: MARESMAR, S.A. | D30: 34655 | E30: 34930 | G30: 2 | H30: 276 | I30: =(E30-D30) +1 -> 276 | J30: =ROUND(H30/30,0) -> 9 | K30: =H30/365 -> 0.75616438 | L30: Total Maresmar = 1 año
B31: GENERAL | C31: C.O. OLIMPICO BARCELONA 92 | D31: 33807 | E31: 33837 | G31: 7 | H31: 31 | I31: =(E31-D31) +1 -> 31 | J31: =ROUND(H31/30,1) -> 1 | K31: =H31/365 -> 0.084931507 | L31: MINIMO
B32: GENERAL | C32: SERVICIOS DE INFORMATICA PROFESIONAL (SIPSA) | D32: 33227 | E32: 33266 | G32: 9 | H32: 40 | I32: =(E32-D32) +1 -> 40 | J32: =ROUND(H32/30,0) -> 1 | K32: =H32/365 -> 0.10958904
B33: GENERAL | C33: MAREMAR S.A. | D33: 33135 | E33: 33207 | G33: 5 | H33: 65 | I33: =(E33-D33) +1 -> 73 | J33: =ROUND(H33/30,0) -> 2 | K33: =H33/365 -> 0.17808219
B34: GENERAL | C34: PRESTACION DESEMPLEO. EXTINCION | D34: 32782 | E34: 32872 | G34: 8 | H34: 91 | I34: =(E34-D34) +1 -> 91
B35: GENERAL | C35: LA SEDA DE BARCELONA, S.A. | D35: 32660 | E35: 32781 | G35: 8 | H35: 122 | I35: =(E35-D35) +1 -> 122 | J35: =ROUND(H35/30,0) -> 4 | K35: =H35/365 -> 0.33424658 | L35: Total La Seda: 16 meses
B36: GENERAL | C36: SUBSIDIO DESEMPLEO. EXTINCION | D36: 32448 | E36: 32567 | G36: 8 | I36: =(E36-D36) +1 -> 120
B37: GENERAL | C37: LA SEDA DE BARCELONA, S.A. | D37: 32295 | E37: 32416 | G37: 8 | H37: 103 | I37: =(E37-D37) +1 -> 122 | J37: =ROUND(H37/30,0) -> 3 | K37: =H37/365 -> 0.28219178
B38: GENERAL | C38: PRESTACION DESEMPLEO. EXTINCION | D38: 32051 | E38: 32141 | H38: 91 | I38: =(E38-D38) +1 -> 91
B39: GENERAL | C39: LA SEDA DE BARCELONA, S.A. | D39: 31929 | E39: 32050 | G39: 8 | H39: 114 | I39: =(E39-D39) +1 -> 122 | J39: =ROUND(H39/30,0) -> 4 | K39: =H39/365 -> 0.31232877
B40: GENERAL | C40: SUBSIDIO DESEMPLEO. EXTINCION | D40: 31717 | E40: 31866 | G40: 10 | I40: =(E40-D40) +1 -> 150
B41: GENERAL | C41: LA SEDA DE BARCELONA, S.A. | D41: 31533 | E41: 31685 | G41: 8 | H41: 153 | I41: =(E41-D41) +1 -> 153 | J41: =ROUND(H41/30,0) -> 5 | K41: =H41/365 -> 0.41917808
H43: =SUM(H4:H42) -> 12018 | I43: =SUM(I4:I42) -> 12409 | J43: =SUM(J4:J42) -> 375 | K43: =SUM(K4:K42) -> 30.980822 | M43: =SUM(K13:K42) + M5 -> 30.980822
H44: DIAS | J44: MESES | K44: AÑOS | M44: Actualización años

Sheet Jubilacion
B3: Simulación Jubilación

Sheet IngGas10-20
B3: Ingresos vs Gastos - Over Time
B5: 2010 - 2024
B7: Año | C7: Mes | D7: Ingresos | E7: Gastos | F7: Diferencia
B8: 2010 | C8: Enero | D8: 4000 | E8: 2430 | F8: =D8-E8 -> 1570
B9: 2010 | C9: Febrero | D9: 4000 | E9: 3555 | F9: =D9-E9 -> 445
B10: 2010 | C10: Marzo | D10: 4445 | E10: 4020 | F10: =D10-E10 -> 425
B11: 2010 | C11: Abril | D11: 5110 | E11: 4123 | F11: =D11-E11 -> 987
B12: 2010 | C12: Mayo | D12: 4380 | E12: 1837 | F12: =D12-E12 -> 2543
B13: 2010 | C13: Junio | D13: 4445 | E13: 7830 | F13: =D13-E13 -> -3385
B14: 2010 | C14: Julio | D14: 3555 | E14: 5600 | F14: =D14-E14 -> -2045
B15: 2010 | C15: Agosto | D15: 1935 | E15: 2655 | F15: =D15-E15 -> -720
B16: 2010 | C16: Septiembre | D16: 2900 | E16: 2290 | F16: =D16-E16 -> 610
B17: 2010 | C17: Octubre | D17: 2250 | E17: 2055 | F17: =D17-E17 -> 195
B18: 2010 | C18: Noviembre | D18: 2150 | E18: 2165 | F18: =D18-E18 -> -15
B19: 2010 | C19: Diciembre | D19: 2150 | E19: 2190 | F19: =D19-E19 -> -40 | G19: =SUM(F8:F19) -> 570
B20: 2011 | C20: Enero | D20: 2800 | E20: 1910 | F20: =D20-E20 -> 890
B21: 2011 | C21: Febrero | D21: 0 | E21: 2325 | F21: =D21-E21 -> -2325
B22: 2011 | C22: Marzo | D22: 0 | E22: 2075 | F22: =D22-E22 -> -2075
B23: 2011 | C23: Abril | D23: 0 | E23: 1630 | F23: =D23-E23 -> -1630
B24: 2011 | C24: Mayo | D24: 1595 | E24: 1715 | F24: =D24-E24 -> -120
B25: 2011 | C25: Junio | D25: 2750 | E25: 3850 | F25: =D25-E25 -> -1100
B26: 2011 | C26: Julio | D26: 1790 | E26: 1845 | F26: =D26-E26 -> -55
B27: 2011 | C27: Agosto | D27: 1800 | E27: 1630 | F27: =D27-E27 -> 170
B28: 2011 | C28: Septiembre | D28: 1785 | E28: 2080 | F28: =D28-E28 -> -295
B29: 2011 | C29: Octubre | D29: 1800 | E29: 1860 | F29: =D29-E29 -> -60
B30: 2011 | C30: Noviembre | D30: 1800 | E30: 2010 | F30: =D30-E30 -> -210
B31: 2011 | C31: Diciembre | D31: 3640 | E31: 3640 | F31: =D31-E31 -> 0 | G31: =SUM(F20:F31) -> -6810
B32: 2012 | C32: Enero | D32: 1810 | E32: 1875 | F32: =D32-E32 -> -65
B33: 2012 | C33: Febrero | D33: 1730 | E33: 2690 | F33: =D33-E33 -> -960
B34: 2012 | C34: Marzo | D34: 1720 | E34: 6415 | F34: =D34-E34 -> -4695
B35: 2012 | C35: Abril | D35: 1695 | E35: 1550 | F35: =D35-E35 -> 145
B36: 2012 | C36: Mayo | D36: 4025 | E36: 3575 | F36: =D36-E36 -> 450
B37: 2012 | C37: Junio | D37: 3480 | E37: 1840 | F37: =D37-E37 -> 1640
B38: 2012 | C38: Julio | D38: 1720 | E38: 1920 | F38: =D38-E38 -> -200
B39: 2012 | C39: Agosto | D39: 1725 | E39: 2725 | F39: =D39-E39 -> -1000
B40: 2012 | C40: Septiembre | D40: 1700 | E40: 2070 | F40: =D40-E40 -> -370
B41: 2012 | C41: Octubre | D41: 1685 | E41: 1515 | F41: =D41-E41 -> 170
B42: 2012 | C42: Noviembre | D42: 1700 | E42: 1700 | F42: =D42-E42 -> 0
B43: 2012 | C43: Diciembre | D43: 3460 | E43: 2365 | F43: =D43-E43 -> 1095 | G43: =SUM(F32:F43) -> -3790
B44: 2013 | C44: Enero | D44: 1685 | E44: 1450 | F44: =D44-E44 -> 235
B45: 2013 | C45: Febrero | D45: 1720 | E45: 11000 | F45: =D45-E45 -> -9280
B46: 2013 | C46: Marzo | D46: 1700 | E46: 1840 | F46: =D46-E46 -> -140
B47: 2013 | C47: Abril | D47: 1700 | E47: 1595 | F47: =D47-E47 -> 105
B48: 2013 | C48: Mayo | D48: 1725 | E48: 1640 | F48: =D48-E48 -> 85
B49: 2013 | C49: Junio | D49: 3550 | E49: 1480 | F49: =D49-E49 -> 2070
B50: 2013 | C50: Julio | D50: 1745 | E50: 2035 | F50: =D50-E50 -> -290
B51: 2013 | C51: Agosto | D51: 1750 | E51: 1750 | F51: =D51-E51 -> 0
B52: 2013 | C52: Septiembre | D52: 1825 | E52: 1760 | F52: =D52-E52 -> 65
B53: 2013 | C53: Octubre | D53: 1725 | E53: 1700 | F53: =D53-E53 -> 25
B54: 2013 | C54: Noviembre | D54: 4100 | E54: 1770 | F54: =D54-E54 -> 2330
B55: 2013 | C55: Diciembre | D55: 2650 | E55: 2115 | F55: =D55-E55 -> 535 | G55: =SUM(F44:F55) -> -4260
B56: 2014 | C56: Enero | D56: 2725 | E56: 1450 | F56: =D56-E56 -> 1275
B57: 2014 | C57: Febrero | D57: 2175 | E57: 1445 | F57: =D57-E57 -> 730
B58: 2014 | C58: Marzo | D58: 2275 | E58: 3845 | F58: =D58-E58 -> -1570
B59: 2014 | C59: Abril | D59: 2275 | E59: 1515 | F59: =D59-E59 -> 760
B60: 2014 | C60: Mayo | D60: 2275 | E60: 1800 | F60: =D60-E60 -> 475
B61: 2014 | C61: Junio | D61: 2060 | E61: 2335 | F61: =D61-E61 -> -275
B62: 2014 | C62: Julio | D62: 2060 | E62: 3280 | F62: =D62-E62 -> -1220
B63: 2014 | C63: Agosto | D63: 2125 | E63: 2055 | F63: =D63-E63 -> 70
B64: 2014 | C64: Septiembre | D64: 2130 | E64: 2040 | F64: =D64-E64 -> 90
B65: 2014 | C65: Octubre | D65: 1995 | E65: 1610 | F65: =D65-E65 -> 385
B66: 2014 | C66: Noviembre | D66: 2080 | E66: 8715 | F66: =D66-E66 -> -6635
B67: 2014 | C67: Diciembre | D67: 3690 | E67: 3000 | F67: =D67-E67 -> 690 | G67: =SUM(F56:F67) -> -5225
B68: 2015 | C68: Enero | D68: 2265 | E68: 1385 | F68: =D68-E68 -> 880
B69: 2015 | C69: Febrero | D69: 2250 | E69: 2360 | F69: =D69-E69 -> -110
B70: 2015 | C70: Marzo | D70: 2245 | E70: 1570 | F70: =D70-E70 -> 675
B71: 2015 | C71: Abril | D71: 2245 | E71: 2070 | F71: =D71-E71 -> 175
B72: 2015 | C72: Mayo | D72: 2340 | E72: 1590 | F72: =D72-E72 -> 750
B73: 2015 | C73: Junio | D73: 2330 | E73: 2180 | F73: =D73-E73 -> 150
B74: 2015 | C74: Julio | D74: 2335 | E74: 1910 | F74: =D74-E74 -> 425
B75: 2015 | C75: Agosto | D75: 2615 | E75: 2565 | F75: =D75-E75 -> 50
B76: 2015 | C76: Septiembre | D76: 3350 | E76: 1985 | F76: =D76-E76 -> 1365
B77: 2015 | C77: Octubre | D77: 2585 | E77: 1740 | F77: =D77-E77 -> 845
B78: 2015 | C78: Noviembre | D78: 1960 | E78: 2305 | F78: =D78-E78 -> -345
B79: 2015 | C79: Diciembre | D79: 2515 | E79: 2515 | F79: =D79-E79 -> 0 | G79: =SUM(F68:F79) -> 4860
B80: 2016 | C80: Enero | D80: 1950 | E80: 1820 | F80: =D80-E80 -> 130
B81: 2016 | C81: Febrero | D81: 1865 | E81: 2095 | F81: =D81-E81 -> -230
B82: 2016 | C82: Marzo | D82: 1865 | E82: 1640 | F82: =D82-E82 -> 225
B83: 2016 | C83: Abril | D83: 2625 | E83: 4000 | F83: =D83-E83 -> -1375
B84: 2016 | C84: Mayo | D84: 1900 | E84: 1750 | F84: =D84-E84 -> 150
B85: 2016 | C85: Junio | D85: 2745 | E85: 12215 | F85: =D85-E85 -> -9470
B86: 2016 | C86: Julio | D86: 3885 | E86: 1720 | F86: =D86-E86 -> 2165
B87: 2016 | C87: Agosto | D87: 2300 | E87: 2300 | F87: =D87-E87 -> 0
B88: 2016 | C88: Septiembre | D88: 2115 | E88: 1630 | F88: =D88-E88 -> 485
B89: 2016 | C89: Octubre | D89: 4330 | E89: 2000 | F89: =D89-E89 -> 2330
B90: 2016 | C90: Noviembre | D90: 1935 | E90: 1865 | F90: =D90-E90 -> 70
B91: 2016 | C91: Diciembre | D91: 4080 | E91: 2980 | F91: =D91-E91 -> 1100 | G91: =SUM(F80:F91) -> -4420
B92: 2017 | C92: Enero | D92: 5875 | E92: 1745 | F92: =D92-E92 -> 4130
B93: 2017 | C93: Febrero | D93: 1905 | E93: 1835 | F93: =D93-E93 -> 70
B94: 2017 | C94: Marzo | D94: 1915 | E94: 1800 | F94: =D94-E94 -> 115
B95: 2017 | C95: Abril | D95: 3065 | E95: 2495 | F95: =D95-E95 -> 570
B96: 2017 | C96: Mayo | D96: 1940 | E96: 3665 | F96: =D96-E96 -> -1725
B97: 2017 | C97: Junio | D97: 2075 | E97: 2175 | F97: =D97-E97 -> -100
B98: 2017 | C98: Julio | D98: 4145 | E98: 2275 | F98: =D98-E98 -> 1870
B99: 2017 | C99: Agosto | D99: 1900 | E99: 2100 | F99: =D99-E99 -> -200
B100: 2017 | C100: Septiembre | D100: 2090 | E100: 1980 | F100: =D100-E100 -> 110
B101: 2017 | C101: Octubre | D101: 4115 | E101: 2105 | F101: =D101-E101 -> 2010
B102: 2017 | C102: Noviembre | D102: 1925 | E102: 2325 | F102: =D102-E102 -> -400
B103: 2017 | C103: Diciembre | D103: 4115 | E103: 3115 | F103: =D103-E103 -> 1000 | G103: =SUM(F92:F103) -> 7450
B104: 2018 | C104: Enero | D104: 1925 | E104: 1925 | F104: =D104-E104 -> 0
...

Sheet Análisis
B2: 2009
B3: TOTALES | C3: Por mes | D3: Estimado | F3: Gasto habitual mensual | G3: Buenas intenciones mensuales 2010 | H3: La cruda realidad | I3: Que pasaría si…
B4: 5460 | C4: 475 | D4: 450 | E4: Smart / Mini | F4: 205 | G4: 0 | H4: 0 | I4: 300 | J4: coche nuevo
B5: 320 | C5: 30 | D5: 40 | E5: Gimnasios | F5: 50 | G5: 35 | H5: 72.083333 | I5: 45
B6: 1200 | C6: 100 | D6: 100 | E6: Plan de Ahorro | F6: 0 | G6: 0 | H6: 0 | I6: 0
B7: 1200 | C7: 100 | D7: 50 | E7: Traspaso Caixa Catalunya | F7: 0 | G7: 0 | H7: 13.333333 | I7: 0
B8: 1770 | C8: 150 | D8: 100 | E8: Comida y bebida | F8: 200 | G8: 200 | H8: 108.75 | I8: 75
B9: 325 | C9: 30 | D9: 25 | E9: Primitiva y otras loterias | F9: 40 | G9: 30 | H9: 64.166667 | I9: 30
B10: 835 | C10: 75 | D10: 60 | E10: Teléfono | F10: 70 | G10: 70 | H10: 176.25 | I10: 50
B11: 2110 | C11: 175 | D11: 150 | E11: Otros | F11: 150 | G11: 120 | H11: 40 | I11: 75
B12: 850 | C12: =B12/10 -> 85 | D12: 75 | E12: Seguro Coche | F12: 0 | G12: 60 | H12: 66.666667 | I12: 60 | J12: seguros
B13: 120 | C13: 10 | D13: 5 | E13: Salud y cuidado personal | F13: 0 | G13: 25 | H13: 11.25 | I13: 10
B14: 0 | C14: 0 | D14: 0 | E14: Averías (fontanería, etc.) | F14: 0 | G14: 0 | H14: 0 | I14: 0
B15: 12 | C15: 5 | D15: 5 | E15: Material oficina (cuadernos, salidas, etc.) | F15: 0 | G15: 10 | H15: 0.83333333 | I15: 0
B16: 830 | C16: 75 | D16: 100 | E16: Gastos trabajo | F16: 50 | G16: 50 | H16: 29.166667 | I16: 0
B17: 1750 | C17: 150 | D17: 50 | E17: Regalos (cumpleaños, reyes, Mangeles) | F17: 25 | G17: 25 | H17: 62.083333 | I17: 25
B18: 1700 | C18: 150 | D18: 100 | E18: Ocio (salidas, cenas, cine,...) | F18: 125 | G18: 120 | H18: 77.5 | I18: 50
B19: 10 | C19: 2 | D19: 2 | E19: Encuadernaciones apuntes MCSE o UOC | F19: 0 | G19: 0 | H19: 0.41666667 | I19: 0
B20: 185 | C20: 15 | D20: 25 | E20: Ropa y calzado | F20: 0 | G20: 25 | H20: 0.83333333 | I20: 25
B21: 1200 | C21: 100 | D21: 100 | E21: Vacaciones | F21: 0 | G21: 50 | H21: 5.4166667 | I21: 50
B22: 0 | C22: 0 | D22: 50 | E22: Reparaciones del automóvil | F22: 0 | G22: 0 | H22: 36.666667 | I22: 0
B23: 310 | C23: 25 | D23: 15 | E23: Libros | F23: 15 | G23: 10 | H23: 30.416667 | I23: 10
B24: 570 | C24: 45 | D24: 50 | E24: Automóvil (combustible + párking) | F24: 0 | G24: 25 | H24: 110.41667 | I24: 120
... B32: 1900 | C32: 150 | D32: 50 | E32: Hacienda | F32: 0 | G32: 50 | H32: 374.58333 | I32: 0
E33: Total mensual | F33: =SUM(F4:F32) -> 1035 | G33: =SUM(G4:G32) -> 1070 | I33: =SUM(I4:I32) -> 970
E34: Resto mensual | F34: =D39-F33 -> 1015 | G34: =D39-G33 -> 980 | I34: =D39-I33 -> 1080
C35: Gastos totales reales | D35: =SUM(B4:B33) -> 27757 | E35: Redondeo | G35: Lo real | H35: =SUM(H4:H32) -> 1359.5833
C36: Total mes estimado al alza | D36: =SUM(C4:C33) -> 2382 | E36: 2050 | G36: Resto real | H36: =D39-H35 -> 690.41667 | L36: =37000/12 -> 3083.3333
C37: Total mes estimado a la baja | D37: =SUM(D4:D32) -> 1862 | E37: 1750
C39: Ingreso medio mensual: | D39: 2050
B42: Hipotesis: Ingresos 30K netos anuales
B44: Ingresos netos | D44: 2500 | F44: Ingresos netos | H44: 2000 | J44: Ingresos netos | L44: 3000
L45: (promedios mensuales)
B46: Seguros | D46: 75 | F46: Seguros | H46: 75 | J46: Seguros | L46: 75
B47: Gimnasio | D47: 50 | F47: Gimnasio | H47: 50 | J47: Gimnasio | L47: 25
B48: Excursiones | D48: 25 | F48: Excursiones | H48: 25 | J48: Excursiones y vacaciones | L48: 250
B49: Teléfono | D49: 50 | F49: Teléfono | H49: 50 | J49: Teléfono | L49: 35
B50: Loterias | D50: 75 | F50: Loterias | H50: 75 | J50: Loterias | L50: 75
B51: Comida | D51: 100 | F51: Comida | H51: 100 | J51: Comida | L51: 300
B52: Transporte | D52: 120 | F52: Transporte | H52: 120 | J52: Transporte y coche | L52: 500 | M52: (cuota coche 450)
B53: Agua y luz: | D53: 125 | F53: Agua y luz: | H53: 125 | J53: Agua, Luz y Gas | L53: 125
B54: Ocio | D54: 75 | F54: Ocio | H54: 75 | J54: Ocio | L54: 150
B55: Imprevistos | D55: 200 | F55: Imprevistos | H55: 200 | J55: Imprevistos | L55: 150
B56: Niño | D56: 100 | F56: Niño | H56: 100 | J56: Niños | L56: 100
J57: Regalos | L57: 50
J58: Inversiones | L58: 250
B61: GASTOS: | D61: =SUM(D46:D57) -> 995 | F61: GASTOS: | H61: =SUM(H46:H57) -> 995 | J61: GASTOS: | L61: =SUM(L46:L59) -> 2085
B63: Alquiler: | D63: 725 | F63: Alquiler: | H63: 725 | J63: Alquiler: | L63: 875
B65: Total Gasto mensual | D65: =D63+D61 -> 1720 | F65: Total Gasto mensual | H65: =H63+H61 -> 1720 | J65: Total Gasto mensual | L65: =L63+L61 -> 2960
B66: Resto Mensual | D66: =D44-D65 -> 780 | F66: Resto Mensual | H66: =H44-H65 -> 280 | J66: Resto Mensual | L66: =L44-L65 -> 40
B70: Historico Ingresos y gastos
D72: Desde Feb08 | E72: Desde Jun08 | F72: Desde Ago09 | G72: Desde Ago10 | H72: Desde May11 | I72: Desde Dic11 | J72: Desde Mar12 | K72: Desde Ene14 | L72: Desde Jun14 | M72: Desde Dic14
C73: Ingresos: | D73: 2000 | E73: 2100 | F73: 3500 | G73: 2100 | H73: 1700 | I73: 1750 | J73: 1675 | K73: 2275 | L73: 2050 | M73: 2000
C75: Prestamo coche/seguro: | D75: 200 | E75: 205 | F75: 50 | G75: 60 | H75: 60 | I75: 60 | J75: 60 | K75: 55 | L75: 55 | M75: 55
C76: Gimnasio: | D76: 50 | E76: 50 | F76: 40 | G76: 40 | H76: 40 | I76: 75 | J76: 40 | K76: 50 | L76: 100 | M76: 30
C77: Excursiones: | D77: 100 | E77: 50 | F77: 50 | G77: 50 | H77: 50 | I77: 25 | J77: 25 | K77: 25 | L77: 25 | M77: 0
C78: Teléfono: | D78: 100 | E78: 75 | F78: 75 | G78: 150 | H78: 100 | I78: 100 | J78: 60 | K78: 50 | L78: 50 | M78: 25
C79: Compras a plazos: | D79: 100 | E79: 50 | F79: 0 | G79: 50 | H79: 30 | I79: 0 | J79: 0 | K79: 0 | L79: 0 | M79: 0
C80: Loterias: | D80: 50 | E80: 50 | F80: 40 | G80: 40 | H80: 40 | I80: 40 | J80: 40 | K80: 40 | L80: 50 | M80: 40
C81: Mantenimiento: | D81: 200 | E81: 200 | F81: 200 | G81: 250 | H81: 250 | I81: 250 | J81: 125 | K81: 125 | L81: 125 | M81: 125
C82: Agua y luz: | D82: 50 | E82: 50 | F82: 50 | G82: 75 | H82: 75 | I82: 75 | J82: 100 | K82: 150 | L82: 175 | M82: 175
C83: Extras: | D83: 200 | E83: 250 | F83: 250 | G83: 150 | H83: 200 | I83: 250 | J83: 200 | K83: 125 | L83: 125 | M83: 150
C84: Autonomos: | D84: 0 | E84: 0 | F84: 300 | G84: 0 | H84: 0 | I84: 0 | J84: 0 | K84: 0 | L84: 0 | M84: 0
C86: GASTOS: | D86: =SUM(D75:D85) -> 1050 | E86: =SUM(E75:E85) -> 980 | F86: =SUM(F75:F85) -> 1055 | G86: =SUM(G75:G85) -> 865 | H86: =SUM(H75:H85) -> 845 | I86: =SUM(I75:I85) -> 875 | J86: =SUM(J75:J85) -> 650 | K86: =SUM(K75:K85) -> 620 | ... M86: =SUM(M75:M85) -> 600
C88: Alquiler: | D88: 610 | E88: 610 | F88: 610 | G88: 700 | H88: 725 | I88: 725 | J88: 725 | K88: 725 | L88: 725 | M88: 740
C90: Total Gasto mensual | D90: =SUM(D86:D89) -> 1660 | E90: =SUM(E86:E89) -> 1590 | F90: =SUM(F86:F89) -> 1665 | G90: =SUM(G86:G89) -> 1565 | H90: =SUM(H86:H89) -> 1570 | I90: =SUM(I86:I89) -> 1600 | J90: =SUM(J86:J89) -> 1375 | K90: =SUM(K86:K89) -> 1345 | ... M90: =SUM(M86:M89) -> 1340
C91: Resto Mensual | D91: =D73-D90 -> 340 | E91: =E73-E90 -> 510 | F91: =F73-F90 -> 1835 | G91: =G73-G90 -> 535 | H91: =H73-H90 -> 130 | I91: =I73-I90 -> 150 | J91: =J73-J90 -> 300 | K91: =K73-K90 -> 930 | ... M91: =M73-M90 -> 660
B95: Hipótesis : Mudanza | F95: Hipótesis : Compra
C96: Coste mensual : | D96: 750 | G96: Coste mensual : | H96: 800 | I96: (inluye gastos Comunidad propietarios)
C97: Fianza dos meses : | D97: =D96*2 -> 1500 | G97: Constitución Hipoteca : | H97: 15000 | I97: (incluye seguro vida y hogar)
C98: Mes en curso (x2) : | D98: =D96*2 -> 1500 | E98: Piso nuevo + Piso actual | G98: Mes en curso (x2) : | H98: 1500
C99: Tramites : | D99: 750 | G99: Tramites :
C100: Seguro : | D100: 125 | G100: Seguro :
C101: Electrodomésticos : | D101: 1000 | E101: Lavadora, Nevera | G101: Electrodomésticos : | H101: 1000
C102: Dormitorio : | D102: 1000 | G102: Dormitorio : | H102: 1000
C103: Transporte : | D103: 750 | G103: Mudanza: | H103: 750
C104: Imprevistos : | D104: 625 | G104: Imprevistos : | H104: 950
C106: TOTAL | D106: =SUM(D96:D105) -> 8000 | G106: TOTAL | H106: =SUM(H96:H105) -> 21000
B110: Hipótesis : Hipoteca
B111: Importe | C111: Años | D111: Interes | E111: Cuota | F111: Se acaba pagando | H111: Seg+Comun | I111: TOTAL
B112: 125000 | C112: 10 | D112: 2 | E112: 1150 | F112: 138000 | G112: 0.1 | H112: 130 | I112: =H112+E112 -> 1280
B113: 125000 | C113: 10 | D113: 2.5 | E113: 1180 | F113: 142000 | G113: 0.12 | H113: 130 | I113: =H113+E113 -> 1310
B114: 125000 | C114: 10 | D114: 3 | E114: 1210 | F114: 145000 | G114: 0.14 | H114: 130 | I114: =H114+E114 -> 1340
B115: 125000 | C115: 15 | D115: 2 | E115: 805 | F115: 145000 | G115: 0.14 | H115: 130 | I115: =H115+E115 -> 935
B116: 125000 | C116: 15 | D116: 2.5 | E116: 835 | F116: 150000 | G116: 0.17 | H116: 130 | I116: =H116+E116 -> 965
B117: 125000 | C117: 15 | D117: 3 | E117: 865 | F117: 155000 | G117: 0.2 | H117: 130 | I117: =H117+E117 -> 995
B118: 125000 | C118: 20 | D118: 2 | E118: 632 | F118: 152000 | G118: 0.18 | H118: 130 | I118: =H118+E118 -> 762
B119: 125000 | C119: 20 | D119: 2.5 | E119: 665 | F119: 160000 | G119: 0.22 | H119: 130 | I119: =H119+E119 -> 795
B120: 125000 | C120: 20 | D120: 3 | E120: 695 | F120: 167000 | G120: 0.25 | H120: 130 | I120: =H120+E120 -> 825
B121: 125000 | C121: 25 | D121: 2 | E121: 530 | F121: 160000 | G121: 0.22 | H121: 130 | I121: =H121+E121 -> 660
B122: 125000 | C122: 25 | D122: 2.5 | E122: 560 | F122: 168000 | G122: 0.26 | H122: 130 | I122: =H122+E122 -> 690
B123: 125000 | C123: 25 | D123: 3 | E123: 595 | F123: 178000 | G123: 0.3 | H123: 130 | I123: =H123+E123 -> 725
B124: 125000 | C124: 25 | D124: 3.5 | E124: 625 | F124: 188000 | G124: 0.34 | H124: 130 | I124: =H124+E124 -> 755
H125: 130 | I125: =H125+E125 -> 130
B126: 115000 | C126: 15 | D126: 3.75 | E126: 835 | F126: 151000 | G126: =(F126-B126)/B126 -> 0.31304348 | H126: 130 | I126: =H126+E126 -> 965
B127: 115000 | C127: 20 | D127: 3.75 | E127: 680 | F127: 165000 | G127: =(F127-B127)/B127 -> 0.43478261 | H127: 130 | I127: =H127+E127 -> 810
B129: 105000 | C129: 20 | D129: 3.75 | E129: 625 | F129: =E129*(C129*12) -> 150000 | G129: =(F129-B129)/B129 -> 0.42857143 | H129: 130 | I129: =H129+E129 -> 755
B130: 110000 | C130: 20 | D130: 3.75 | E130: 650 | F130: =E130*(C130*12) -> 156000 | G130: =(F130-B130)/B130 -> 0.41818182 | H130: 130 | I130: =H130+E130 -> 780
B131: 90000 | C131: 20 | D131: 3.75 | E131: 530 | F131: 130000 | G131: =(F131-B131)/B131 -> 0.44444444 | H131: 130 | I131: =H131+E131 -> 660
B136: Gastos para compra segunda mano
...

Sheet Nomina
B3: De Enero a Diciembre de 2008
B4: Dias | C4: Precio | D4: Concepto | F4: Devengos | G4: Deducciones
B5: 30 | C5: 50.43 | D5: Salario Base | F5: =B5*C5 -> 1512.9
B6: 30 | C6: 17.65 | D6: Plus Convenio | F6: =B6*C6 -> 529.5
B7: 30 | C7: 26.15 | D7: Mejoras Voluntarias (14) | F7: =B7*C7 -> 784.5
B8: 1 | D8: Km | F8: =B8*C8 -> 0 | H8: =SUM(F5:F8) -> 2826.9
D9: P.P.Extras | F9: 235.58 | H9: =SUM(F5:F9) -> 3062.48 | I9: Base IRPF
D11: Cotizacion Cont.Com. | E11: 4.7 | G11: =(E11*H9)/100 -> 143.93656
D12: Cotizacion Formacion | G12: =(E12*H9)/100 -> 0
D13: Cotizacion Desempleo | E13: 1.65 | G13: =(E13*H9)/100 -> 50.53092
D14: IRPF | E14: 17.98 | G14: =(E14*H8)/100 -> 508.27662
H15: =SUM(G11:G14) -> 702.7441 | I15: Total Deducciones
I17: Total a Percibir | J17: =H8-H15 -> 2124.1559
B19: De Junio a Diciembre 2010
B20: Dias | C20: Precio | D20: Concepto | F20: Devengos | G20: Deducciones
B21: 30 | C21: 52.308 | D21: Salario Base | F21: =B21*C21 -> 1569.24
B22: 30 | C22: 3.658 | D22: Plus Convenio | F22: =B22*C22 -> 109.74
B23: 30 | C23: 23.595 | D23: Mejoras Voluntarias (14) | F23: =B23*C23 -> 707.85
B24: 1 | F24: =B24*C24 -> 0 | H24: =SUM(F21:F24) -> 2386.83 | L24: =J33-J17 -> 26.50539
D25: P.P.Extras | F25: 279.83 | H25: =SUM(F21:F25) -> 2666.66 | I25: Base IRPF
D27: Cotizacion Cont.Com. | E27: 4.7 | G27: =(E27*H25)/100 -> 125.33302
D28: Dto Base Accidente | G28: =(E28*H25)/100 -> 0
D29: Cotizacion Desempleo | E29: 1.65 | G29: =(E29*H25)/100 -> 43.99989
D30: IRPF | E30: 13 | G30: =(E30*H25)/100 -> 346.6658
H31: =SUM(G27:G30) -> 515.99871 | I31: Total Deducciones
I33: Total a Percibir | J33: =H25-H31 -> 2150.6613
B35: De Abril a Diciembre 2011
B36: Dias | C36: Precio | D36: Concepto | F36: Devengos | G36: Deducciones
B37: 30 | C37: 52.308 | D37: Salario Base | F37: =B37*C37 -> 1569.24
B38: 30 | C38: 3.658 | D38: Plus Convenio | F38: =B38*C38 -> 109.74
B39: 30 | C39: 15.463 | D39: Mejoras Voluntarias (14) | F39: =B39*C39 -> 463.89
B40: 1 | C40: 32.62 | D40: Km | F40: =B40*C40 -> 32.62 | H40: =SUM(F37:F40) -> 2175.49 | I40: Base IRPF | L40: =J49-J33 -> -440.5619
D41: P.P.Extras | F41: 357.14 | H41: =SUM(F37:F41) -> 2532.63 | I41: Base A.T. y Des.
D43: Cotizacion Cont.Com. | E43: 4.7 | G43: =(E43*H41)/100 -> 119.03361
D44: Cotizacion Formacion | E44: 0.1 | G44: =(E44*H41)/100 -> 2.53263
D45: Cotizacion Desempleo | E45: 1.55 | G45: =(E45*H41)/100 -> 39.255765
D46: IRPF | E46: 14 | G46: =(E46*H40)/100 -> 304.5686
H47: =SUM(G43:G46) -> 465.3906 | I47: Total Deducciones
I49: Total a Percibir | J49: =H40-H47 -> 1710.0994
B51: Desde Febrero 2012
B52: Dias | C52: Precio | D52: Concepto | F52: Devengos | G52: Deducciones
B53: 30 | C53: 52.308 | D53: Salario Base | F53: =B53*C53 -> 1569.24
B54: 30 | C54: 3.658 | D54: Plus Convenio | F54: =B54*C54 -> 109.74
B55: 30 | C55: 15.463 | D55: Mejoras Voluntarias (14) | F55: =B55*C55 -> 463.89
B56: 1 | C56: 22.83 | D56: Km | F56: =B56*C56 -> 22.83 | H56: =SUM(F53:F56) -> 2165.7 | I56: Base IRPF | L56: =J65-J49 -> -96.158295
D57: P.P.Extras | F57: 357.14 | H57: =SUM(F53:F57) -> 2522.84 | I57: Base A.T. y Des.
D59: Cotizacion Cont.Com. | E59: 4.7 | G59: =(E59*H57)/100 -> 118.57348
D60: Cotizacion Formacion | E60: 0.1 | G60: =(E60*H57)/100 -> 2.52284
D61: Cotizacion Desempleo | E61: 1.55 | G61: =(E61*H57)/100 -> 39.10402
D62: IRPF | E62: 18.08 | G62: =(E62*H56)/100 -> 391.55856
H63: =SUM(G59:G62) -> 551.7589 | I63: Total Deducciones
I65: Total a Percibir | J65: =H56-H63 -> 1613.9411
B67: Desde Junio 2013
B68: Dias | C68: Precio | D68: Concepto | F68: Devengos | G68: Deducciones
B69: 30 | C69: 52.308 | D69: Salario Base | F69: =B69*C69 -> 1569.24
B70: 30 | C70: 3.658 | D70: Plus Convenio | F70: =B70*C70 -> 109.74
B71: 30 | C71: 15.742 | D71: Mejoras Voluntarias (14) | F71: =B71*C71 -> 472.26
B72: 30 | C72: 3.292 | D72: Incr.a cuenta(???) | F72: =B72*C72 -> 98.76
B73: 1 | C73: 37.51 | D73: Km | F73: =B73*C73 -> 37.51 | H73: =SUM(F69:F73) -> 2287.51 | I73: Base IRPF | L73: =J82-J65 -> 61.180077
D74: P.P.Extras | F74: 375 | H74: =SUM(F69:F74) -> 2662.51 | I74: Base A.T. y Des.
D76: Cotizacion Cont.Com. | E76: 4.7 | G76: =(E76*H74)/100 -> 125.13797
D77: Cotizacion Formacion | E77: 0.1 | G77: =(E77*H74)/100 -> 2.66251
D78: Cotizacion Desempleo | E78: 1.55 | G78: =(E78*H74)/100 -> 41.268905
D79: IRPF | E79: 19.38 | G79: =(E79*H73)/100 -> 443.31944
C80: =786.16/32 -> 24.5675 | H80: =SUM(G76:G79) -> 612.38882 | I80: Total Deducciones
I82: Total a Percibir | J82: =H73-H80 -> 1675.1212
B84: Desde Enero 2014
B85: Dias | C85: Precio | D85: Concepto | F85: Devengos | G85: Deducciones
B86: 30 | C86: 51.323 | D86: Salario Base | F86: =B86*C86 -> 1539.69
B87: 30 | C87: 13.492 | D87: Parte Proporcional Pagas | F87: =B87*C87 -> 404.76
B88: 30 | C88: 3.424 | D88: Plus Convenio | F88: =B88*C88 -> 102.72
B89: 32 | C89: 24.5675 | D89: Mejora Voluntaria | F89: =B89*C89 -> 786.16
D90: Tickets Restaurante | F90: -72
D91: Transporte | F91: -25
B92: 1 | D92: Suplidos (NF) | F92: 182.4 | H92: =SUM(F86:F91) -> 2736.33 | I92: Base IRPF
H93: =SUM(F86:F89) -> 2833.33 | I93: Base A.T. y Des. | L93: =J101-J82 -> 603.14524
D95: Cotizacion Cont.Com. | E95: 4.7 | G95: =(E95*H93)/100 -> 133.16651
D96: Cotizacion Formacion | E96: 0.1 | G96: 2.87
D97: Cotizacion Desempleo | E97: 1.55 | G97: 44.45
D98: IRPF | E98: 16.81 | G98: =(E98*H92)/100 -> 459.97707
H99: =SUM(G95:G98) -> 640.46358 | I99: Total Deducciones
I101: Total a Percibir | J101: =H92-H99+F92 -> 2278.2664

Sheet GrandesCompras
B3: Grandes Compras desde 1997
B6: AÑO | C6: CONCEPTO | D6: VALOR
B7: 1997 | C7: Lentillas | D7: 60
B8: 1997 | C8: Traje Americana | D8: 215
B9: 1997 | C9: PC INVES 200 MMX | D9: 1805 | E9: TECNOLOGIA
B10: 1997 | C10: Lector-Grabador CDs | D10: 545 | E10: TECNOLOGIA
B11: 1998 | C11: Disquetera LS120 + Cintas especiales de gran capacidad | D11: 270 | E11: TECNOLOGIA
B12: 1999 | C12: Bicicleta Corte Inglés (??) | D12: 515 | E12: DEPORTE
B13: 1999 | C13: Muebles comedor Badalona | D13: 3000 | E13: MUEBLES Y MUDANZAS
B14: 1999 | C14: Monitor IBM | D14: 250 | E14: TECNOLOGIA
B15: 1999 | C15: Impresora HP Office | D15: 150 | E15: TECNOLOGIA
B16: 2000 | C16: PC Packard Bell | D16: 2400 | E16: TECNOLOGIA
B17: 2003 | C17: PC HP Pavilion AMD Athlon 2,5GHz 60Gb HD | D17: 1000 | E17: TECNOLOGIA
B18: 2003 | C18: Cámara digital Sanyo | D18: 600 | E18: TECNOLOGIA
B19: 2003 | C19: Mini Cooper S | D19: 25000 | E19: COCHES
B20: 2004 | C20: Apeman. Historia de la Evolución Humana + II Guerra mundial | D20: 100 | E20: COLECCIONES
... B59: 2024 | C59: Tratamiento en Madrid, nH Barajas (Jul-Ago) | D59: 5190 | E59: SALUD
C65: TOTAL | D65: =SUM(D7:D63) -> 118835

Sheet LaCasaFutura
C3: Amortización de un Préstamo Hipotecario
H5: Estimación imposible
G6: Precio de Compra | H6: 200000
G7: Entrada | H7: 30000
G8: Préstamo solicitado | H8: =H6-H7 -> 170000
G9: Interés anual | H9: 0.03
G10: Duración del préstamo (años) | H10: 30
G11: Número de pagos anuales | H11: 12
G12: Cantidad a pagar por periodo | H12: =ABS(PMT($H$9/12,$H$11*12,$H$8)) -> 1407.2374
G13: Total a pagar (intereses + capital) | H13: =(H12*(H10*H11)) -> 506605.45
G14: Total de intereses a pagar | H14: =H13-H8 -> 336605.45
H16: Estimación realista
G17: Precio de Compra | H17: 200000
G18: Entrada | H18: 40000
G19: Préstamo solicitado | H19: =H17-H18 -> 160000 | I19: (80%) | J19: =(200000*80)/100 -> 160000
G20: Interés anual | H20: 0.03
G21: Duración del préstamo (años) | H21: 30
G22: Número de pagos anuales | H22: 12
G23: Cantidad a pagar por periodo | H23: =ABS(PMT($H$20/12,$H$22*12,$H$19)) -> 1324.4587
G24: Total a pagar (intereses + capital) | H24: =(H23*(H21*H22)) -> 476805.13
G25: Total de intereses a pagar | H25: =H24-H19 -> 316805.13

Sheet Borrador
B4: 2019
B5: Categoría | C5: Ene | D5: Feb | E5: Mar | F5: Abr | G5: Mayo | H5: Jun | I5: Jul | J5: Ago | K5: Sep | L5: Oct | M5: Nov | N5: Dic | O5: Global
C6: 2019 | D6: 2019 | E6: 2019 | F6: 2019 | G6: 2019 | H6: 2019 | I6: 2019 | J6: 2019 | K6: 2019 | L6: 2019 | M6: 2019 | N6: 2019
B7: Ahorro | C7: -30 | D7: -30 | E7: -30 | F7: -30 | G7: -30 | H7: -30 | I7: -30 | J7: -30 | K7: -30 | L7: -30 | M7: -30 | N7: -30 | O7: -360
B8: Automovil : Mantenimiento | C8: -50 | D8: 0 | E8: 0 | F8: 0 | G8: 0 | H8: 0 | I8: -100 | J8: 0 | K8: 0 | L8: 0 | M8: -5 | N8: 0 | O8: -155
B9: Automovil : Combustible | C9: -90 | D9: -50 | E9: -90 | F9: -50 | G9: -80 | H9: -50 | I9: -60 | J9: -50 | K9: -80 | L9: -90 | M9: -50 | N9: -80 | O9: -820
B10: Automovil : Parking-Peajes | C10: 0 | D10: 0 | E10: -85 | F10: 0 | G10: 0 | H10: -5 | I10: 0 | J10: -10 | K10: -70 | L10: -20 | M10: -5 | N10: -60 | O10: -255
B11: Automovil : Impuestos | C11: 0 | D11: 0 | E11: 0 | F11: 0 | G11: -70 | H11: 0 | I11: 0 | J11: 0 | K11: 0 | L11: 0 | M11: 0 | N11: 0 | O11: -70
B12: Automovil : Compra/Renting | C12: -2000 | D12: 0 | E12: -150 | F12: -200 | G12: -100 | H12: 0 | I12: -300 | J12: 0 | K12: -50 | L12: -300 | M12: -50 | N12: -300 | O12: -3450
B13: Comida : Dietas | C13: -150 | D13: -160 | E13: -230 | F13: -120 | G13: -230 | H13: -275 | I13: -300 | J13: -135 | K13: -75 | L13: -210 | M13: -140 | N13: -115 | O13: -2140
B14: Deporte : Ropa | C14: 0 | D14: 0 | E14: 0 | F14: -50 | G14: 0 | H14: 0 | I14: 0 | J14: 0 | K14: 0 | L14: 0 | M14: 0 | N14: 0 | O14: -50
B15: Deporte : Gimnasio | C15: -25 | D15: -25 | E15: -25 | F15: -25 | G15: -25 | H15: -25 | I15: -25 | J15: -25 | K15: -25 | L15: -45 | M15: -25 | N15: -25 | O15: -320
B16: Formacion-Cultura : Libros | C16: 0 | D16: 0 | E16: -15 | F16: 0 | G16: -5 | H16: -20 | I16: -10 | J16: 0 | K16: 0 | L16: -10 | M16: 0 | N16: 0 | O16: -60
B17: Formacion-Cultura : Papeleria | C17: -20 | D17: 0 | E17: 0 | F17: -15 | G17: 0 | H17: 0 | I17: 0 | J17: -25 | K17: -20 | L17: 0 | M17: 0 | N17: -25 | O17: -105
B18: Formacion-Cultura : Matricula | C18: 0 | D18: 0 | E18: 0 | F18: -50 | G18: 0 | H18: 0 | I18: 0 | J18: 0 | K18: 0 | L18: 0 | M18: 0 | N18: 0 | O18: -50
... B49: Total | C49: -1955 | D49: 255 | E49: 50 | F49: 830 | G49: 134 | H49: 150 | I49: 1375 | J49: -980 | K49: 0 | L49: 1565 | M49: 100 | N49: 950 | O49: 2474
B52: 2020
B53: Categoría | C53: Ene | D53: Feb | E53: Mar | F53: Abr | G53: Mayo | H53: Jun | I53: Jul | J53: Ago | K53: Sep | L53: Oct | M53: Nov | N53: Dic | O53: Global
C54: 2020 | D54: 2020 | E54: 2020 | F54: 2020 | G54: 2020 | H54: 2020 | I54: 2020 | J54: 2020 | K54: 2020 | L54: 2020 | M54: 2020 | N54: 2020
B55: Ahorro | C55: -30 | D55: -30 | E55: -30 | F55: -30 | G55: -30 | H55: -30 | I55: -30 | J55: -30 | K55: -30 | L55: -30 | M55: -30 | N55: -780 | O55: -1110
B56: Automovil : Combustible | C56: -60 | D56: -80 | E56: 0 | F56: 0 | G56: 0 | H56: -30 | I56: 0 | J56: -50 | K56: -25 | L56: 0 | M56: 0 | N56: 0 | O56: -245
B57: Automovil : Parking-Peajes | C57: 0 | D57: -60 | E57: 0 | F57: 0 | G57: 0 | H57: 0 | I57: 0 | J57: 0 | K57: 0 | L57: 0 | M57: 0 | N57: -15 | O57: -75
B58: Automovil : Impuestos | C58: 0 | D58: 0 | E58: 0 | F58: 0 | G58: 0 | H58: -70 | I58: 0 | J58: 0 | K58: 0 | L58: 0 | M58: 0 | N58: 0 | O58: -70
B59: Automovil : Compra/Renting | C59: 0 | D59: -175 | E59: -100 | F59: -300 | G59: -100 | H59: -200 | I59: -300 | J59: -150 | K59: -100 | L59: -300 | M59: -150 | N59: -300 | O59: -2175
B60: Comida : Dietas | C60: -160 | D60: -175 | E60: -165 | F60: -230 | G60: -265 | H60: -285 | I60: -285 | J60: -205 | K60: -200 | L60: -280 | M60: -250 | N60: -425 | O60: -2925
B61: Deporte : Ropa | C61: 0 | D61: 0 | E61: 0 | F61: 0 | G61: 0 | H61: 0 | I61: -35 | J61: 0 | K61: 0 | L61: 0 | M61: 0 | N61: 0 | O61: -35
B62: Deporte : Gimnasio | C62: -25 | D62: -25 | E62: -25 | F62: -25 | G62: -25 | H62: -25 | I62: -25 | J62: -25 | K62: -25 | L62: -25 | M62: -25 | N62: -25 | O62: -300
B63: Formacion-Cultura : Libros | C63: 0 | D63: -30 | E63: -10 | F63: 0 | G63: 0 | H63: 0 | I63: 0 | J63: 0 | K63: 0 | L63: 0 | M63: 0 | N63: 0 | O63: -40
B64: Formacion-Cultura : Papeleria | C64: 0 | D64: 0 | E64: 0 | F64: 0 | G64: 0 | H64: 0 | I64: 0 | J64: -15 | K64: 0 | L64: 0 | M64: 0 | N64: -45 | O64: -60
B65: GastoFijoMensual : Telefono | C65: -30 | D65: -30 | E65: -35 | F65: -35 | G65: -35 | H65: -35 | I65: -35 | J65: -35 | K65: -35 | L65: -35 | M65: -35 | N65: -35 | O65: -410
B66: GastoFijoMensual : Electricidad | C66: -115 | D66: 0 | E66: -110 | F66: 0 | G66: -130 | H66: 0 | I66: -125 | J66: 0 | K66: -130 | L66: 0 | M66: -125 | N66: 0 | O66: -735
... B94: Total | C94: 5 | D94: 50 | E94: 210 | F94: 1530 | G94: 480 | H94: 135 | I94: -260 | J94: -295 | K94: 180 | L94: 1735 | M94: 205 | N94: 575 | O94: 4550
B97: 2021
B98: Categoría ▾ | C98: Ene | D98: Feb | E98: Mar | F98: Abr | G98: Mayo | H98: Jun | I98: Jul | J98: Ago | K98: Sep | L98: Oct | M98: Nov | N98: Dic | O98: Global
C99: 2021 | D99: 2021 | E99: 2021 | F99: 2021 | G99: 2021 | H99: 2021 | I99: 2021 | J99: 2021 | K99: 2021 | L99: 2021 | M99: 2021 | N99: 2021
B100: Ahorro | C100: -30 | D100: -30 | E100: -30 | F100: -30 | G100: 0 | H100: 0 | I100: 0 | J100: 0 | K100: 0 | L100: 0 | M100: 0 | N100: 0 | O100: -120
B101: Automovil : Combustible | C101: 0 | D101: 0 | E101: 0 | F101: -30 | G101: 0 | H101: 0 | I101: 0 | J101: 0 | K101: 0 | L101: 0 | M101: -30 | N101: 0 | O101: -60
B102: Automovil : Compra/Renting | C102: -400 | D102: -200 | E102: -200 | F102: -300 | G102: 0 | H102: -200 | I102: -300 | J102: 0 | K102: -150 | L102: -300 | M102: -150 | N102: -150 | O102: -2350
B103: Automovil : Impuestos | C103: 0 | D103: 0 | E103: 0 | F103: 0 | G103: -70 | H103: 0 | I103: 0 | J103: 0 | K103: 0 | L103: 0 | M103: 0 | N103: -80 | O103: -150
B104: Automovil : Mantenimiento | C104: 0 | D104: 0 | E104: 0 | F104: 0 | G104: 0 | H104: 0 | I104: 0 | J104: 0 | K104: -165 | L104: 0 | M104: 0 | N104: 0 | O104: -165
B105: Comida : Dietas | C105: -290 | D105: -360 | E105: -235 | F105: -390 | G105: -310 | H105: -270 | I105: -455 | J105: -110 | K105: -240 | L105: -260 | M105: -295 | N105: -440 | O105: -3655
B106: Deporte : Gimnasio | C106: 0 | D106: 0 | E106: 0 | F106: 0 | G106: 0 | H106: 0 | I106: 0 | J106: 0 | K106: 0 | L106: -115 | M106: 0 | N106: 0 | O106: -115
B107: Deporte : Ropa | C107: 0 | D107: 0 | E107: 0 | F107: -65 | G107: 0 | H107: 0 | I107: 0 | J107: 0 | K107: 0 | L107: -25 | M107: 0 | N107: 0 | O107: -90
B108: Formacion-Cultura : Libros | C108: 0 | D108: 0 | E108: 0 | F108: 0 | G108: 0 | H108: 0 | I108: 0 | J108: 0 | K108: 0 | L108: 0 | M108: 0 | N108: -20 | O108: -20
B109: Formacion-Cultura : Matricula | C109: 0 | D109: 0 | E109: 0 | F109: -110 | G109: 0 | H109: 0 | I109: 0 | J109: 0 | K109: 0 | L109: 0 | M109: 0 | N109: 0 | O109: -110
B110: GastoFijoMensual : Agua | C110: 0 | D110: -60 | E110: 0 | F110: -70 | G110: 0 | H110: -65 | I110: 0 | J110: -60 | K110: 0 | L110: -65 | M110: 0 | N110: -55 | O110: -375
B111: GastoFijoMensual : Alquiler | C111: -820 | D111: -820 | E111: -820 | F111: -820 | G111: -820 | H111: -820 | I111: -820 | J111: -820 | K111: -820 | L111: -820 | M111: -820 | N111: -820 | O111: -9840
... B138: Total | C138: 4725 | D138: 315 | E138: 250 | F138: 1460 | G138: -40 | H138: -30 | I138: 385 | J138: -145 | K138: -1850 | L138: 1310 | M138: -120 | N138: -1470 | O138: 4790
B140: 2022
B141: Categoría ▾ | C141: Ene | D141: Feb | E141: Mar | F141: Abr | G141: Mayo | H141: Jun | I141: Jul | J141: Ago | K141: Sep | L141: Oct | M141: Nov | N141: Dic | O141: Global
C142: 2022 | D142: 2022 | E142: 2022 | F142: 2022 | G142: 2022 | H142: 2022 | I142: 2022 | J142: 2022 | K142: 2022 | L142: 2022 | M142: 2022 | N142: 2022
B143: Automovil : Combustible | C143: 0 | D143: 0 | E143: -30 | F143: 0 | G143: -30 | H143: 0 | I143: -30 | J143: 0 | K143: -30 | L143: -30 | M143: 0 | N143: -25 | O143: -175
B144: Automovil : Compra/Renting | C144: -300 | D144: -100 | E144: 0 | F144: 0 | G144: 0 | H144: 0 | I144: 0 | J144: 0 | K144: 0 | L144: 0 | M144: 0 | N144: 0 | O144: -400
B145: Automovil : Impuestos | C145: 0 | D145: 0 | E145: 0 | F145: 0 | G145: -70 | H145: 0 | I145: 0 | J145: 0 | K145: 0 | L145: 0 | M145: 0 | N145: 0 | O145: -70
B146: Automovil : Mantenimiento | C146: 0 | D146: -30 | E146: 0 | F146: 0 | G146: 0 | H146: 0 | I146: 0 | J146: 0 | K146: 0 | L146: 0 | M146: 0 | N146: 0 | O146: -30
B147: Automovil : Parking-Peajes | C147: 0 | D147: 0 | E147: -30 | F147: 0 | G147: -10 | H147: 0 | I147: 0 | J147: 0 | K147: 0 | L147: -5 | M147: 0 | N147: 0 | O147: -45
B148: Comida : Dietas | C148: -240 | D148: -255 | E148: -400 | F148: -350 | G148: -350 | H148: -420 | I148: -300 | J148: -195 | K148: -190 | L148: -400 | M148: -265 | N148: -475 | O148: -3840
B149: Deporte : Gimnasio | C149: -65 | D149: 0 | E149: 0 | F149: -65 | G149: 0 | H149: 0 | I149: -65 | J149: 0 | K149: 0 | L149: -65 | M149: 0 | N149: 0 | O149: -260
B150: Deporte : Ropa | C150: 0 | D150: 0 | E150: 0 | F150: 0 | G150: 0 | H150: 0 | I150: -25 | J150: 0 | K150: 0 | L150: 0 | M150: 0 | N150: 0 | O150: -25
B151: Formacion-Cultura : Papeleria | C151: 0 | D151: 0 | E151: 0 | F151: 0 | G151: 0 | H151: 0 | I151: 0 | J151: 0 | K151: 0 | L151: 0 | M151: -5 | N151: 0 | O151: -5
B152: GastoFijoMensual : Agua | C152: 0 | D152: -60 | E152: 0 | F152: -60 | G152: 0 | H152: -55 | I152: 0 | J152: -55 | K152: 0 | L152: -55 | M152: 0 | N152: -55 | O152: -340
B153: GastoFijoMensual : Alquiler | C153: -820 | D153: -820 | E153: -820 | F153: -820 | G153: -820 | H153: -820 | I153: -820 | J153: -820 | K153: -820 | L153: -820 | M153: -870 | N153: -870 | O153: -9940
B154: GastoFijoMensual : Electricidad | C154: 0 | D154: -105 | E154: 0 | F154: -105 | G154: 0 | H154: -110 | I154: 0 | J154: -115 | K154: 0 | L154: -115 | M154: 0 | N154: -115 | O154: -665
... B179: Total | C179: 40 | D179: -4585 | E179: 10 | F179: 7070 | G179: -51 | H179: -220 | I179: 985 | J179: -1491 | K179: -2820 | L179: 435 | M179: -365 | N179: -350 | O179: -1342
